Workbook

Sheet Depo
B1: Statement I : Payment Banks : Deposits/Investments/Advances
B2: As on March 31 | D2: (₹ Crore)
B3: Sr. No. | C3: Banks | D3: Deposits | G3: Investments | J3: Total Assets
D4: 2023 | E4: 2024 | F4: 2025 | G4: 2023 | H4: 2024 | I4: 2025 | J4: 2023 | K4: 2024 | L4: 2025
B5: 1 | C5: Airtel Payments Bank Ltd. | D5: 1678.95 | E5: 2630.54 | F5: 3418.06 | G5: 1631.27 | H5: 2623.76 | I5: 3293.99 | J5: 3026.45 | K5: 4697.6 | L5: 7511.08
B6: 2 | C6: Fino Payments Bank Ltd. | D6: 917.147 | E6: 1412.54 | F6: 1939.44 | G6: 1146.43 | H6: 1746.93 | I6: 2388.13 | J6: 2466.4 | K6: 3419.11 | L6: 4205.93
B7: 3 | C7: India Post Payments Bank Ltd. | D7: 6292.36 | E7: 11552.19 | F7: 19345.24 | G7: 4599.1846 | H7: 8839.4593 | I7: 16536.79 | J7: 7620.72 | K7: 13662.76 | L7: 22907.27
B8: 4 | C8: Jio Payments Bank Ltd. | D8: 26.97 | E8: 87.96 | F8: 295.23 | G8: 198.32 | H8: 190.8 | I8: 336.04 | J8: 212.8 | K8: 224.9 | L8: 523.87
B9: 5 | C9: NSDL Payment Bank Ltd. | D9: 21.73 | E9: 59.34 | F9: 178.87 | G9: 144.15 | H9: 149.88 | I9: 255.52 | J9: 391.92 | K9: 333.12 | L9: 515.57
B10: 6 | C10: Paytm Payments Bank Ltd. | D10: 3285.27 | E10: 588.56 | F10: 429 | G10: 4687.34 | H10: 1075.7763 | I10: 1226 | J10: 9843.89 | K10: 2866 | L10: 1919
C11: TOTAL OF PAYMENT BANKS | D11: =SUM(D5:D10) -> 12222.427 | E11: =SUM(E5:E10) -> 16331.13 | F11: =SUM(F5:F10) -> 25605.84 | G11: =SUM(G5:G10) -> 12406.695 | H11: =SUM(H5:H10) -> 14626.606 | I11: =SUM(I5:I10) -> 24036.47 | J11: =SUM(J5:J10) -> 23562.18 | K11: =SUM(K5:K10) -> 25203.49 | L11: =SUM(L5:L10) -> 37582.72
B13: 1

Sheet Income
B1: Statement II : Payment Banks : Income
B2: As on March 31 | D2: (₹ Crore)
B3: Sr. No. | C3: Banks | D3: Interest Income | G3: Other Income | J3: Total Income
D4: 2023 | E4: 2024 | F4: 2025 | G4: 2023 | H4: 2024 | I4: 2025 | J4: 2023 | K4: 2024 | L4: 2025
B5: 1 | C5: Airtel Payments Bank Ltd. | D5: 96.13 | E5: 165.11 | F5: 252.71 | G5: 1194.95 | H5: 1670.69 | I5: 2455.92 | J5: 1291.08 | K5: 1835.8 | L5: 2708.63 | N5: =D5+G5-J5 -> 0 | O5: =E5+H5-K5 -> 0 | P5: =F5+I5-L5 -> 0
B6: 2 | C6: Fino Payments Bank Ltd. | D6: 94.8649 | E6: 150.05 | F6: 195.23 | G6: 1135.05 | H6: 1328.34 | I6: 1651.87 | J6: 1229.91 | K6: 1478.38 | L6: 1847.1 | N6: =D6+G6-J6 -> 0.0049 | O6: =E6+H6-K6 -> 0.01 | P6: =F6+I6-L6 -> 0
B7: 3 | C7: India Post Payments Bank Ltd. | D7: 279.05 | E7: 607.58 | F7: 1122.85 | G7: 487.098 | H7: 657.715 | I7: 1025.27 | J7: 766.15 | K7: 1265.2909 | L7: 2148.12 | N7: =D7+G7-J7 -> -0.002 | O7: =E7+H7-K7 -> 0.0041 | P7: =F7+I7-L7 -> 0
B8: 4 | C8: Jio Payments Bank Ltd. | D8: 7.93 | E8: 13.07 | F8: 20.53 | G8: 5.94 | H8: 18.25 | I8: 17.71 | J8: 13.8633 | K8: 31.32 | L8: 38.23 | N8: =D8+G8-J8 -> 0.0067 | O8: =E8+H8-K8 -> 0 | P8: =F8+I8-L8 -> 0.01
B9: 5 | C9: NSDL Payment Bank Ltd. | D9: 8.8992 | E9: 11.75 | F9: 18.22 | G9: 532.3059 | H9: 707.94 | I9: 703.36 | J9: 541.21 | K9: 719.69 | L9: 721.58 | N9: =D9+G9-J9 -> -0.0049 | O9: =E9+H9-K9 -> 0 | P9: =F9+I9-L9 -> 0
B10: 6 | C10: Paytm Payments Bank Ltd. | D10: 390.23 | E10: 493.39 | F10: 124 | G10: 2288.01 | H10: 2028.76 | I10: 110 | J10: 2678.24 | K10: 2522.15 | L10: 234 | N10: =D10+G10-J10 -> 0 | O10: =E10+H10-K10 -> 0 | P10: =F10+I10-L10 -> 0
C11: TOTAL OF PAYMENT BANKS | D11: =SUM(D5:D10) -> 877.1041 | E11: =SUM(E5:E10) -> 1440.95 | F11: =SUM(F5:F10) -> 1733.54 | G11: =SUM(G5:G10) -> 5643.3539 | H11: =SUM(H5:H10) -> 6411.695 | I11: =SUM(I5:I10) -> 5964.13 | J11: =SUM(J5:J10) -> 6520.4533 | K11: =SUM(K5:K10) -> 7852.6309 | L11: =SUM(L5:L10) -> 7697.66 | N11: =D11+G11-J11 -> 0.0047 | O11: =E11+H11-K11 -> 0.0141 | P11: =F11+I11-L11 -> 0.01
B13: 2
E15: =(E11-D11)/D11*100 -> 64.284946 | F15: =(F11-E11)/E11*100 -> 20.305354 | H15: =(H11-G11)/G11*100 -> 13.614973 | I15: =(I11-H11)/H11*100 -> -6.9804474 | K15: =(K11-J11)/J11*100 -> 20.430751 | L15: =(L11-K11)/K11*100 -> -1.9734902

Sheet Exps.
B1: Statement III : Payment Banks : Expenditure
B2: As on March 31 | D2: (₹ Crore)
B3: Sr. No. | C3: Banks | D3: Interest Expended | G3: Operating Expenses | J3: Total Expenditure *
D4: 2023 | E4: 2024 | F4: 2025 | G4: 2023 | H4: 2024 | I4: 2025 | J4: 2023 | K4: 2024 | L4: 2025
B5: 1 | C5: Airtel Payments Bank Ltd. | D5: 31.94 | E5: 43.91 | F5: 61.84 | G5: 1231.26 | H5: 1744.81 | I5: 2604.23 | J5: =D5+G5 -> 1263.2 | K5: =E5+H5 -> 1788.72 | L5: 2666.06 | N5: =D5+G5-J5 -> 0 | O5: =E5+H5-K5 -> 0 | P5: =F5+I5-L5 -> 0.01
B6: 2 | C6: Fino Payments Bank Ltd. | D6: 47.37 | E6: 78.9 | F6: 100.58 | G6: 1117.46 | H6: 1312.62 | I6: 1638.17 | J6: 1164.83 | K6: 1391.52 | L6: 1738.75 | N6: =D6+G6-J6 -> 0 | O6: =E6+H6-K6 -> 0 | P6: =F6+I6-L6 -> 0
B7: 3 | C7: India Post Payments Bank Ltd. | D7: 94.02 | E7: 169.736 | F7: 366.67 | G7: 646.14 | H7: 1003.68 | I7: 1513.04 | J7: =G7+D7 -> 740.16 | K7: 1173.42 | L7: 1879.71 | N7: =D7+G7-J7 -> 0 | O7: =E7+H7-K7 -> -0.004 | P7: =F7+I7-L7 -> 0
B8: 4 | C8: Jio Payments Bank Ltd. | D8: 0.7 | E8: 1.49 | F8: 7.39 | G8: 57.63 | H8: 88.35 | I8: 134.69 | J8: 58.33 | K8: 89.84 | L8: 142.09 | N8: =D8+G8-J8 -> 0 | O8: =E8+H8-K8 -> 0 | P8: =F8+I8-L8 -> -0.01
B9: 5 | C9: NSDL Payment Bank Ltd. | D9: 0.37 | E9: 0.83 | F9: 3.13 | G9: 531.5 | H9: 716.86 | I9: 716.71 | J9: 531.87 | K9: 717.69 | L9: 719.84 | N9: =D9+G9-J9 -> 0 | O9: =E9+H9-K9 -> 0 | P9: =F9+I9-L9 -> 0
B10: 6 | C10: Paytm Payments Bank Ltd. | D10: 72.36 | E10: 60.66 | F10: 8 | G10: 2583.75 | H10: 2572.82 | I10: 315 | J10: 2656.11 | K10: 2633.48 | L10: 323 | N10: =D10+G10-J10 -> 0 | O10: =E10+H10-K10 -> 0 | P10: =F10+I10-L10 -> 0
C11: TOTAL OF PAYMENT BANKS | D11: =SUM(D5:D10) -> 246.76 | E11: =SUM(E5:E10) -> 355.526 | F11: =SUM(F5:F10) -> 547.61 | G11: =SUM(G5:G10) -> 6167.74 | H11: =SUM(H5:H10) -> 7439.14 | I11: =SUM(I5:I10) -> 6921.84 | J11: =SUM(J5:J10) -> 6414.5 | K11: =SUM(K5:K10) -> 7794.67 | L11: =SUM(L5:L10) -> 7469.45 | N11: =D11+G11-J11 -> 0 | O11: =E11+H11-K11 -> -0.004 | P11: =F11+I11-L11 -> 0
B13: * Excludes Provisions & Contingencies.
B15: 3

Sheet Profit
B1: Statement IV : Payment Banks : Profit
B2: As on March 31 | D2: (₹ Crore)
B3: Sr. No. | C3: Banks | D3: Operating Profit | G3: Provisions & Contingencies | J3: Net Profit
D4: 2023 | E4: 2024 | F4: 2025 | G4: 2023 | H4: 2024 | I4: 2025 | J4: 2023 | K4: 2024 | L4: 2025
B5: 1 | C5: Airtel Payments Bank Ltd. | D5: 27.89 | E5: 47.08 | F5: 42.57 | G5: 6.25 | H5: 12.57 | I5: -20.03 | J5: 21.64 | K5: 34.51 | L5: 62.6 | N5: =Income!J5-Exps.!J5-D5 -> -0.01 | O5: =Income!K5-Exps.!K5-E5 -> -7.1054274e-14 | P5: =Income!L5-Exps.!L5-F5 -> 1.6342483e-13 | Q5: =D5-G5-J5 -> 0 | R5: =E5-H5-K5 -> 0 | S5: =F5-I5-L5 -> 0 | U5: =Income!J5-Exps.!D5-Exps.!G5-D5 -> -0.01 | V5: =Income!K5-Exps.!E5-Exps.!H5-E5 -> -7.1054274e-14 | W5: =Income!L5-Exps.!F5-Exps.!I5-F5 -> -0.01 | Y5: =Income!J5-Exps.!J5-Profit!G5 -> 21.63 | Z5: =Income!K5-Exps.!K5-Profit!H5 -> 34.51 | AA5: =Income!L5-Exps.!L5-Profit!I5 -> 62.6 | AB5: =Y5-J5 -> -0.01 | AC5: =Z5-K5 -> -7.1054274e-14 | AD5: =AA5-L5 -> 1.6342483e-13
B6: 2 | C6: Fino Payments Bank Ltd. | D6: 65.09 | E6: 86.86 | F6: 108.35 | G6: 0 | H6: 0.64 | I6: 15.82 | J6: 65.09 | K6: 86.22 | L6: 92.53 | N6: =Income!J6-Exps.!J6-D6 -> -0.01 | O6: =Income!K6-Exps.!K6-E6 -> 1.2789769e-13 | P6: =Income!L6-Exps.!L6-F6 -> 0 | Q6: =D6-G6-J6 -> 0 | R6: =E6-H6-K6 -> 0 | S6: =F6-I6-L6 -> 0 | U6: =Income!J6-Exps.!D6-Exps.!G6-D6 -> -0.01 | V6: =Income!K6-Exps.!E6-Exps.!H6-E6 -> 1.2789769e-13 | W6: =Income!L6-Exps.!F6-Exps.!I6-F6 -> 0 | Y6: =Income!J6-Exps.!J6-Profit!G6 -> 65.08 | Z6: =Income!K6-Exps.!K6-Profit!H6 -> 86.22 | AA6: =Income!L6-Exps.!L6-Profit!I6 -> 92.53 | AB6: =Y6-J6 -> -0.01 | AC6: =Z6-K6 -> 1.2789769e-13 | AD6: =AA6-L6 -> 0
B7: 3 | C7: India Post Payments Bank Ltd. | D7: 25.99 | E7: 91.87 | F7: 268.41 | G7: 5.83 | H7: 57.6348 | I7: 134.56 | J7: 20.16 | K7: 34.24 | L7: 133.85 | N7: =Income!J7-Exps.!J7-D7 -> 0 | O7: =Income!K7-Exps.!K7-E7 -> 0.0009 | P7: =Income!L7-Exps.!L7-F7 -> 0 | Q7: =D7-G7-J7 -> 0 | R7: =E7-H7-K7 -> -0.0048 | S7: =F7-I7-L7 -> 0 | U7: =Income!J7-Exps.!D7-Exps.!G7-D7 -> 0 | V7: =Income!K7-Exps.!E7-Exps.!H7-E7 -> 0.0049 | W7: =Income!L7-Exps.!F7-Exps.!I7-F7 -> 0 | Y7: =Income!J7-Exps.!J7-Profit!G7 -> 20.16 | Z7: =Income!K7-Exps.!K7-Profit!H7 -> 34.2361 | AA7: =Income!L7-Exps.!L7-Profit!I7 -> 133.85 | AB7: =Y7-J7 -> 0 | AC7: =Z7-K7 -> -0.0039 | AD7: =AA7-L7 -> 0
B8: 4 | C8: Jio Payments Bank Ltd. | D8: -44.47 | E8: -58.52 | F8: -103.86 | G8: 0 | H8: 0 | I8: 0 | J8: -44.47 | K8: -58.52 | L8: -103.86 | N8: =Income!J8-Exps.!J8-D8 -> 0.0033 | O8: =Income!K8-Exps.!K8-E8 -> 0 | P8: =Income!L8-Exps.!L8-F8 -> 0 | Q8: =D8-G8-J8 -> 0 | R8: =E8-H8-K8 -> 0 | S8: =F8-I8-L8 -> 0 | U8: =Income!J8-Exps.!D8-Exps.!G8-D8 -> 0.0033 | V8: =Income!K8-Exps.!E8-Exps.!H8-E8 -> 0 | W8: =Income!L8-Exps.!F8-Exps.!I8-F8 -> 0.01 | Y8: =Income!J8-Exps.!J8-Profit!G8 -> -44.4667 | Z8: =Income!K8-Exps.!K8-Profit!H8 -> -58.52 | AA8: =Income!L8-Exps.!L8-Profit!I8 -> -103.86 | AB8: =Y8-J8 -> 0.0033 | AC8: =Z8-K8 -> 0 | AD8: =AA8-L8 -> 0
B9: 5 | C9: NSDL Payment Bank Ltd. | D9: 9.33 | E9: 2 | F9: 1.74 | G9: 1.24 | H9: 0.29 | I9: -0.06 | J9: 8.09 | K9: 1.71 | L9: 1.8 | N9: =Income!J9-Exps.!J9-D9 -> 0.01 | O9: =Income!K9-Exps.!K9-E9 -> 0 | P9: =Income!L9-Exps.!L9-F9 -> 9.1038288e-15 | Q9: =D9-G9-J9 -> 0 | R9: =E9-H9-K9 -> 0 | S9: =F9-I9-L9 -> 0 | U9: =Income!J9-Exps.!D9-Exps.!G9-D9 -> 0.01 | V9: =Income!K9-Exps.!E9-Exps.!H9-E9 -> 0 | W9: =Income!L9-Exps.!F9-Exps.!I9-F9 -> 9.1038288e-15 | Y9: =Income!J9-Exps.!J9-Profit!G9 -> 8.1 | Z9: =Income!K9-Exps.!K9-Profit!H9 -> 1.71 | AA9: =Income!L9-Exps.!L9-Profit!I9 -> 1.8 | AB9: =Y9-J9 -> 0.01 | AC9: =Z9-K9 -> 0 | AD9: =AA9-L9 -> 9.1038288e-15
B10: 6 | C10: Paytm Payments Bank Ltd. | D10: 22.12 | E10: -111.33 | F10: -89 | G10: 7.5843 | H10: 44.83 | I10: 5 | J10: 14.54 | K10: -156.1618 | L10: -94 | N10: =Income!J10-Exps.!J10-D10 -> 0.01 | O10: =Income!K10-Exps.!K10-E10 -> 0 | P10: =Income!L10-Exps.!L10-F10 -> 0 | Q10: =D10-G10-J10 -> -0.0043 | R10: =E10-H10-K10 -> 0.0018 | S10: =F10-I10-L10 -> 0 | U10: =Income!J10-Exps.!D10-Exps.!G10-D10 -> 0.01 | V10: =Income!K10-Exps.!E10-Exps.!H10-E10 -> 0 | W10: =Income!L10-Exps.!F10-Exps.!I10-F10 -> 0 | Y10: =Income!J10-Exps.!J10-Profit!G10 -> 14.5457 | Z10: =Income!K10-Exps.!K10-Profit!H10 -> -156.16 | AA10: =Income!L10-Exps.!L10-Profit!I10 -> -94 | AB10: =Y10-J10 -> 0.0057 | AC10: =Z10-K10 -> 0.0018 | AD10: =AA10-L10 -> 0
C11: TOTAL OF PAYMENT BANKS | D11: =SUM(D5:D10) -> 105.95 | E11: =SUM(E5:E10) -> 57.96 | F11: =SUM(F5:F10) -> 228.21 | G11: =SUM(G5:G10) -> 20.9043 | H11: =SUM(H5:H10) -> 115.9648 | I11: =SUM(I5:I10) -> 135.29 | J11: =SUM(J5:J10) -> 85.05 | K11: =SUM(K5:K10) -> -58.0018 | L11: =SUM(L5:L10) -> 92.92 | N11: =Income!J11-Exps.!J11-D11 -> 0.0033 | O11: =Income!K11-Exps.!K11-E11 -> 0.0009 | P11: =Income!L11-Exps.!L11-F11 -> -9.094947e-13 | Q11: =D11-G11-J11 -> -0.0043 | R11: =E11-H11-K11 -> -0.003 | S11: =F11-I11-L11 -> 0 | U11: =Income!J11-Exps.!D11-Exps.!G11-D11 -> 0.0033 | V11: =Income!K11-Exps.!E11-Exps.!H11-E11 -> 0.0049 | W11: =Income!L11-Exps.!F11-Exps.!I11-F11 -> 0 | Y11: =Income!J11-Exps.!J11-Profit!G11 -> 85.049 | Z11: =Income!K11-Exps.!K11-Profit!H11 -> -58.0039 | AA11: =Income!L11-Exps.!L11-Profit!I11 -> 92.92 | AB11: =Y11-J11 -> -0.001 | AC11: =Z11-K11 -> -0.0021 | AD11: =AA11-L11 -> -8.8107299e-13
B13: 4

Sheet Ratio I
B1: Statement V : Payment Banks : Ratios
B2: As on March 31 | D2: (In Per cent)
B3: Sr. No. | C3: Banks | D3: Investment Deposit Ratio | G3: Spread as % to Total Assets | J3: Operating Exp. as % to Total Expenses
D4: 2023 | E4: 2024 | F4: 2025 | G4: 2023 | H4: 2024 | I4: 2025 | J4: 2023 | K4: 2024 | L4: 2025
B5: 1 | C5: Airtel Payments Bank Ltd. | D5: =Depo!G5/Depo!D5*100 -> 97.16013 | E5: =Depo!H5/Depo!E5*100 -> 99.742258 | F5: =Depo!I5/Depo!F5*100 -> 96.370163 | G5: 2.1209668 | H5: 2.5800409 | I5: 2.5411792 | J5: 97.471501 | K5: 97.545172 | L5: 97.680847
B6: 2 | C6: Fino Payments Bank Ltd. | D6: =Depo!G6/Depo!D6*100 -> 124.99959 | E6: =Depo!H6/Depo!E6*100 -> 123.67296 | F6: =Depo!I6/Depo!F6*100 -> 123.13503 | G6: 1.9256771 | H6: 2.0809509 | I6: 2.2503941 | J6: 95.933312 | K6: 94.329941 | L6: 94.215385
B7: 3 | C7: India Post Payments Bank Ltd. | D7: =Depo!G7/Depo!D7*100 -> 73.091568 | E7: =Depo!H7/Depo!E7*100 -> 76.517607 | F7: =Depo!I7/Depo!F7*100 -> 85.482475 | G7: 2.4279858 | H7: 3.2046526 | I7: 3.3010481 | J7: 87.297341 | K7: 85.534591 | L7: 80.493268
B8: 4 | C8: Jio Payments Bank Ltd. | D8: =Depo!G8/Depo!D8*100 -> 735.33556 | E8: =Depo!H8/Depo!E8*100 -> 216.91678 | F8: =Depo!I8/Depo!F8*100 -> 113.82312 | G8: 3.3975564 | H8: 5.1489551 | I8: 2.5082559 | J8: 98.799931 | K8: 98.341496 | L8: 94.792033
B9: 5 | C9: NSDL Payment Bank Ltd. | D9: =Depo!G9/Depo!D9*100 -> 663.36861 | E9: =Depo!H9/Depo!E9*100 -> 252.57836 | F9: =Depo!I9/Depo!F9*100 -> 142.85235 | G9: 2.1762605 | H9: 3.278098 | I9: 2.9268577 | J9: 99.930434 | K9: 99.884351 | L9: 99.565181
B10: 6 | C10: Paytm Payments Bank Ltd. | D10: =Depo!G10/Depo!D10*100 -> 142.67747 | E10: =Depo!H10/Depo!E10*100 -> 182.78108 | F10: =Depo!I10/Depo!F10*100 -> 285.78089 | G10: 3.2291096 | H10: 14.983155 | I10: 6.044815 | J10: 97.275715 | K10: 97.696584 | L10: 97.52322
C11: TOTAL OF PAYMENT BANKS | D11: =Depo!G11/Depo!D11*100 -> 101.50762 | E11: =Depo!H11/Depo!E11*100 -> 89.562728 | F11: =Depo!I11/Depo!F11*100 -> 93.871047 | G11: 2.6752368 | H11: 4.3028669 | I11: 3.1555193 | J11: 96.153091 | K11: 95.438806 | L11: 92.66867
B13: 5

Sheet Ratio II
B1: Statement VI : Payment Banks : Ratios
B2: As on March 31 | D2: (In Per cent) | M2: (₹ Crore) | P2: (₹ Lacs)
B3: Sr. No. | C3: Banks | D3: Operating Exp. as % to Total Expenses | G3: Return on Assets [%] | J3: Capital Adequacy Ratio - Basel III [%] | M3: Business Per Employee | P3: Profit Per Employee
D4: 2023 | E4: 2024 | F4: 2025 | G4: 2023 | H4: 2024 | I4: 2025 | J4: 2023 | K4: 2024 | L4: 2025 | M4: 2023 | N4: 2024 | O4: 2025 | P4: 2023 | Q4: 2024 | R4: 2025
B5: 1 | C5: Airtel Payments Bank Ltd. | D5: =Exps.!G5/Exps.!J5*100 -> 97.471501 | E5: =Exps.!H5/Exps.!K5*100 -> 97.545172 | F5: =Exps.!I5/Exps.!L5*100 -> 97.680847 | G5: 0.87 | H5: 0.99 | I5: 1.2 | J5: 49.1 | K5: 38.31 | L5: 37.95 | M5: 1.34 | N5: 1.86 | O5: 2.01 | P5: 1.72 | Q5: 2.44 | R5: 3.68
B6: 2 | C6: Fino Payments Bank Ltd. | D6: =Exps.!G6/Exps.!J6*100 -> 95.933312 | E6: =Exps.!H6/Exps.!K6*100 -> 94.329941 | F6: =Exps.!I6/Exps.!L6*100 -> 94.215385 | G6: 3.14 | H6: 2.93 | I6: 2.43 | J6: 86.05 | K6: 74.5 | L6: 80.45 | M6: 0.32 | N6: 0.53 | O6: 0.7 | P6: 2.27 | Q6: 3.21 | R6: 3.34
B7: 3 | C7: India Post Payments Bank Ltd. | D7: =Exps.!G7/Exps.!J7*100 -> 87.297341 | E7: =Exps.!H7/Exps.!K7*100 -> 85.534591 | F7: =Exps.!I7/Exps.!L7*100 -> 80.493268 | G7: 0.3 | H7: 0.32 | I7: 0.71 | J7: 56.96 | K7: 54.86 | L7: 49.24 | M7: 3.57 | N7: 6.65 | O7: 10.94 | P7: 1.14 | Q7: 1.97 | R7: 7.57
B8: 4 | C8: Jio Payments Bank Ltd. * # | D8: =Exps.!G8/Exps.!J8*100 -> 98.799931 | E8: =Exps.!H8/Exps.!K8*100 -> 98.341496 | F8: =Exps.!I8/Exps.!L8*100 -> 94.792033 | G8: -26.09 | H8: -28.14 | I8: -26.63 | J8: 3271 | K8: 557 | L8: 436 | M8: 0.149 | N8: 0.4398 | O8: 0.82 | P8: -0.2457 | Q8: -0.2926 | R8: -0.29
B9: 5 | C9: NSDL Payment Bank Ltd. | D9: =Exps.!G9/Exps.!J9*100 -> 99.930434 | E9: =Exps.!H9/Exps.!K9*100 -> 99.884351 | F9: =Exps.!I9/Exps.!L9*100 -> 99.565181 | G9: 2.94 | H9: 0.57 | I9: 0.43 | J9: 305.89 | K9: 234 | L9: 142.53 | M9: 0.19 | N9: 0.39 | O9: 0.89 | P9: 7 | Q9: 1 | R9: 1
B10: 6 | C10: Paytm Payments Bank Ltd. | D10: =Exps.!G10/Exps.!J10*100 -> 97.275715 | E10: =Exps.!H10/Exps.!K10*100 -> 97.696584 | F10: =Exps.!I10/Exps.!L10*100 -> 97.52322 | G10: 0.15 | H10: -1.69 | I10: -4.92 | J10: 28.35 | K10: 122.6 | L10: 151.88 | M10: 1.84 | N10: 1.11 | O10: 0.54 | P10: 0.89 | Q10: -6.89 | R10: -11.33
B12: * For the purpose of computing Return on Assets, denominator represent average of total assets (excluding accumulated losses, if any) as reported to Reserve Bank of India in Form X under Section 27 of the Banking Regulation Act, 1949, during the 12 months of the financial year.
B13: # Bank's RCA (Networth/Risk Weighted Assets) is above 100% because its Risk-Weighted Asset (RWA) (denominator) is very low compared to its Net worth(numerator). This happens because a large portion of Jio Payments Bank(JPB)'s assets such as investments in Government securities, RBI balance and Repo lending carry a 0% risk weight. Consequently, these assets contribute minimally to Risk Weighted Assets(RWA) thereby leading to a much higher RCA.
B15: 6

Sheet Ratio III
B1: Statement VIII : Payment Banks : Ratios
B2: As on March 31 | D2: (Per Cent) | G2: (₹ Crore) | J2: (₹ Lacs)
B3: Sr. No. | C3: Banks | D3: Net NPA as % to Net Advances | G3: Business Per Employee | J3: Profit Per Employee
D4: 2023 | E4: 2024 | F4: 2025 | G4: 2023 | H4: 2024 | I4: 2025 | J4: 2023 | K4: 2024 | L4: 2025
B5: 1 | C5: Airtel Payments Bank Ltd. | D5: 0 | E5: 0 | F5: 0 | G5: 1.34 | H5: 1.86 | I5: 2.01 | J5: 1.72 | K5: 2.44 | L5: 3.68 | N5: PPE given in Cr
B6: 2 | C6: Fino Payments Bank Ltd. | D6: 0 | E6: 0 | F6: 0 | G6: 0.32 | H6: 0.53 | I6: 0.7 | J6: 2.27 | K6: 3.21 | L6: 3.34 | N6: PPE given in Cr
B7: 3 | C7: India Post Payments Bank Ltd. | D7: 0 | E7: 0 | F7: 0 | G7: 3.57 | H7: 6.65 | I7: 10.94 | J7: 1.14 | K7: 1.97 | L7: 7.57
B8: 4 | C8: Jio Payments Bank Ltd. | D8: 0 | E8: 0 | F8: 0 | G8: 0.149 | H8: 0.4398 | I8: 0.82 | J8: -0.2457 | K8: -0.2926 | L8: -0.29
B9: 5 | C9: NSDL Payment Bank Ltd. | D9: 0 | E9: 0 | F9: 0 | G9: 0.19 | H9: 0.39 | I9: 0.89 | J9: 7 | K9: 1 | L9: 1
B10: 6 | C10: Paytm Payments Bank Ltd. | D10: 0 | E10: 0 | F10: 0 | G10: 1.84 | H10: 1.11 | I10: 0.54 | J10: 0.89 | K10: -6.89 | L10: -11.33
C11: TOTAL OF PAYMENT BANKS [II] | D11: 0 | E11: 0 | F11: 0
B13: 8
