Workbook

Sheet depo
B1: Statement I : Foreign Banks in India : Deposits/Investments/Advances
B2: As on March 31 | L2: (₹ Crore)
B3: S. No | C3: Name of the Bank | D3: Deposits | G3: Investments | J3: Advances
D4: 2023 | E4: 2024 | F4: 2025 | G4: 2023 | H4: 2024 | I4: 2025 | J4: 2023 | K4: 2024 | L4: 2025
B5: 1 | C5: AB Bank Ltd. | D5: 132.24 | E5: 221.522 | F5: 248.0446 | G5: 59.67 | H5: 74.2646 | I5: 132.2759 | J5: 54.28 | K5: 68.22 | L5: 73.3726 | N5: =(F5-E5)/E5*100-9.03 -> 2.9428966 | O5: =(I5-H5)/H5*100-14.55 -> 63.564337 | P5: =(L5-K5)/K5*100-13.02 -> -5.467083
B6: 2 | C6: American Express Banking Corporation | D6: 3214.22 | E6: 4116.504 | F6: 5157.5965 | G6: 4095.91 | H6: 4609.907 | I6: 4660.5838 | J6: 3970.78 | K6: 4718.723 | L6: 6194.7637 | N6: =(F6-E6)/E6*100-9.03 -> 16.260696 | O6: =(I6-H6)/H6*100-14.55 -> -13.450698 | P6: =(L6-K6)/K6*100-13.02 -> 18.260512
B7: 3 | C7: Australia & New Zealand Banking Group Ltd. (ANZ) | D7: 6062.31 | E7: 7963.6249 | F7: 8023.8488 | G7: 7575.62 | H7: 17757.725 | I7: 22801.694 | J7: 3169.66 | K7: 3877.756 | L7: 4323.6731 | N7: =(F7-E7)/E7*100-9.03 -> -8.2737627 | O7: =(I7-H7)/H7*100-14.55 -> 13.854366 | P7: =(L7-K7)/K7*100-13.02 -> -1.5206406
B8: 4 | C8: Bank of America NA | D8: 52655.43 | E8: 59855.692 | F8: 66780.086 | G8: 36096.55 | H8: 60159.609 | I8: 79380.948 | J8: 20716.12 | K8: 27437.983 | L8: 34492.26 | N8: =(F8-E8)/E8*100-9.03 -> 2.5384799 | O8: =(I8-H8)/H8*100-14.55 -> 17.400572 | P8: =(L8-K8)/K8*100-13.02 -> 12.689897
B9: 5 | C9: Bank of Bahrain and Kuwait B.S.C. | D9: 2238.27 | E9: 2064.597 | F9: 1897.79 | G9: 533.07 | H9: 529.452 | I9: 600.552 | J9: 1728.86 | K9: 1434.328 | L9: 1415.066 | N9: =(F9-E9)/E9*100-9.03 -> -17.109398 | O9: =(I9-H9)/H9*100-14.55 -> -1.1210206 | P9: =(L9-K9)/K9*100-13.02 -> -14.362929
B10: 6 | C10: Bank of Ceylon | D10: 303.5 | E10: 278.682 | F10: 259.2734 | G10: 67.617 | H10: 71.908 | I10: 82.3795 | J10: 393.91 | K10: 376.6193 | L10: 443.619 | N10: =(F10-E10)/E10*100-9.03 -> -15.994425 | O10: =(I10-H10)/H10*100-14.55 -> 0.012357457 | P10: =(L10-K10)/K10*100-13.02 -> 4.7697681
B11: 7 | C11: Bank of China | D11: 100.479 | E11: 15.7355 | F11: 27.5363 | G11: 142.659 | H11: 144.9151 | I11: 160.4484 | J11: 100 | K11: 80 | L11: 161.6667 | N11: =(F11-E11)/E11*100-9.03 -> 65.964757 | O11: =(I11-H11)/H11*100-14.55 -> -3.8311032 | P11: =(L11-K11)/K11*100-13.02 -> 89.063375
B12: 8 | C12: Bank of Nova Scotia | D12: 45.02 | E12: 32.7 | F12: 20.437 | G12: 594.89 | H12: 592.69 | I12: 1240.5231 | J12: 168.8 | K12: 2.7873 | L12: 2.2414 | N12: =(F12-E12)/E12*100-9.03 -> -46.531529 | O12: =(I12-H12)/H12*100-14.55 -> 94.753869 | P12: =(L12-K12)/K12*100-13.02 -> -32.605262
B13: 9 | C13: Barclays Bank PLC | D13: 12660.3 | E13: 21620.34 | F13: 19668.902 | G13: 29425.5 | H13: 33137.078 | I13: 43828.043 | J13: 9467.11 | K13: 9026.06 | L13: 10416.97 | N13: =(F13-E13)/E13*100-9.03 -> -18.055938 | O13: =(I13-H13)/H13*100-14.55 -> 17.712849 | P13: =(L13-K13)/K13*100-13.02 -> 2.3899386
B14: 10 | C14: BNP Paribas | D14: 18909.06 | E14: 19388.278 | F14: 24790.194 | G14: 28468.81 | H14: 30292.592 | I14: 45782.371 | J14: 11597.88 | K14: 12923.024 | L14: 14354.722 | N14: =(F14-E14)/E14*100-9.03 -> 18.831763 | O14: =(I14-H14)/H14*100-14.55 -> 36.583885 | P14: =(L14-K14)/K14*100-13.02 -> -1.9413353
B15: 11 | C15: Citibank N.A. | D15: 147382.59 | E15: 191625.54 | F15: 199807.29 | G15: 115004.81 | H15: 110758.81 | I15: 132157.33 | J15: 49965.42 | K15: 68307.62 | L15: 72260.24 | N15: =(F15-E15)/E15*100-9.03 -> -4.7603426 | O15: =(I15-H15)/H15*100-14.55 -> 4.7699241 | P15: =(L15-K15)/K15*100-13.02 -> -7.2335006
B16: 12 | C16: Cooperatieve Rabobank U.A. | D16: 149.6 | E16: 0 | F16: 0 | G16: 160.04 | H16: 82.42 | I16: 0 | J16: 225.93 | K16: 0 | L16: 0 | N16: =(F16-E16)/E16*100-9.03 -> #DIV/0! | O16: =(I16-H16)/H16*100-14.55 -> -114.55 | P16: =(L16-K16)/K16*100-13.02 -> #DIV/0!
... B32: 28 | C32: Kookmin Bank | D32: 1862.709 | E32: 1315 | F32: 1802.72 | G32: 1302.02 | H32: 1852.742 | I32: 1901.5737 | J32: 1026.2 | K32: 1023.758 | L32: 1359.909 | N32: =(F32-E32)/E32*100-9.03 -> 28.058973 | O32: =(I32-H32)/H32*100-14.55 -> -11.914355 | P32: =(L32-K32)/K32*100-13.02 -> 19.815006
B33: 29 | C33: Krung Thai Bank Public Company Ltd. # | D33: 0 | E33: - | F33: - | G33: 0 | H33: - | I33: - | J33: 0 | K33: - | L33: - | N33: =(F33-E33)/E33*100-9.03 -> #VALUE! | O33: =(I33-H33)/H33*100-14.55 -> #VALUE! | P33: =(L33-K33)/K33*100-13.02 -> #VALUE!
B34: 30 | C34: Mashreqbank psc | D34: 127.58 | E34: 234.01 | F34: 413.2737 | G34: 367.97 | H34: 253.58 | I34: 389.7749 | J34: 1022.18 | K34: 1131.56 | L34: 2563.0641 | N34: =(F34-E34)/E34*100-9.03 -> 67.575145 | O34: =(I34-H34)/H34*100-14.55 -> 39.158849 | P34: =(L34-K34)/K34*100-13.02 -> 113.48713
B35: 31 | C35: Mizuho Bank Ltd. | D35: 18501.6 | E35: 21817.874 | F35: 28882.376 | G35: 5741.7 | H35: 11826.07 | I35: 22168.011 | J35: 13201.9 | K35: 18170.193 | L35: 20882.219 | N35: =(F35-E35)/E35*100-9.03 -> 23.349423 | O35: =(I35-H35)/H35*100-14.55 -> 72.900358 | P35: =(L35-K35)/K35*100-13.02 -> 1.9056874
B36: 32 | C36: MUFG Bank Ltd | D36: 18880.04 | E36: 22222.148 | F36: 22347.99 | G36: 7502.62 | H36: 11164.91 | I36: 10631.532 | J36: 17368.26 | K36: 18066.02 | L36: 21153.313 | N36: =(F36-E36)/E36*100-9.03 -> -8.4637091 | O36: =(I36-H36)/H36*100-14.55 -> -19.327274 | P36: =(L36-K36)/K36*100-13.02 -> 4.068951
B37: 33 | C37: NatWest Markets PLC | D37: 0 | E37: 0 | F37: 0 | G37: 4366.54 | H37: 4340.2 | I37: 4382.9197 | J37: 0 | K37: 0 | L37: 0 | N37: =(F37-E37)/E37*100-9.03 -> #DIV/0! | O37: =(I37-H37)/H37*100-14.55 -> -13.56572 | P37: =(L37-K37)/K37*100-13.02 -> #DIV/0!
B38: 34 | C38: NongHyup Bank ^^ | D38: - | E38: 0.2756 | F38: 13.4496 | G38: - | H38: 0 | I38: 0 | J38: - | K38: 108 | L38: 138 | N38: =(F38-E38)/E38*100-9.03 -> 4771.0861 | O38: =(I38-H38)/H38*100-14.55 -> #DIV/0! | P38: =(L38-K38)/K38*100-13.02 -> 14.757778
B39: 35 | C39: PT Bank Maybank Indonesia TBK | D39: 34.69 | E39: 48.12 | F39: 118.089 | G39: 68.04 | H39: 126.64 | I39: 122.436 | J39: 158.01 | K39: 193.24 | L39: 275.305 | N39: =(F39-E39)/E39*100-9.03 -> 136.37524 | O39: =(I39-H39)/H39*100-14.55 -> -17.869646 | P39: =(L39-K39)/K39*100-13.02 -> 29.447916
B40: 36 | C40: Qatar National Bank | D40: 802.49 | E40: 1129.49 | F40: 1706.9319 | G40: 335.68 | H40: 359.87 | I40: 530.893 | J40: 608.42 | K40: 979.63 | L40: 1477.2159 | N40: =(F40-E40)/E40*100-9.03 -> 42.094127 | O40: =(I40-H40)/H40*100-14.55 -> 32.97355 | P40: =(L40-K40)/K40*100-13.02 -> 37.773248
B41: 37 | C41: Sberbank | D41: 378.69 | E41: 2124.279 | F41: NA | G41: 1383.13 | H41: 2073.048 | I41: NA | J41: 23.769 | K41: 13.7531 | L41: NA | N41: =(F41-E41)/E41*100-9.03 -> #VALUE! | O41: =(I41-H41)/H41*100-14.55 -> #VALUE! | P41: =(L41-K41)/K41*100-13.02 -> #VALUE!
B42: 38 | C42: SBM Bank (India) Ltd. | D42: 7318.53 | E42: 7112.981 | F42: 7699.4625 | G42: 3692.71 | H42: 3057.383 | I42: 2211.6971 | J42: 4835.93 | K42: 4676.204 | L42: 4653.6277 | N42: =(F42-E42)/E42*100-9.03 -> -0.78477201 | O42: =(I42-H42)/H42*100-14.55 -> -42.21045 | P42: =(L42-K42)/K42*100-13.02 -> -13.502791
B43: 39 | C43: Shinhan Bank | D43: 8626.1 | E43: 10915.343 | F43: 13521.788 | G43: 2983.63 | H43: 2943.263 | I43: 3176.5639 | J43: 7046.74 | K43: 8931.3442 | L43: 10764.613 | N43: =(F43-E43)/E43*100-9.03 -> 14.848729 | O43: =(I43-H43)/H43*100-14.55 -> -6.6233927 | P43: =(L43-K43)/K43*100-13.02 -> 7.5062372
B44: 40 | C44: Societe Generale | D44: 1929.69 | E44: 1655.366 | F44: 2059.5868 | G44: 4956.22 | H44: 5226.27 | I44: 5974.5367 | J44: 1276.32 | K44: 1422.865 | L44: 827.0142 | N44: =(F44-E44)/E44*100-9.03 -> 15.388817 | O44: =(I44-H44)/H44*100-14.55 -> -0.23258624 | P44: =(L44-K44)/K44*100-13.02 -> -54.896833
B45: 41 | C45: Sonali Bank Ltd. | D45: 98.02 | E45: 124.065 | F45: 107.544 | G45: 35.97 | H45: 32.94 | I45: 33.593 | J45: 37.72 | K45: 13.162 | L45: 5.5538 | N45: =(F45-E45)/E45*100-9.03 -> -22.346407 | O45: =(I45-H45)/H45*100-14.55 -> -12.567608 | P45: =(L45-K45)/K45*100-13.02 -> -70.824285
B46: 42 | C46: Standard Chartered Bank | D46: 132582.76 | E46: 144090.46 | F46: 145896.21 | G46: 95344.59 | H46: 110050.83 | I46: 110934.38 | J46: 85879.62 | K46: 87076.27 | L46: 84958.282 | N46: =(F46-E46)/E46*100-9.03 -> -7.7767989 | O46: =(I46-H46)/H46*100-14.55 -> -13.747146 | P46: =(L46-K46)/K46*100-13.02 -> -15.452337
B47: 43 | C47: Sumitomo Mitsui Banking Corporation (SMBC) | D47: 19822.01 | E47: 28605.19 | F47: 30066.453 | G47: 9826.33 | H47: 13064.642 | I47: 12436.903 | J47: 14271.87 | K47: 20513.622 | L47: 22546.112 | N47: =(F47-E47)/E47*100-9.03 -> -3.9216172 | O47: =(I47-H47)/H47*100-14.55 -> -19.354866 | P47: =(L47-K47)/K47*100-13.02 -> -3.1120003
B48: 44 | C48: United Overseas Bank Ltd. | D48: 690.54 | E48: 886.23 | F48: 144.1815 | G48: 234.13 | H48: 406.57 | I48: 401.4136 | J48: 597.89 | K48: 802.896 | L48: 631.825 | N48: =(F48-E48)/E48*100-9.03 -> -92.760916 | O48: =(I48-H48)/H48*100-14.55 -> -15.818269 | P48: =(L48-K48)/K48*100-13.02 -> -34.326745
B49: 45 | C49: Woori Bank | D49: 2800.73 | E49: 2966.943 | F49: 3607.9605 | G49: 1791.91 | H49: 1800.336 | I49: 1701.4484 | J49: 1947.93 | K49: 2593.088 | L49: 2924.502 | N49: =(F49-E49)/E49*100-9.03 -> 12.575318 | O49: =(I49-H49)/H49*100-14.55 -> -20.04273 | P49: =(L49-K49)/K49*100-13.02 -> -0.23933077
B50: Total of Foreign Banks in India | D50: =SUM(D5:D49) -> 855824.95 | E50: =SUM(E5:E49) -> 1008119.3 | F50: =SUM(F5:F49) -> 1099160.8 | G50: =SUM(G5:G49) -> 674077.02 | H50: =SUM(H5:H49) -> 807327.84 | I50: =SUM(I5:I49) -> 924780.73 | J50: =SUM(J5:J49) -> 491029.26 | K50: =SUM(K5:K49) -> 548443.26 | L50: =SUM(L5:L49) -> 619871.67
E52: =SUM(E50-D50)/D50*100 -> 17.795041 | F52: =SUM(F50-E50)/E50*100 -> 9.0308172 | H52: =SUM(H50-G50)/G50*100 -> 19.767892 | I52: =SUM(I50-H50)/H50*100 -> 14.548351 | K52: =SUM(K50-J50)/J50*100 -> 11.692582 | L52: =SUM(L50-K50)/K50*100 -> 13.023847
B53: ! The Name of 'Credit Suisse Bank' has been excluded from second schedule of RBI Act 1934 and name of 'UBS AG' has been included w.e.f. June 4, 2024.
B54: # The 'Krung Thai Bank Public Company Ltd.' has ceased to be a banking company within the meaning of the Banking Regulation Act, 1949 vide Notification dated July 3, 2024, which is published in the Gazette of India (Part III - Section 4) dated 17 to 23 August, 2023.
D55: =(D50-#REF!)/#REF!*100 -> #REF! | G55: =(G50-#REF!)/#REF!*100 -> #REF! | J55: =(J50-#REF!)/#REF!*100 -> #REF!
B56: ^^ NongHyup Bank open branch in India (Mumbai) October, 2023.
D57: =(D50-#REF!)/#REF!*100 -> #REF! | E57: =(E50-D50)/D50*100 -> 17.795041 | G57: =(G50-#REF!)/#REF!*100 -> #REF! | H57: =(H50-G50)/G50*100 -> 19.767892 | J57: =(J50-#REF!)/#REF!*100 -> #REF! | K57: =(K50-J50)/J50*100 -> 11.692582
B58: 1

Sheet assets 
B1: Statement II: Foreign Banks: Assets/Gross NPA/Net NPA
B2: As on March 31 | L2: (₹ Crore)
B3: S.No. | C3: Name of the Bank | D3: Total Assets | G3: Gross NPA | J3: Net NPA
D4: 2023 | E4: 2024 | F4: 2025 | G4: 2023 | H4: 2024 | I4: 2025 | J4: 2023 | K4: 2024 | L4: 2025
B5: 1 | C5: AB Bank Ltd. | D5: 257.88 | E5: 436.387 | F5: 474.746 | G5: 0 | H5: 0 | I5: 0 | J5: 0 | K5: 0 | L5: 0 | N5: =(F5-E5)/E5*100-19.43 -> -10.639866
B6: 2 | C6: American Express Banking Corporation | D6: 9849.68 | E6: 10643.478 | F6: 12243.756 | G6: 288.12 | H6: 261.8794 | I6: 295.2784 | J6: 41.4 | K6: 38.13 | L6: 37.81 | N6: =(F6-E6)/E6*100-19.43 -> -4.3947039
B7: 3 | C7: Australia & New Zealand Banking Group Ltd. (ANZ) | D7: 17969.52 | E7: 27939.11 | F7: 37754.764 | G7: 0 | H7: 0 | I7: 0 | J7: 0 | K7: 0 | L7: 0 | N7: =(F7-E7)/E7*100-19.43 -> 15.702309
B8: 4 | C8: Bank of America NA | D8: 83121.09 | E8: 106784 | F8: 137176.27 | G8: 0 | H8: 0 | I8: 0 | J8: 0 | K8: 0 | L8: 0 | N8: =(F8-E8)/E8*100-19.43 -> 9.0314433
B9: 5 | C9: Bank of Bahrain and Kuwait B.S.C. | D9: 2751.03 | E9: 2558.061 | F9: 2414.761 | G9: 18.35 | H9: 18.39 | I9: 5.18 | J9: 13.39 | K9: 2.89 | L9: 0.09 | N9: =(F9-E9)/E9*100-19.43 -> -25.031899
B10: 6 | C10: Bank of Ceylon | D10: 592.169 | E10: 575.881 | F10: 600.1084 | G10: 48.88 | H10: 48.02 | I10: 35.7 | J10: 16.13 | K10: 12.67 | L10: 8.7 | N10: =(F10-E10)/E10*100-19.43 -> -15.222985
B11: 7 | C11: Bank of China | D11: 461.28 | E11: 379.402 | F11: 400.9255 | G11: 0 | H11: 0 | I11: 0 | J11: 0 | K11: 0 | L11: 0 | N11: =(F11-E11)/E11*100-19.43 -> -13.756994
B12: 8 | C12: Bank of Nova Scotia | D12: 2053.04 | E12: 2097.94 | F12: 2123.758 | G12: 0.36 | H12: 0.36 | I12: 0 | J12: 0 | K12: 0 | L12: 0 | N12: =(F12-E12)/E12*100-19.43 -> -18.199364
B13: 9 | C13: Barclays Bank PLC | D13: 53205.05 | E13: 53910.089 | F13: 70701.872 | G13: 31.56 | H13: 0.1559 | I13: 0 | J13: 0 | K13: 0 | L13: 0 | N13: =(F13-E13)/E13*100-19.43 -> 11.717756
B14: 10 | C14: BNP Paribas | D14: 61632 | E14: 58854.492 | F14: 86112.643 | G14: 0 | H14: 0 | I14: 0 | J14: 0 | K14: 0 | L14: 0 | N14: =(F14-E14)/E14*100-19.43 -> 26.884478
B15: 11 | C15: Citibank N.A. | D15: 217302.18 | E15: 259587.65 | F15: 270544.72 | G15: 207.3 | H15: 196.06 | I15: 104.755 | J15: 0 | K15: 0 | L15: 0 | N15: =(F15-E15)/E15*100-19.43 -> -15.209046
B16: 12 | C16: Cooperatieve Rabobank U.A. | D16: 1383.36 | E16: 1045.586 | F16: 1051.107 | G16: 103.93 | H16: 0 | I16: 0 | J16: 37.93 | K16: 0 | L16: 0 | N16: =(F16-E16)/E16*100-19.43 -> -18.901971
... B32: 28 | C32: Kookmin Bank | D32: 2534.75 | E32: 3066.667 | F32: 3602.8621 | G32: 0 | H32: 0 | I32: 0 | J32: 0 | K32: 0 | L32: 0 | N32: =(F32-E32)/E32*100-19.43 -> -1.9453791
B33: 29 | C33: Krung Thai Bank Public Company Ltd. | D33: 61.45 | E33: - | F33: - | G33: 0 | H33: - | I33: - | J33: 0 | K33: - | L33: - | N33: =(F33-E33)/E33*100-19.43 -> #VALUE!
B34: 30 | C34: Mashreqbank psc | D34: 1476.21 | E34: 1556.48 | F34: 3148.9396 | G34: 0 | H34: 0 | I34: 0 | J34: 0 | K34: 0 | L34: 0 | N34: =(F34-E34)/E34*100-19.43 -> 82.881601
B35: 31 | C35: Mizuho Bank Ltd. | D35: 27984.21 | E35: 36445.5 | F35: 50670.726 | G35: 6.34 | H35: 6.34 | I35: 0 | J35: 0 | K35: 0 | L35: 0 | N35: =(F35-E35)/E35*100-19.43 -> 19.601503
B36: 32 | C36: MUFG Bank Ltd. | D36: 37040.97 | E36: 41292.913 | F36: 45326.588 | G36: 0 | H36: 0 | I36: 0 | J36: 0 | K36: 0 | L36: 0 | N36: =(F36-E36)/E36*100-19.43 -> -9.6615573
B37: 33 | C37: NatWest Markets PLC | D37: 4853.03 | E37: 4717.26 | F37: 4619.508 | G37: 0 | H37: 0 | I37: 0 | J37: 0 | K37: 0 | L37: 0 | N37: =(F37-E37)/E37*100-19.43 -> -21.50222
B38: 34 | C38: NongHyup Bank | D38: - | E38: 329.7237 | F38: 342.8379 | G38: - | H38: 0 | I38: 0 | J38: - | K38: 0 | L38: 0 | N38: =(F38-E38)/E38*100-19.43 -> -15.45267
B39: 35 | C39: PT Bank Maybank Indonesia TBK | D39: 297.42 | E39: 386.02 | F39: 477.421 | G39: 0 | H39: 0 | I39: 0 | J39: 0 | K39: 0 | L39: 0 | N39: =(F39-E39)/E39*100-19.43 -> 4.2477887
B40: 36 | C40: Qatar National Bank | D40: 1169.01 | E40: 1636.71 | F40: 2276.491 | G40: 52.23 | H40: 0 | I40: 0 | J40: 0 | K40: 0 | L40: 0 | N40: =(F40-E40)/E40*100-19.43 -> 19.659454
B41: 37 | C41: Sberbank | D41: 9882.7 | E41: 5633.0484 | F41: NA | G41: 21.87 | H41: 21.87 | I41: NA | J41: 0 | K41: 0 | L41: NA | N41: =(F41-E41)/E41*100-19.43 -> #VALUE!
B42: 38 | C42: SBM Bank (India) Ltd. | D42: 10125.26 | E42: 8945.88 | F42: 9583.247 | G42: 97.48 | H42: 123.63 | I42: 162.92 | J42: 16.59 | K42: 28.66 | L42: 45.94 | N42: =(F42-E42)/E42*100-19.43 -> -12.305301
B43: 39 | C43: Shinhan Bank | D43: 11115 | E43: 13239.964 | F43: 16013.976 | G43: 156.23 | H43: 20.86 | I43: 25.8 | J43: 10.91 | K43: 6.44 | L43: 16.34 | N43: =(F43-E43)/E43*100-19.43 -> 1.5218064
B44: 40 | C44: Societe Generale | D44: 11627.73 | E44: 10074.197 | F44: 9981.0564 | G44: 78.91 | H44: 5.637 | I44: 3.9422 | J44: 0 | K44: 0 | L44: 0 | N44: =(F44-E44)/E44*100-19.43 -> -20.354546
B45: 41 | C45: Sonali Bank Ltd. | D45: 183.01 | E45: 288.548 | F45: 352.9711 | G45: 4.23 | H45: 4.49 | I45: 5.63 | J45: 0 | K45: 0.2 | L45: 0.6863 | N45: =(F45-E45)/E45*100-19.43 -> 2.8966493
B46: 42 | C46: Standard Chartered Bank | D46: 228486.27 | E46: 237130.1 | F46: 258908.5 | G46: 3232.79 | H46: 2674.37 | I46: 2016.5312 | J46: 375.18 | K46: 301.88 | L46: 285.569 | N46: =(F46-E46)/E46*100-19.43 -> -10.245843
B47: 43 | C47: Sumitomo Mitsui Banking Corporation (SMBC) | D47: 34946.51 | E47: 46245.301 | F47: 48166.428 | G47: 0 | H47: 0 | I47: 0 | J47: 0 | K47: 0 | L47: 0 | N47: =(F47-E47)/E47*100-19.43 -> -15.27579
B48: 44 | C48: United Overseas Bank Ltd. | D48: 1594.86 | E48: 1943.32 | F48: 1298.3656 | G48: 55 | H48: 0 | I48: 0 | J48: 0 | K48: 0 | L48: 0 | N48: =(F48-E48)/E48*100-19.43 -> -52.618276
B49: 45 | C49: Woori Bank | D49: 4459.34 | E49: 5749.3575 | F49: 5108.4397 | G49: 7.6 | H49: 65.77 | I49: 0 | J49: 6.46 | K49: 49.33 | L49: 0 | N49: =(F49-E49)/E49*100-19.43 -> -30.577642
B50: Total of Foreign Banks in India | D50: =SUM(D5:D49) -> 1567704 | E50: =SUM(E5:E49) -> 1705694.2 | F50: =SUM(F5:F49) -> 2037082.6 | G50: =SUM(G5:G49) -> 9525.2 | H50: =SUM(H5:H49) -> 6512.6803 | I50: =SUM(I5:I49) -> 5307.5108 | J50: =SUM(J5:J49) -> 1671.75 | K50: =SUM(K5:K49) -> 811.638 | L50: =SUM(L5:L49) -> 775.9202 | N50: =(F50-E50)/E50*100-19.43 -> -0.0016399073
E52: =SUM(E50-D50)/D50*100 -> 8.8020587 | F52: =SUM(F50-E50)/E50*100 -> 19.42836 | H52: =SUM(H50-G50)/G50*100 -> -31.626839 | I52: =SUM(I50-H50)/H50*100 -> -18.504969 | K52: =SUM(K50-J50)/J50*100 -> -51.449798 | L52: =SUM(L50-K50)/K50*100 -> -4.4007057
B53: # Net NPA is after considering ECGC claim, sundries balance and floating provision.
D55: =(D50-#REF!)/#REF!*100 -> #REF! | E55: =(E50-D50)/D50*100 -> 8.8020587 | G55: =(G50-#REF!)/#REF!*100 -> #REF! | H55: =(H50-G50)/G50*100 -> -31.626839 | J55: =(J50-#REF!)/#REF!*100 -> #REF! | K55: =(K50-J50)/J50*100 -> -51.449798
B56: 2

Sheet income 
B1: Statement III : Foreign Banks in India : Income
B2: As on March 31 | L2: (₹ Crore)
B3: S. No. | C3: Name of the Bank | D3: Interest Income | G3: Other Income | J3: Total Income
D4: 2023 | E4: 2024 | F4: 2025 | G4: 2023 | H4: 2024 | I4: 2025 | J4: 2023 | K4: 2024 | L4: 2025
B5: 1 | C5: AB Bank Limited | D5: 8.7 | E5: 14.9429 | F5: 23.5 | G5: 27.28 | H5: 28.4586 | I5: 33.1 | J5: =G5+D5 -> 35.98 | K5: =H5+E5 -> 43.4015 | L5: =I5+F5 -> 56.6 | N5: =(L5-K5)/K5*100-12.3 -> 18.110239
B6: 2 | C6: American Express Banking Corporation | D6: 602.65 | E6: 665.833 | F6: 752.9684 | G6: 1259.39 | H6: 1541.602 | I6: 1917.0689 | J6: =D6+G6 -> 1862.04 | K6: =E6+H6 -> 2207.435 | L6: =F6+I6 -> 2670.0373 | N6: =(L6-K6)/K6*100-12.3 -> 8.6565536
B7: 3 | C7: Australia & New Zealand Banking Group Ltd. (ANZ) | D7: 652.2 | E7: 1243.197 | F7: 1879.9122 | G7: -32.15 | H7: -72.937 | I7: 176.1906 | J7: =D7+G7 -> 620.05 | K7: =E7+H7 -> 1170.26 | L7: =F7+I7 -> 2056.1028 | N7: =(L7-K7)/K7*100-12.3 -> 63.396238
B8: 4 | C8: Bank of America NA | D8: 3729.15 | E8: 5616.671 | F8: 6926.3965 | G8: 278.37 | H8: 743.436 | I8: 1263.2457 | J8: =G8+D8 -> 4007.52 | K8: =H8+E8 -> 6360.107 | L8: =I8+F8 -> 8189.6422 | N8: =(L8-K8)/K8*100-12.3 -> 16.465793
B9: 5 | C9: Bank of Bahrain and Kuwait B.S.C. | D9: 145.86 | E9: 166.948 | F9: 168.299 | G9: 19.19 | H9: 30.502 | I9: 14.9678 | J9: =D9+G9 -> 165.05 | K9: =E9+H9 -> 197.45 | L9: =F9+I9 -> 183.2668 | N9: =(L9-K9)/K9*100-12.3 -> -19.483186
B10: 6 | C10: Bank of Ceylon | D10: 40.929 | E10: 45.085 | F10: 46.05 | G10: 5.35 | H10: 3.76 | I10: 4.0285 | J10: =D10+G10 -> 46.279 | K10: =E10+H10 -> 48.845 | L10: =F10+I10 -> 50.0785 | N10: =(L10-K10)/K10*100-12.3 -> -9.7746648
B11: 7 | C11: Bank of China | D11: 19.666 | E11: 26.421 | F11: 27.0721 | G11: 35.59 | H11: 21.213 | I11: 14.5021 | J11: =D11+G11 -> 55.256 | K11: =E11+H11 -> 47.634 | L11: =F11+I11 -> 41.5742 | N11: =(L11-K11)/K11*100-12.3 -> -25.021585
B12: 8 | C12: Bank of Nova Scotia | D12: 140.74 | E12: 125.56 | F12: 128.7017 | G12: 13.45 | H12: 41.4276 | I12: 31.775 | J12: =G12+D12 -> 154.19 | K12: =E12+H12 -> 166.9876 | L12: =F12+I12 -> 160.4767 | N12: =(L12-K12)/K12*100-12.3 -> -16.199032
B13: 9 | C13: Barclays Bank PLC | D13: 2303.03 | E13: 2926.766 | F13: 3579.2671 | G13: 373.65 | H13: 382.75 | I13: 696.5968 | J13: =D13+G13 -> 2676.68 | K13: =E13+H13 -> 3309.516 | L13: =F13+I13 -> 4275.8639 | N13: =(L13-K13)/K13*100-12.3 -> 16.89907
B14: 10 | C14: BNP Paribas | D14: 2607.61 | E14: 3087.212 | F14: 4037.7316 | G14: 323.49 | H14: 421.756 | I14: 215.291 | J14: =D14+G14 -> 2931.1 | K14: =E14+H14 -> 3508.968 | L14: =F14+I14 -> 4253.0226 | N14: =(L14-K14)/K14*100-12.3 -> 8.9043712
B15: 11 | C15: Citibank N.A. | D15: 14265 | E15: 15411.1 | F15: 17000.01 | G15: 14454.24 | H15: 4625.93 | I15: 5173.316 | J15: =G15+D15 -> 28719.24 | K15: =E15+H15 -> 20037.03 | L15: =F15+I15 -> 22173.326 | N15: =(L15-K15)/K15*100-12.3 -> -1.6382602
B16: 12 | C16: Cooperatieve Rabobank U.A. | D16: 142.16 | E16: 91.691 | F16: 61.407 | G16: 27.02 | H16: 5.08 | I16: 0.9374 | J16: =G16+D16 -> 169.18 | K16: =H16+E16 -> 96.771 | L16: =I16+F16 -> 62.3444 | N16: =(L16-K16)/K16*100-12.3 -> -47.875327
B17: 13 | C17: Credit Agricole Corporate & Investment Bank | D17: 799.48 | E17: 1126.558 | F17: 1376.488 | G17: -52.69 | H17: -52.179 | I17: 25.907 | J17: =G17+D17 -> 746.79 | K17: =H17+E17 -> 1074.379 | L17: =I17+F17 -> 1402.395 | N17: =(L17-K17)/K17*100-12.3 -> 18.230753
B18: 14 | C18: UBS AG (earlier Credit Suisse) | D18: 1394.93 | E18: 871.44 | F18: 398.865 | G18: -69.94 | H18: 13.066 | I18: 26.715 | J18: =D18+G18 -> 1324.99 | K18: =E18+H18 -> 884.506 | L18: =F18+I18 -> 425.58 | N18: =(L18-K18)/K18*100-12.3 -> -64.185007
B19: 15 | C19: CTBC Bank Co. Ltd. | D19: 163.26 | E19: 243.11 | F19: 289.9697 | G19: 14.79 | H19: 29.72 | I19: 30.4161 | J19: =D19+G19 -> 178.05 | K19: =E19+H19 -> 272.83 | L19: =F19+I19 -> 320.3858 | N19: =(L19-K19)/K19*100-12.3 -> 5.1305612
B20: 16 | C20: DBS Bank Ltd. | D20: 5734.893 | E20: 7836.763 | F20: 9295.23 | G20: 969.903 | H20: 1547.177 | I20: 2036.863 | J20: =G20+D20 -> 6704.796 | K20: =H20+E20 -> 9383.94 | L20: =I20+F20 -> 11332.093 | N20: =(L20-K20)/K20*100-12.3 -> 8.4605015
B21: 17 | C21: Deutsche Bank AG | D21: 8517.88 | E21: 9723.088 | F21: 10358.579 | G21: 476.07 | H21: 1510.823 | I21: 2056.55 | J21: =G21+D21 -> 8993.95 | K21: =H21+E21 -> 11233.911 | L21: =I21+F21 -> 12415.129 | N21: =(L21-K21)/K21*100-12.3 -> -1.7852487
B22: 18 | C22: Doha Bank | D22: 72.22 | E22: 85.06 | F22: 101.878 | G22: 45.198 | H22: 16.2 | I22: 11.125 | J22: =D22+G22 -> 117.418 | K22: =H22+E22 -> 101.26 | L22: =I22+F22 -> 113.003 | N22: =(L22-K22)/K22*100-12.3 -> -0.70312068
B23: 19 | C23: Emirates NBD Bank (PJSC) | D23: 289.9 | E23: 538.43 | F23: 642.4709 | G23: 42.63 | H23: 55.88 | I23: 103.1193 | J23: =G23+D23 -> 332.53 | K23: =E23+H23 -> 594.31 | L23: =F23+I23 -> 745.5902 | N23: =(L23-K23)/K23*100-12.3 -> 13.154763
B24: 20 | C24: First Abu Dhabi Bank | D24: 557.36 | E24: 536.235 | F24: 475.526 | G24: -36.14 | H24: -0.22 | I24: 51.307 | J24: =D24+G24 -> 521.22 | K24: =E24+H24 -> 536.015 | L24: =F24+I24 -> 526.833 | N24: =(L24-K24)/K24*100-12.3 -> -14.013012
B25: 21 | C25: FirstRand Bank Ltd. | D25: 17.63 | E25: 21.33 | F25: 21.5306 | G25: 26.15 | H25: 21.637 | I25: 13.1179 | J25: =D25+G25 -> 43.78 | K25: =E25+H25 -> 42.967 | L25: =F25+I25 -> 34.6485 | N25: =(L25-K25)/K25*100-12.3 -> -31.660207
B26: 22 | C26: Hongkong and Shanghai Banking Corpn.Ltd. (HSBC) | D26: 15602.76 | E26: 19962.248 | F26: 23414.08 | G26: 1731.01 | H26: 3952.723 | I26: 4197.4722 | J26: =G26+D26 -> 17333.77 | K26: =H26+E26 -> 23914.971 | L26: =F26+I26 -> 27611.553 | N26: =(L26-K26)/K26*100-12.3 -> 3.1571862
B27: 23 | C27: Industrial Bank of Korea | D27: 44.9 | E27: 60.2 | F27: 64.4656 | G27: 8.48 | H27: 6.14 | I27: 5.4856 | J27: =D27+G27 -> 53.38 | K27: =E27+H27 -> 66.34 | L27: =F27+I27 -> 69.9512 | N27: =(L27-K27)/K27*100-12.3 -> -6.856527
B28: 24 | C28: Industrial & Commercial Bank of China Limited (ICBC) | D28: 219.41 | E28: 324.854 | F28: 369.987 | G28: 11.16 | H28: 37.307 | I28: 34.1899 | J28: =G28+D28 -> 230.57 | K28: =H28+E28 -> 362.161 | L28: =I28+F28 -> 404.1769 | N28: =(L28-K28)/K28*100-12.3 -> -0.69855755
B29: 25 | C29: JPMorgan Chase Bank | D29: 4827.74 | E29: 6739.161 | F29: 8173.9465 | G29: 877.14 | H29: 1357.728 | I29: 2324.6113 | J29: =G29+D29 -> 5704.88 | K29: =H29+E29 -> 8096.889 | L29: =I29+F29 -> 10498.558 | N29: =(L29-K29)/K29*100-12.3 -> 17.361624
B30: 26 | C30: JSC VTB Bank | D30: 10.57 | E30: 40.233 | F30: 109.019 | G30: 9.89 | H30: 53.619 | I30: 84.749 | J30: =D30+G30 -> 20.46 | K30: =E30+H30 -> 93.852 | L30: =F30+I30 -> 193.768 | N30: =(L30-K30)/K30*100-12.3 -> 94.161237
B31: 27 | C31: KEB Hana Bank | D31: 167.45 | E31: 261.391 | F31: 301.038 | G31: 23.7 | H31: 26.678 | I31: 33.8769 | J31: =D31+G31 -> 191.15 | K31: =E31+H31 -> 288.069 | L31: =F31+I31 -> 334.9149 | N31: =(L31-K31)/K31*100-12.3 -> 3.9620414
B32: 28 | C32: Kookmin Bank | D32: 159.12 | E32: 221.93 | F32: 235.1347 | G32: -23.38 | H32: 8.84 | I32: 13.0423 | J32: =G32+D32 -> 135.74 | K32: =H32+E32 -> 230.77 | L32: =I32+F32 -> 248.177 | N32: =(L32-K32)/K32*100-12.3 -> -4.7569918
B33: 29 | C33: Krung Thai Bank Public Company Ltd. | D33: 2.23 | E33: - | F33: - | G33: 0.02 | H33: - | I33: - | J33: =G33+D33 -> 2.25 | K33: - | L33: - | N33: =(L33-K33)/K33*100-12.3 -> #VALUE!
B34: 30 | C34: Mashreqbank psc | D34: 87.08 | E34: 115.998 | F34: 165.1287 | G34: 17.86 | H34: 13.888 | I34: 17.0821 | J34: =G34+D34 -> 104.94 | K34: =H34+E34 -> 129.886 | L34: =I34+F34 -> 182.2108 | N34: =(L34-K34)/K34*100-12.3 -> 27.985173
B35: 31 | C35: Mizuho Bank Ltd. | D35: 1451.36 | E35: 2181.855 | F35: 3301.3425 | G35: 326.36 | H35: 419.461 | I35: 550.0729 | J35: =G35+D35 -> 1777.72 | K35: =H35+E35 -> 2601.316 | L35: =I35+F35 -> 3851.4154 | N35: =(L35-K35)/K35*100-12.3 -> 35.756422
B36: 32 | C36: MUFG Bank Ltd | D36: 1797.524 | E36: 2484.897 | F36: 2795.9549 | G36: 449.41 | H36: 628 | I36: 840.021 | J36: =G36+D36 -> 2246.934 | K36: =H36+E36 -> 3112.897 | L36: =I36+F36 -> 3635.9759 | N36: =(L36-K36)/K36*100-12.3 -> 4.5036045
B37: 33 | C37: NatWest Markets PLC | D37: 190.5 | E37: 272.59 | F37: 264.987 | G37: 0.62 | H37: 0.9589 | I37: 3.776 | J37: =G37+D37 -> 191.12 | K37: =H37+E37 -> 273.5489 | L37: =I37+F37 -> 268.763 | N37: =(L37-K37)/K37*100-12.3 -> -14.049559
B38: 34 | C38: NongHyup Bank | D38: - | E38: 19.96 | F38: 22.83 | G38: - | H38: 0.203 | I38: 0.1571 | J38: - | K38: =H38+E38 -> 20.163 | L38: =I38+F38 -> 22.9871 | N38: =(L38-K38)/K38*100-12.3 -> 1.7063483
B39: 35 | C39: PT Bank Maybank Indonesia TBK | D39: 15.5 | E39: 20.25 | F39: 31.0282 | G39: 5.75 | H39: 12.11 | I39: 19.08 | J39: =G39+D39 -> 21.25 | K39: =H39+E39 -> 32.36 | L39: =I39+F39 -> 50.1082 | N39: =(L39-K39)/K39*100-12.3 -> 42.546106
B40: 36 | C40: Qatar National Bank | D40: 88.67 | E40: 99.46 | F40: 155.465 | G40: 12.17 | H40: 26.05 | I40: 18.1075 | J40: =G40+D40 -> 100.84 | K40: =E40+H40 -> 125.51 | L40: =F40+I40 -> 173.5725 | N40: =(L40-K40)/K40*100-12.3 -> 25.993761
B41: 37 | C41: Sberbank | D41: 191.66 | E41: 674.045 | F41: NA | G41: 520.4 | H41: 758.7574 | I41: NA | J41: =G41+D41 -> 712.06 | K41: =H41+E41 -> 1432.8024 | L41: NA | N41: =(L41-K41)/K41*100-12.3 -> #VALUE!
B42: 38 | C42: SBM Bank (India) Ltd. | D42: 665.67 | E42: 752.932 | F42: 740.8333 | G42: 201.35 | H42: 186.577 | I42: 175.7382 | J42: =G42+D42 -> 867.02 | K42: =H42+E42 -> 939.509 | L42: =I42+F42 -> 916.5715 | N42: =(L42-K42)/K42*100-12.3 -> -14.741435
B43: 39 | C43: Shinhan Bank | D43: 738.28 | E43: 892.513 | F43: 1017.8909 | G43: 86.71 | H43: 70.135 | I43: 80.1332 | J43: =G43+D43 -> 824.99 | K43: =H43+E43 -> 962.648 | L43: =I43+F43 -> 1098.0241 | N43: =(L43-K43)/K43*100-12.3 -> 1.762887
B44: 40 | C44: Societe Generale | D44: 427.3 | E44: 504.2497 | F44: 489.1443 | G44: -5.59 | H44: 91.4205 | I44: 19.4648 | J44: =D44+G44 -> 421.71 | K44: =E44+H44 -> 595.6702 | L44: =F44+I44 -> 508.6091 | N44: =(L44-K44)/K44*100-12.3 -> -26.915655
B45: 41 | C45: Sonali Bank Ltd. | D45: 6.37 | E45: 10.255 | F45: 15.766 | G45: 13.22 | H45: 10.618 | I45: 2.5529 | J45: =G45+D45 -> 19.59 | K45: =H45+E45 -> 20.873 | L45: =I45+F45 -> 18.3189 | N45: =(L45-K45)/K45*100-12.3 -> -24.536382
B46: 42 | C46: Standard Chartered Bank | D46: 12313.63 | E46: 16786.67 | F46: 16930.133 | G46: 2023.58 | H46: 4861.65 | I46: 3007.4561 | J46: =G46+D46 -> 14337.21 | K46: =E46+H46 -> 21648.32 | L46: =F46+I46 -> 19937.589 | N46: =(L46-K46)/K46*100-12.3 -> -20.202372
B47: 43 | C47: Sumitomo Mitsui Banking Corporation (SMBC) | D47: 1723.05 | E47: 2789.005 | F47: 3384.1388 | G47: 279.57 | H47: 311.317 | I47: 383.6289 | J47: =D47+G47 -> 2002.62 | K47: =E47+H47 -> 3100.322 | L47: =F47+I47 -> 3767.7677 | N47: =(L47-K47)/K47*100-12.3 -> 9.2282703
B48: 44 | C48: United Overseas Bank Ltd. | D48: 67.1 | E48: 96.14 | F48: 88.8389 | G48: 10.5 | H48: 10.95 | I48: 10.196 | J48: =G48+D48 -> 77.6 | K48: =H48+E48 -> 107.09 | L48: =I48+F48 -> 99.0349 | N48: =(L48-K48)/K48*100-12.3 -> -19.821804
B49: 45 | C49: Woori Bank | D49: 311.12 | E49: 327.477 | F49: 394.4279 | G49: 36.31 | H49: 33.1316 | I49: 29.8738 | J49: =D49+G49 -> 347.43 | K49: =E49+H49 -> 360.6086 | L49: =F49+I49 -> 424.3017 | N49: =(L49-K49)/K49*100-12.3 -> 5.3626681
B50: Total of Foreign Banks in India | D50: =SUM(D5:D49) -> 83314.242 | E50: =SUM(E5:E49) -> 106041.75 | F50: =SUM(F5:F49) -> 120057.43 | G50: =SUM(G5:G49) -> 24817.081 | H50: =SUM(H5:H49) -> 23793.345 | I50: =SUM(I5:I49) -> 25746.908 | J50: =SUM(J5:J49) -> 108131.32 | K50: =SUM(K5:K49) -> 129835.1 | L50: =SUM(L5:L49) -> 145804.34 | N50: =(L50-K50)/K50*100-12.3 -> -0.00036608098
D52: =(D50-#REF!)/#REF!*100 -> #REF! | G52: =(G50-#REF!)/#REF!*100 -> #REF! | J52: =(J50-#REF!)/#REF!*100 -> #REF!
E53: =SUM(E50-D50)/D50*100 -> 27.279265 | F53: =SUM(F50-E50)/E50*100 -> 13.217132 | H53: =SUM(H50-G50)/G50*100 -> -4.1251282 | I53: =SUM(I50-H50)/H50*100 -> 8.2105447 | K53: =SUM(K50-J50)/J50*100 -> 20.071683 | L53: =SUM(L50-K50)/K50*100 -> 12.299634
B54: 3

Sheet expenditure
B1: Statement IV : Foreign Banks in India : Expenditure
B2: As on March 31 | L2: (₹ Crore)
B3: S.No. | C3: Name of the Bank | D3: Interest Expended | G3: Operating Expenses | J3: Total Expenditure #
D4: 2023 | E4: 2024 | F4: 2025 | G4: 2023 | H4: 2024 | I4: 2025 | J4: 2023 | K4: 2024 | L4: 2025
B5: 1 | C5: AB Bank Ltd. | D5: 0.64 | E5: 0.6689 | F5: 0.3645 | G5: 16.42 | H5: 15.9858 | I5: 21.3953 | J5: =G5+D5 -> 17.06 | K5: =H5+E5 -> 16.6547 | L5: =I5+F5 -> 21.7598
B6: 2 | C6: American Express Banking Corporation | D6: 130.44 | E6: 208.743 | F6: 298.777 | G6: 1617.19 | H6: 1909.365 | I6: 2232.6205 | J6: =G6+D6 -> 1747.63 | K6: =H6+E6 -> 2118.108 | L6: =I6+F6 -> 2531.3975
B7: 3 | C7: Australia & New Zealand Banking Group Ltd. (ANZ) | D7: 278.43 | E7: 774.169 | F7: 1376.6365 | G7: 141.07 | H7: 145.725 | I7: 196.3093 | J7: =G7+D7 -> 419.5 | K7: =H7+E7 -> 919.894 | L7: =I7+F7 -> 1572.9458
B8: 4 | C8: Bank of America NA | D8: 881.97 | E8: 1872.144 | F8: 2857.7788 | G8: 979.01 | H8: 1013.447 | I8: 1102.5726 | J8: =G8+D8 -> 1860.98 | K8: =H8+E8 -> 2885.591 | L8: =I8+F8 -> 3960.3514
B9: 5 | C9: Bank of Bahrain and Kuwait B.S.C. | D9: 93.254 | E9: 115.007 | F9: 113.617 | G9: 43.63 | H9: 49.557 | I9: 47.604 | J9: =D9+G9 -> 136.884 | K9: =E9+H9 -> 164.564 | L9: =F9+I9 -> 161.221
B10: 6 | C10: Bank of Ceylon | D10: 13.769 | E10: 16.35 | F10: 17.7892 | G10: 11.055 | H10: 11.676 | I10: 14.4759 | J10: =D10+G10 -> 24.824 | K10: =E10+H10 -> 28.026 | L10: =F10+I10 -> 32.2651
B11: 7 | C11: Bank of China | D11: 1.94 | E11: 2.9761 | F11: 0.7652 | G11: 34.19 | H11: 39.273 | I11: 36.8862 | J11: =D11+G11 -> 36.13 | K11: =E11+H11 -> 42.2491 | L11: =F11+I11 -> 37.6514
B12: 8 | C12: Bank of Nova Scotia | D12: 45.46 | E12: 1.02 | F12: 1.177 | G12: 124.26 | H12: 77.82 | I12: 72.8078 | J12: =D12+G12 -> 169.72 | K12: =E12+H12 -> 78.84 | L12: =F12+I12 -> 73.9848
B13: 9 | C13: Barclays Bank PLC | D13: 826.38 | E13: 1290.384 | F13: 1781.0558 | G13: 594.74 | H13: 584.807 | I13: 748.0025 | J13: =D13+G13 -> 1421.12 | K13: =E13+H13 -> 1875.191 | L13: =F13+I13 -> 2529.0583
B14: 10 | C14: BNP Paribas | D14: 1416.11 | E14: 1784.249 | F14: 2419.7118 | G14: 633.5 | H14: 652.526 | I14: 768.906 | J14: =D14+G14 -> 2049.61 | K14: =E14+H14 -> 2436.775 | L14: =F14+I14 -> 3188.6178
B15: 11 | C15: Citibank N.A. | D15: 3401.48 | E15: 4554.57 | F15: 5273.32 | G15: 5336.4 | H15: 4268.17 | I15: 6026.997 | J15: =G15+D15 -> 8737.88 | K15: =E15+H15 -> 8822.74 | L15: =F15+I15 -> 11300.317
B16: 12 | C16: Cooperatieve Rabobank U.A. | D16: 36.28 | E16: 2.47 | F16: 0 | G16: 78.64 | H16: 51.778 | I16: 20.872 | J16: =G16+D16 -> 114.92 | K16: =H16+E16 -> 54.248 | L16: =I16+F16 -> 20.872
B17: 13 | C17: Credit Agricole Corporate & Investment Bank | D17: 385.42 | E17: 611.91 | F17: 805.893 | G17: 192.29 | H17: 230.819 | I17: 240.762 | J17: =G17+D17 -> 577.71 | K17: =H17+E17 -> 842.729 | L17: =I17+F17 -> 1046.655
B18: 14 | C18: UBS AG (earlier Credit Suisse) | D18: 760.587 | E18: 420.399 | F18: 79.7726 | G18: 88.44 | H18: 104.483 | I18: 57.929 | J18: =D18+G18 -> 849.027 | K18: =E18+H18 -> 524.882 | L18: =F18+I18 -> 137.7016
B19: 15 | C19: CTBC Bank Co. Ltd. | D19: 93.65 | E19: 135.99 | F19: 167.1366 | G19: 62.45 | H19: 77.02 | I19: 90.1025 | J19: =G19+D19 -> 156.1 | K19: =H19+E19 -> 213.01 | L19: =I19+F19 -> 257.2391
B20: 16 | C20: DBS Bank Ltd. | D20: 3353.45 | E20: 5119.692 | F20: 6177.01 | G20: 2966.88 | H20: 3552.62 | I20: 3857.1 | J20: =G20+D20 -> 6320.33 | K20: =H20+E20 -> 8672.312 | L20: =I20+F20 -> 10034.11
B21: 17 | C21: Deutsche Bank AG | D21: 3416.69 | E21: 3998.14 | F21: 4145.6211 | G21: 2820.99 | H21: 3213.321 | I21: 3182.1963 | J21: =G21+D21 -> 6237.68 | K21: =H21+E21 -> 7211.461 | L21: =I21+F21 -> 7327.8174
B22: 18 | C22: Doha Bank | D22: 29.25 | E22: 42.47 | F22: 59.9 | G22: 41.5 | H22: 36.61 | I22: 36.205 | J22: =G22+D22 -> 70.75 | K22: =E22+H22 -> 79.08 | L22: =F22+I22 -> 96.105
B23: 19 | C23: Emirates NBD Bank (PJSC) | D23: 137.42 | E23: 332.07 | F23: 441.8856 | G23: 105.71 | H23: 133.28 | I23: 158.04 | J23: =G23+D23 -> 243.13 | K23: =E23+H23 -> 465.35 | L23: =F23+I23 -> 599.9256
B24: 20 | C24: First Abu Dhabi Bank | D24: 303.8 | E24: 345.89 | F24: 311 | G24: 88.17 | H24: 91.308 | I24: 105.09 | J24: =D24+G24 -> 391.97 | K24: =E24+H24 -> 437.198 | L24: =F24+I24 -> 416.09
B25: 21 | C25: FirstRand Bank Ltd. | D25: 0 | E25: 0 | F25: 0 | G25: 25.94 | H25: 34.068 | I25: 27.7611 | J25: =D25+G25 -> 25.94 | K25: =E25+H25 -> 34.068 | L25: =F25+I25 -> 27.7611
B26: 22 | C26: Hongkong and Shanghai Banking Corpn.Ltd. (HSBC) | D26: 6113.65 | E26: 8650.233 | F26: 10562.568 | G26: 4750.79 | H26: 5694.529 | I26: 6525.2782 | J26: =G26+D26 -> 10864.44 | K26: =H26+E26 -> 14344.762 | L26: =I26+F26 -> 17087.847
B27: 23 | C27: Industrial Bank of Korea | D27: 5.4 | E27: 11.38 | F27: 12.3879 | G27: 18.28 | H27: 20.717 | I27: 22.3066 | J27: =G27+D27 -> 23.68 | K27: =H27+E27 -> 32.097 | L27: =I27+F27 -> 34.6945
B28: 24 | C28: Industrial & Commercial Bank of China Limited (ICBC) | D28: 147.28 | E28: 223.518 | F28: 228.8908 | G28: 55.66 | H28: 51.236 | I28: 61.1697 | J28: =G28+D28 -> 202.94 | K28: =H28+E28 -> 274.754 | L28: =I28+F28 -> 290.0605
B29: 25 | C29: JPMorgan Chase Bank | D29: 1290.3 | E29: 2469.041 | F29: 3076.3588 | G29: 831.27 | H29: 1005.235 | I29: 1098.6945 | J29: =D29+G29 -> 2121.57 | K29: =E29+H29 -> 3474.276 | L29: =F29+I29 -> 4175.0533
B30: 26 | C30: JSC VTB Bank | D30: 0 | E30: 0 | F30: 0 | G30: 10.18 | H30: 18.507 | I30: 38.522 | J30: =D30+G30 -> 10.18 | K30: =E30+H30 -> 18.507 | L30: =F30+I30 -> 38.522
B31: 27 | C31: KEB Hana Bank | D31: 78.4 | E31: 159.045 | F31: 182.772 | G31: 38.76 | H31: 42.716 | I31: 47.6929 | J31: =D31+G31 -> 117.16 | K31: =E31+H31 -> 201.761 | L31: =F31+I31 -> 230.4649
B32: 28 | C32: Kookmin Bank | D32: 104.1918 | E32: 180.905 | F32: 192.1745 | G32: 27.577 | H32: 30.362 | I32: 52.044 | J32: =G32+D32 -> 131.7688 | K32: =H32+E32 -> 211.267 | L32: =I32+F32 -> 244.2185
B33: 29 | C33: Krung Thai Bank Public Company Ltd. | D33: 0 | E33: - | F33: - | G33: 3.96 | H33: - | I33: - | J33: =G33+D33 -> 3.96 | K33: - | L33: -
B34: 30 | C34: Mashreqbank psc | D34: 2.43 | E34: 5.24 | F34: 47.4505 | G34: 33.8 | H34: 44.84 | I34: 64.1937 | J34: =G34+D34 -> 36.23 | K34: =H34+E34 -> 50.08 | L34: =I34+F34 -> 111.6442
B35: 31 | C35: Mizuho Bank Ltd. | D35: 861.57 | E35: 1273.948 | F35: 2098.1252 | G35: 413.61 | H35: 556.7 | I35: 503.2601 | J35: =G35+D35 -> 1275.18 | K35: =H35+E35 -> 1830.648 | L35: =I35+F35 -> 2601.3853
B36: 32 | C36: MUFG Bank | D36: 930.441 | E36: 1334.746 | F36: 1457.399 | G36: 462.83 | H36: 911.346 | I36: 807.49689 | J36: =G36+D36 -> 1393.271 | K36: =H36+E36 -> 2246.092 | L36: =I36+F36 -> 2264.8959
B37: 33 | C37: NatWest Markets PLC | D37: 101.526 | E37: 165.97 | F37: 167.866 | G37: 78.159 | H37: 31.07 | I37: -72.606 | J37: =D37+G37 -> 179.685 | K37: =E37+H37 -> 197.04 | L37: =F37+I37 -> 95.26
B38: 34 | C38: NongHyup Bank | D38: - | E38: 0.003 | F38: 0.4306 | G38: - | H38: 18.87 | I38: 22.2335 | J38: - | K38: =E38+H38 -> 18.873 | L38: =F38+I38 -> 22.6641
B39: 35 | C39: PT Bank Maybank Indonesia TBK | D39: 2.22 | E39: 3.4 | F39: 7.489 | G39: 17.27 | H39: 20.69 | I39: 23.842 | J39: =G39+D39 -> 19.49 | K39: =H39+E39 -> 24.09 | L39: =I39+F39 -> 31.331
B40: 36 | C40: Qatar National Bank | D40: 64.15 | E40: 70.61 | F40: 110.02 | G40: 34.74 | H40: 40.19 | I40: 45.021 | J40: =D40+G40 -> 98.89 | K40: =H40+E40 -> 110.8 | L40: =I40+F40 -> 155.041
B41: 37 | C41: Sberbank | D41: 1.54 | E41: 0.6753 | F41: NA | G41: 50.21 | H41: 110.8526 | I41: NA | J41: =D41+G41 -> 51.75 | K41: =E41+H41 -> 111.5279 | L41: NA
B42: 38 | C42: SBM Bank (India) Ltd. | D42: 453.39 | E42: 527.545 | F42: 545.0702 | G42: 375.98 | H42: 428.777 | I42: 434.0719 | J42: =D42+G42 -> 829.37 | K42: =E42+H42 -> 956.322 | L42: =F42+I42 -> 979.1421
B43: 39 | C43: Shinhan Bank | D43: 525.53 | E43: 636.564 | F43: 736.4002 | G43: 158.92 | H43: 189.891 | I43: 188.9109 | J43: =D43+G43 -> 684.45 | K43: =E43+H43 -> 826.455 | L43: =F43+I43 -> 925.3111
B44: 40 | C44: Societe Generale | D44: 154.55 | E44: 237.171 | F44: 194.5653 | G44: 173.94 | H44: 196.277 | I44: 189.7944 | J44: =D44+G44 -> 328.49 | K44: =E44+H44 -> 433.448 | L44: =F44+I44 -> 384.3597
B45: 41 | C45: Sonali Bank Ltd. | D45: 2.49 | E45: 2.298 | F45: 1.5825 | G45: 9.18 | H45: 7.403 | I45: 11.6756 | J45: =D45+G45 -> 11.67 | K45: =E45+H45 -> 9.701 | L45: =F45+I45 -> 13.2581
B46: 42 | C46: Standard Chartered Bank | D46: 4105.44 | E46: 7496.76 | F46: 7431.291 | G46: 4032.29 | H46: 8421.43 | I46: 8846.6099 | J46: =D46+G46 -> 8137.73 | K46: =H46+E46 -> 15918.19 | L46: =I46+F46 -> 16277.901
B47: 43 | C47: Sumitomo Mitsui Banking Corporation (SMBC) | D47: 860.13 | E47: 1645.416 | F47: 2148.8229 | G47: 291.12 | H47: 482.698 | I47: 464.0695 | J47: =D47+G47 -> 1151.25 | K47: =E47+H47 -> 2128.114 | L47: =F47+I47 -> 2612.8924
B48: 44 | C48: United Overseas Bank Ltd. | D48: 23.75 | E48: 34.92 | F48: 26.111 | G48: 29.78 | H48: 34.2568 | I48: 35.572 | J48: =D48+G48 -> 53.53 | K48: =E48+H48 -> 69.1768 | L48: =F48+I48 -> 61.683
B49: 45 | C49: Woori Bank | D49: 243.14 | E49: 237.169 | F49: 308.717 | G49: 57.4 | H49: 57.717 | I49: 76.9216 | J49: =D49+G49 -> 300.54 | K49: =E49+H49 -> 294.886 | L49: =F49+I49 -> 385.6386
B50: Total of Foreign Banks in India | D50: =SUM(D5:D49) -> 31677.939 | E50: =SUM(E5:E49) -> 46995.869 | F50: =SUM(F5:F49) -> 55865.705 | G50: =SUM(G5:G49) -> 27958.181 | H50: =SUM(H5:H49) -> 34709.969 | I50: =SUM(I5:I49) -> 38531.41 | J50: =SUM(J5:J49) -> 59636.12 | K50: =SUM(K5:K49) -> 81705.838 | L50: =SUM(L5:L49) -> 94397.114
E52: =SUM(E50-D50)/D50*100 -> 48.355199 | F52: =SUM(F50-E50)/E50*100 -> 18.873649 | H52: =SUM(H50-G50)/G50*100 -> 24.149598 | I52: =SUM(I50-H50)/H50*100 -> 11.009634 | K52: =SUM(K50-J50)/J50*100 -> 37.007302 | L52: =SUM(L50-K50)/K50*100 -> 15.532888
D53: =(D50-#REF!)/#REF!*100 -> #REF! | E53: =(E50-D50)/D50*100 -> 48.355199 | G53: =(G50-#REF!)/#REF!*100 -> #REF! | H53: =(H50-G50)/G50*100 -> 24.149598 | J53: =(J50-#REF!)/#REF!*100 -> #REF! | K53: =(K50-J50)/J50*100 -> 37.007302
B54: # Excluding Provisions.
B56: 4

Sheet Profit
B1: Statement V : Foreign Banks in India : Profit
B2: As on March 31 | L2: (₹ Crore)
B3: S. No. | C3: Name of the Bank | D3: Operating Profit | G3: Provisions & Contingencies | J3: Net Profit
D4: 2023 | E4: 2024 | F4: 2025 | G4: 2023 | H4: 2024 | I4: 2025 | J4: 2023 | K4: 2024 | L4: 2025
B5: 1 | C5: AB Bank Limited | D5: ='income '!J5-expenditure!J5 -> 18.92 | E5: ='income '!K5-expenditure!K5 -> 26.7468 | F5: ='income '!L5-expenditure!L5 -> 34.8402 | G5: 9.92 | H5: 11.5241 | I5: 13.4847 | J5: =D5-G5 -> 9 | K5: =E5-H5 -> 15.2227 | L5: =F5-I5 -> 21.3555
B6: 2 | C6: American Express Banking Corporation | D6: ='income '!J6-expenditure!J6 -> 114.41 | E6: ='income '!K6-expenditure!K6 -> 89.327 | F6: ='income '!L6-expenditure!L6 -> 138.6398 | G6: 43.62 | H6: 23.1 | I6: 125.2471 | J6: =D6-G6 -> 70.79 | K6: =E6-H6 -> 66.227 | L6: =F6-I6 -> 13.3927
B7: 3 | C7: Australia & New Zealand Banking Group Ltd. (ANZ) | D7: ='income '!J7-expenditure!J7 -> 200.55 | E7: ='income '!K7-expenditure!K7 -> 250.366 | F7: ='income '!L7-expenditure!L7 -> 483.157 | G7: 71.89 | H7: 101.812 | I7: 203.7564 | J7: =D7-G7 -> 128.66 | K7: =E7-H7 -> 148.554 | L7: 279.4006
B8: 4 | C8: Bank of America NA | D8: ='income '!J8-expenditure!J8 -> 2146.54 | E8: ='income '!K8-expenditure!K8 -> 3474.516 | F8: ='income '!L8-expenditure!L8 -> 4229.2908 | G8: 986.91 | H8: 1593.098 | I8: 1658.9491 | J8: =D8-G8 -> 1159.63 | K8: =E8-H8 -> 1881.418 | L8: =F8-I8 -> 2570.3417
B9: 5 | C9: Bank of Bahrain and Kuwait B.S.C. | D9: ='income '!J9-expenditure!J9 -> 28.166 | E9: ='income '!K9-expenditure!K9 -> 32.886 | F9: ='income '!L9-expenditure!L9 -> 22.0458 | G9: 11 | H9: 26.99 | I9: 21.709 | J9: =D9-G9 -> 17.166 | K9: =E9-H9 -> 5.896 | L9: 0.3346
B10: 6 | C10: Bank of Ceylon | D10: ='income '!J10-expenditure!J10 -> 21.455 | E10: ='income '!K10-expenditure!K10 -> 20.819 | F10: ='income '!L10-expenditure!L10 -> 17.8134 | G10: 9.6 | H10: 11.799 | I10: 7.5601 | J10: =D10-G10 -> 11.855 | K10: =E10-H10 -> 9.02 | L10: =F10-I10 -> 10.2533
B11: 7 | C11: Bank of China | D11: ='income '!J11-expenditure!J11 -> 19.126 | E11: ='income '!K11-expenditure!K11 -> 5.3849 | F11: ='income '!L11-expenditure!L11 -> 3.9228 | G11: 11.34 | H11: 3.246 | I11: 0.969 | J11: =D11-G11 -> 7.786 | K11: =E11-H11 -> 2.1389 | L11: =F11-I11 -> 2.9538
B12: 8 | C12: Bank of Nova Scotia | D12: ='income '!J12-expenditure!J12 -> -15.53 | E12: ='income '!K12-expenditure!K12 -> 88.1476 | F12: ='income '!L12-expenditure!L12 -> 86.4919 | G12: 6.09 | H12: 22.54 | I12: 43.637 | J12: =D12-G12 -> -21.62 | K12: =E12-H12 -> 65.6076 | L12: =F12-I12 -> 42.8549
B13: 9 | C13: Barclays Bank PLC | D13: ='income '!J13-expenditure!J13 -> 1255.56 | E13: ='income '!K13-expenditure!K13 -> 1434.325 | F13: ='income '!L13-expenditure!L13 -> 1746.8056 | G13: 586.46 | H13: 649.123 | I13: 712.2218 | J13: =D13-G13 -> 669.1 | K13: 785.201 | L13: =F13-I13 -> 1034.5838
B14: 10 | C14: BNP Paribas | D14: ='income '!J14-expenditure!J14 -> 881.49 | E14: ='income '!K14-expenditure!K14 -> 1072.193 | F14: ='income '!L14-expenditure!L14 -> 1064.4048 | G14: 408.1 | H14: 479.141 | I14: 429.1479 | J14: =D14-G14 -> 473.39 | K14: =E14-H14 -> 593.052 | L14: =F14-I14 -> 635.2569
B15: 11 | C15: Citibank N.A. | D15: ='income '!J15-expenditure!J15 -> 19981.36 | E15: ='income '!K15-expenditure!K15 -> 11214.29 | F15: ='income '!L15-expenditure!L15 -> 10873.009 | G15: 6367.62 | H15: 4977.17 | I15: 4680.22 | J15: =D15-G15 -> 13613.74 | K15: =E15-H15 -> 6237.12 | L15: =F15-I15 -> 6192.789
B16: 12 | C16: Cooperatieve Rabobank U.A. | D16: ='income '!J16-expenditure!J16 -> 54.26 | E16: ='income '!K16-expenditure!K16 -> 42.523 | F16: ='income '!L16-expenditure!L16 -> 41.4724 | G16: 13.12 | H16: -20.23 | I16: 23.828 | J16: =D16-G16 -> 41.14 | K16: =E16-H16 -> 62.753 | L16: =F16-I16 -> 17.6444
B17: 13 | C17: Credit Agricole Corporate & Investment Bank | D17: ='income '!J17-expenditure!J17 -> 169.08 | E17: ='income '!K17-expenditure!K17 -> 231.65 | F17: ='income '!L17-expenditure!L17 -> 355.74 | G17: 88.34 | H17: 100.455 | I17: 141.663 | J17: =D17-G17 -> 80.74 | K17: =E17-H17 -> 131.195 | L17: =F17-I17 -> 214.077
B18: 14 | C18: UBS AG (earlier Credit Suisse) | D18: ='income '!J18-expenditure!J18 -> 475.963 | E18: ='income '!K18-expenditure!K18 -> 359.624 | F18: ='income '!L18-expenditure!L18 -> 287.8784 | G18: 216.2 | H18: 162.301 | I18: 114.824 | J18: =D18-G18 -> 259.763 | K18: =E18-H18 -> 197.323 | L18: =F18-I18 -> 173.0544
B19: 15 | C19: CTBC Bank Co. Ltd. | D19: ='income '!J19-expenditure!J19 -> 21.95 | E19: ='income '!K19-expenditure!K19 -> 59.82 | F19: ='income '!L19-expenditure!L19 -> 63.1467 | G19: 11.74 | H19: 26.677 | I19: 30.2672 | J19: =D19-G19 -> 10.21 | K19: =E19-H19 -> 33.143 | L19: =F19-I19 -> 32.8795
B20: 16 | C20: DBS Bank Ltd. | D20: ='income '!J20-expenditure!J20 -> 384.466 | E20: ='income '!K20-expenditure!K20 -> 711.628 | F20: ='income '!L20-expenditure!L20 -> 1297.983 | G20: 156.33 | H20: 334.778 | I20: 613.66 | J20: =D20-G20 -> 228.136 | K20: =E20-H20 -> 376.85 | L20: =F20-I20 -> 684.323
B21: 17 | C21: Deutsche Bank AG | D21: ='income '!J21-expenditure!J21 -> 2756.27 | E21: ='income '!K21-expenditure!K21 -> 4022.45 | F21: ='income '!L21-expenditure!L21 -> 5087.3114 | G21: 1289.38 | H21: 2045.689 | I21: 2017.2957 | J21: =D21-G21 -> 1466.89 | K21: =E21-H21 -> 1976.761 | L21: =F21-I21 -> 3070.0157
B22: 18 | C22: Doha Bank | D22: ='income '!J22-expenditure!J22 -> 46.668 | E22: ='income '!K22-expenditure!K22 -> 22.18 | F22: ='income '!L22-expenditure!L22 -> 16.898 | G22: 11.31 | H22: -6.53 | I22: 3.681 | J22: =D22-G22 -> 35.358 | K22: =E22-H22 -> 28.71 | L22: =F22-I22 -> 13.217
B23: 19 | C23: Emirates NBD Bank (PJSC) | D23: ='income '!J23-expenditure!J23 -> 89.4 | E23: ='income '!K23-expenditure!K23 -> 128.96 | F23: ='income '!L23-expenditure!L23 -> 145.6646 | G23: 48.63 | H23: 54.88 | I23: 61.9728 | J23: =D23-G23 -> 40.77 | K23: =E23-H23 -> 74.08 | L23: =F23-I23 -> 83.6918
B24: 20 | C24: First Abu Dhabi Bank | D24: ='income '!J24-expenditure!J24 -> 129.25 | E24: ='income '!K24-expenditure!K24 -> 98.817 | F24: ='income '!L24-expenditure!L24 -> 110.743 | G24: 159 | H24: -13.869 | I24: 58.93 | J24: =D24-G24 -> -29.75 | K24: =E24-H24 -> 112.686 | L24: =F24-I24 -> 51.813
B25: 21 | C25: FirstRand Bank Ltd. | D25: ='income '!J25-expenditure!J25 -> 17.84 | E25: ='income '!K25-expenditure!K25 -> 8.899 | F25: ='income '!L25-expenditure!L25 -> 6.8874 | G25: 0.61 | H25: 0.54 | I25: 0.637 | J25: =D25-G25 -> 17.23 | K25: =E25-H25 -> 8.359 | L25: =F25-I25 -> 6.2504
B26: 22 | C26: Hongkong and Shanghai Banking Corpn.Ltd. (HSBC) | D26: ='income '!J26-expenditure!J26 -> 6469.33 | E26: ='income '!K26-expenditure!K26 -> 9570.209 | F26: ='income '!L26-expenditure!L26 -> 10523.706 | G26: 3016.39 | H26: 4133.876 | I26: 4346.8454 | J26: =D26-G26 -> 3452.94 | K26: =E26-H26 -> 5436.333 | L26: =F26-I26 -> 6176.8605
B27: 23 | C27: Industrial Bank of Korea | D27: ='income '!J27-expenditure!J27 -> 29.7 | E27: ='income '!K27-expenditure!K27+0.02 -> 34.263 | F27: ='income '!L27-expenditure!L27+0.02 -> 35.2767 | G27: 13.186 | H27: 15.904 | I27: 14.8441 | J27: =D27-G27 -> 16.514 | K27: =E27-H27 -> 18.359 | L27: =F27-I27 -> 20.4326
B28: 24 | C28: Industrial & Commercial Bank of China Limited (ICBC) | D28: ='income '!J28-expenditure!J28 -> 27.63 | E28: ='income '!K28-expenditure!K28 -> 87.407 | F28: ='income '!L28-expenditure!L28 -> 114.1164 | G28: 12.83 | H28: 37.976 | I28: 51.8334 | J28: =D28-G28 -> 14.8 | K28: 49.429 | L28: 62.283
B29: 25 | C29: JPMorgan Chase Bank | D29: ='income '!J29-expenditure!J29 -> 3583.31 | E29: ='income '!K29-expenditure!K29 -> 4622.613 | F29: ='income '!L29-expenditure!L29 -> 6323.5045 | G29: 1650.95 | H29: 2058.887 | I29: 2608.8881 | J29: =D29-G29 -> 1932.36 | K29: =E29-H29 -> 2563.726 | L29: =F29-I29 -> 3714.6164
B30: 26 | C30: JSC VTB Bank | D30: ='income '!J30-expenditure!J30 -> 10.28 | E30: ='income '!K30-expenditure!K30 -> 75.345 | F30: ='income '!L30-expenditure!L30 -> 155.246 | G30: 4.52 | H30: 33.461 | I30: 59.8652 | J30: =D30-G30 -> 5.76 | K30: =E30-H30 -> 41.884 | L30: =F30-I30 -> 95.3808
B31: 27 | C31: KEB Hana Bank | D31: ='income '!J31-expenditure!J31 -> 73.99 | E31: ='income '!K31-expenditure!K31 -> 86.308 | F31: ='income '!L31-expenditure!L31 -> 104.45 | G31: 48.81 | H31: 36.419 | I31: 13.088 | J31: =D31-G31-0.02 -> 25.16 | K31: =E31-H31 -> 49.889 | L31: =F31-I31 -> 91.362
B32: 28 | C32: Kookmin Bank | D32: ='income '!J32-expenditure!J32 -> 3.9712 | E32: ='income '!K32-expenditure!K32 -> 19.503 | F32: ='income '!L32-expenditure!L32 -> 3.9585 | G32: 3.1 | H32: 15.48 | I32: 4.492 | J32: =D32-G32 -> 0.8712 | K32: =E32-H32 -> 4.023 | L32: =F32-I32 -> -0.5335
B33: 29 | C33: Krung Thai Bank Public Company Ltd. | D33: ='income '!J33-expenditure!J33 -> -1.71 | E33: - | F33: - | G33: 0.06 | H33: - | I33: - | J33: =D33-G33 -> -1.77 | K33: - | L33: -
B34: 30 | C34: Mashreqbank psc | D34: ='income '!J34-expenditure!J34 -> 68.71 | E34: ='income '!K34-expenditure!K34 -> 79.806 | F34: ='income '!L34-expenditure!L34 -> 70.5666 | G34: 34.55 | H34: 34.82 | I34: 28.877 | J34: =D34-G34 -> 34.16 | K34: =E34-H34 -> 44.986 | L34: =F34-I34 -> 41.6896
B35: 31 | C35: Mizuho Bank Ltd. | D35: ='income '!J35-expenditure!J35 -> 502.54 | E35: ='income '!K35-expenditure!K35 -> 770.668 | F35: ='income '!L35-expenditure!L35 -> 1250.0301 | G35: 219.56 | H35: 331.281 | I35: 519.9214 | J35: =D35-G35 -> 282.98 | K35: =E35-H35 -> 439.387 | L35: =F35-I35 -> 730.1087
B36: 32 | C36: MUFG Bank | D36: ='income '!J36-expenditure!J36 -> 853.663 | E36: ='income '!K36-expenditure!K36 -> 866.805 | F36: ='income '!L36-expenditure!L36 -> 1371.08 | G36: 345.24 | H36: 464.577 | I36: 654.69 | J36: =D36-G36 -> 508.423 | K36: =E36-H36 -> 402.228 | L36: =F36-I36 -> 716.39001
B37: 33 | C37: NatWest Markets PLC | D37: ='income '!J37-expenditure!J37 -> 11.435 | E37: ='income '!K37-expenditure!K37 -> 76.5089 | F37: ='income '!L37-expenditure!L37 -> 173.503 | G37: 93.486 | H37: 163.18 | I37: 111.885 | J37: =D37-G37 -> -82.051 | K37: =E37-H37 -> -86.6711 | L37: =F37-I37 -> 61.618
B38: 34 | C38: NongHyup Bank | D38: - | E38: ='income '!K38-expenditure!K38 -> 1.29 | F38: ='income '!L38-expenditure!L38 -> 0.323 | G38: - | H38: 1.577 | I38: 0.8992 | J38: - | K38: =E38-H38 -> -0.287 | L38: =F38-I38 -> -0.5762
B39: 35 | C39: PT Bank Maybank Indonesia TBK | D39: ='income '!J39-expenditure!J39 -> 1.76 | E39: ='income '!K39-expenditure!K39 -> 8.27 | F39: ='income '!L39-expenditure!L39 -> 18.7772 | G39: 0.25 | H39: 0.14 | I39: 3.324 | J39: =D39-G39 -> 1.51 | K39: =E39-H39 -> 8.13 | L39: =F39-I39 -> 15.4532
B40: 36 | C40: Qatar National Bank | D40: ='income '!J40-expenditure!J40 -> 1.95 | E40: ='income '!K40-expenditure!K40 -> 14.71 | F40: ='income '!L40-expenditure!L40 -> 18.5315 | G40: 1.86 | H40: 22.28 | I40: 5.6784 | J40: =D40-G40 -> 0.09 | K40: =E40-H40 -> -7.57 | L40: =F40-I40 -> 12.8531
B41: 37 | C41: Sberbank | D41: ='income '!J41-expenditure!J41 -> 660.31 | E41: ='income '!K41-expenditure!K41 -> 1321.2745 | F41: NA | G41: 293.35 | H41: 576.648 | I41: NA | J41: =D41-G41 -> 366.96 | K41: 744.627 | L41: NA
B42: 38 | C42: SBM Bank (India) Ltd. | D42: ='income '!J42-expenditure!J42 -> 37.65 | E42: ='income '!K42-expenditure!K42 -> -16.813 | F42: ='income '!L42-expenditure!L42 -> -62.5706 | G42: 16.83 | H42: 26.434 | I42: 24.6299 | J42: =D42-G42 -> 20.82 | K42: =E42-H42 -> -43.247 | L42: =F42-I42 -> -87.2005
B43: 39 | C43: Shinhan Bank | D43: ='income '!J43-expenditure!J43 -> 140.54 | E43: ='income '!K43-expenditure!K43 -> 136.193 | F43: ='income '!L43-expenditure!L43 -> 172.713 | G43: 72.7 | H43: 80.74 | I43: 72.56 | J43: =D43-G43 -> 67.84 | K43: =E43-H43 -> 55.453 | L43: =F43-I43 -> 100.153
B44: 40 | C44: Societe Generale | D44: ='income '!J44-expenditure!J44 -> 93.22 | E44: ='income '!K44-expenditure!K44 -> 162.2222 | F44: ='income '!L44-expenditure!L44 -> 124.2494 | G44: 43.2355 | H44: 93.138 | I44: 22.4513 | J44: =D44-G44 -> 49.9845 | K44: =E44-H44 -> 69.0842 | L44: =F44-I44 -> 101.7981
B45: 41 | C45: Sonali Bank Ltd. | D45: ='income '!J45-expenditure!J45 -> 7.92 | E45: ='income '!K45-expenditure!K45 -> 11.172 | F45: ='income '!L45-expenditure!L45 -> 5.0608 | G45: 3.43 | H45: 5.007 | I45: 2.4213 | J45: =D45-G45 -> 4.49 | K45: =E45-H45 -> 6.165 | L45: =F45-I45 -> 2.6395
B46: 42 | C46: Standard Chartered Bank | D46: ='income '!J46-expenditure!J46 -> 6199.48 | E46: ='income '!K46-expenditure!K46 -> 5730.13 | F46: ='income '!L46-expenditure!L46 -> 3659.6883 | G46: 1578.09 | H46: 2000.32 | I46: 1787.032 | J46: =D46-G46-0.02 -> 4621.37 | K46: =E46-H46 -> 3729.81 | L46: =F46-I46 -> 1872.6563
B47: 43 | C47: Sumitomo Mitsui Banking Corporation (SMBC) | D47: ='income '!J47-expenditure!J47 -> 851.37 | E47: ='income '!K47-expenditure!K47 -> 972.208 | F47: ='income '!L47-expenditure!L47 -> 1154.8753 | G47: 371.41 | H47: 461.3 | I47: 498.5243 | J47: =D47-G47 -> 479.96 | K47: =E47-H47 -> 510.908 | L47: =F47-I47 -> 656.351
B48: 44 | C48: United Overseas Bank Ltd. | D48: ='income '!J48-expenditure!J48 -> 24.07 | E48: ='income '!K48-expenditure!K48 -> 37.9132 | F48: ='income '!L48-expenditure!L48 -> 37.3519 | G48: 0.4 | H48: 18.767 | I48: 13.4705 | J48: =D48-G48 -> 23.67 | K48: =E48-H48 -> 19.1462 | L48: 23.882
B49: 45 | C49: Woori Bank | D49: ='income '!J49-expenditure!J49 -> 46.89 | E49: ='income '!K49-expenditure!K49 -> 65.7226 | F49: ='income '!L49-expenditure!L49 -> 38.6631 | G49: 20.37 | H49: 47.8066 | I49: 41.1475 | J49: =D49-G49 -> 26.52 | K49: =E49-H49 -> 17.916 | L49: =F49-I49 -> -2.4844
B50: Total of Foreign Banks in India | D50: =SUM(D5:D49) -> 48495.203 | E50: =SUM(E5:E49) -> 48129.281 | F50: =SUM(F5:F49) -> 51407.247 | G50: =SUM(G5:G49) -> 18351.818 | H50: =SUM(H5:H49) -> 21244.253 | I50: =SUM(I5:I49) -> 21851.029 | J50: =SUM(J5:J49) -> 30143.346 | K50: =SUM(K5:K49) -> 26885.025 | L50: =SUM(L5:L49) -> 29556.216
E52: =SUM(E50-D50)/D50*100 -> -0.75455401 | F52: =SUM(F50-E50)/E50*100 -> 6.8107519 | H52: =SUM(H50-G50)/G50*100 -> 15.761029 | I52: =SUM(I50-H50)/H50*100 -> 2.8561894 | K52: =SUM(K50-J50)/J50*100 -> -10.809418 | L52: =SUM(L50-K50)/K50*100 -> 9.9356079
B53: 5
D54: =(D50-#REF!)/#REF!*100 -> #REF! | E54: =(E50-D50)/D50*100 -> -0.75455401 | G54: =(G50-#REF!)/#REF!*100 -> #REF! | H54: =(H50-G50)/G50*100 -> 15.761029 | J54: =(J50-#REF!)/#REF!*100 -> #REF! | K54: =(K50-J50)/J50*100 -> -10.809418

Sheet ratio
B1: Statement VI : Foreign Banks in India : Ratios
B2: As on March 31 | L2: (Per Cent)
B3: S. No. | C3: Name of the Bank | D3: Credit Deposit Ratio | G3: Investment Deposit Ratio | J3: Spread as % of Assets
D4: 2023 | E4: 2024 | F4: 2025 | G4: 2023 | H4: 2024 | I4: 2025 | J4: 2023 | K4: 2024 | L4: 2025
B5: 1 | C5: AB Bank Limited | D5: =depo!J5/depo!D5*100 -> 41.046582 | E5: =depo!K5/depo!E5*100 -> 30.796038 | F5: =depo!L5/depo!F5*100 -> 29.580406 | G5: =depo!G5/depo!D5*100 -> 45.122505 | H5: =depo!H5/depo!E5*100 -> 33.524706 | I5: =depo!I5/depo!F5*100 -> 53.327466 | J5: =('income '!D5-expenditure!D5)/'assets '!D5*100 -> 3.1254847 | K5: =('income '!E5-expenditure!E5)/'assets '!E5*100 -> 3.2709499 | L5: =('income '!F5-expenditure!F5)/'assets '!F5*100 -> 4.8732375
B6: 2 | C6: American Express Banking Corporation | D6: =depo!J6/depo!D6*100 -> 123.5379 | E6: =depo!K6/depo!E6*100 -> 114.62938 | F6: =depo!L6/depo!F6*100 -> 120.10951 | G6: =depo!G6/depo!D6*100 -> 127.43092 | H6: =depo!H6/depo!E6*100 -> 111.98597 | I6: =depo!I6/depo!F6*100 -> 90.363482 | J6: =('income '!D6-expenditure!D6)/'assets '!D6*100 -> 4.7941659 | K6: =('income '!E6-expenditure!E6)/'assets '!E6*100 -> 4.2945549 | L6: =('income '!F6-expenditure!F6)/'assets '!F6*100 -> 3.7095757
B7: 3 | C7: Australia & New Zealand Banking Group Ltd. (ANZ) | D7: =depo!J7/depo!D7*100 -> 52.28469 | E7: =depo!K7/depo!E7*100 -> 48.693353 | F7: =depo!L7/depo!F7*100 -> 53.885276 | G7: =depo!G7/depo!D7*100 -> 124.9626 | H7: =depo!H7/depo!E7*100 -> 222.98545 | I7: =depo!I7/depo!F7*100 -> 284.17403 | J7: =('income '!D7-expenditure!D7)/'assets '!D7*100 -> 2.0800222 | K7: =('income '!E7-expenditure!E7)/'assets '!E7*100 -> 1.6787507 | L7: =('income '!F7-expenditure!F7)/'assets '!F7*100 -> 1.3330124
B8: 4 | C8: Bank of America NA | D8: =depo!J8/depo!D8*100 -> 39.342799 | E8: =depo!K8/depo!E8*100 -> 45.840224 | F8: =depo!L8/depo!F8*100 -> 51.650518 | G8: =depo!G8/depo!D8*100 -> 68.552379 | H8: =depo!H8/depo!E8*100 -> 100.50775 | I8: =depo!I8/depo!F8*100 -> 118.86919 | J8: =('income '!D8-expenditure!D8)/'assets '!D8*100 -> 3.4253401 | K8: =('income '!E8-expenditure!E8)/'assets '!E8*100 -> 3.5066366 | L8: =('income '!F8-expenditure!F8)/'assets '!F8*100 -> 2.9659777
B9: 5 | C9: Bank of Bahrain and Kuwait B.S.C. | D9: =depo!J9/depo!D9*100 -> 77.240905 | E9: =depo!K9/depo!E9*100 -> 69.472541 | F9: =depo!L9/depo!F9*100 -> 74.563887 | G9: =depo!G9/depo!D9*100 -> 23.816162 | H9: =depo!H9/depo!E9*100 -> 25.644327 | I9: =depo!I9/depo!F9*100 -> 31.644808 | J9: =('income '!D9-expenditure!D9)/'assets '!D9*100 -> 1.9122292 | K9: =('income '!E9-expenditure!E9)/'assets '!E9*100 -> 2.0304832 | L9: =('income '!F9-expenditure!F9)/'assets '!F9*100 -> 2.2644891
B10: 6 | C10: Bank of Ceylon | D10: =depo!J10/depo!D10*100 -> 129.78913 | E10: =depo!K10/depo!E10*100 -> 135.14303 | F10: =depo!L10/depo!F10*100 -> 171.10085 | G10: =depo!G10/depo!D10*100 -> 22.279077 | H10: =depo!H10/depo!E10*100 -> 25.802886 | I10: =depo!I10/depo!F10*100 -> 31.773217 | J10: =('income '!D10-expenditure!D10)/'assets '!D10*100 -> 4.5865285 | K10: =('income '!E10-expenditure!E10)/'assets '!E10*100 -> 4.9897461 | L10: =('income '!F10-expenditure!F10)/'assets '!F10*100 -> 4.7092825
B11: 7 | C11: Bank of China | D11: =depo!J11/depo!D11*100 -> 99.523283 | E11: =depo!K11/depo!E11*100 -> 508.40456 | F11: =depo!L11/depo!F11*100 -> 587.10393 | G11: =depo!G11/depo!D11*100 -> 141.97892 | H11: =depo!H11/depo!E11*100 -> 920.94373 | I11: =depo!I11/depo!F11*100 -> 582.67959 | J11: =('income '!D11-expenditure!D11)/'assets '!D11*100 -> 3.8427853 | K11: =('income '!E11-expenditure!E11)/'assets '!E11*100 -> 6.179435 | L11: =('income '!F11-expenditure!F11)/'assets '!F11*100 -> 6.5615432
B12: 8 | C12: Bank of Nova Scotia | D12: =depo!J12/depo!D12*100 -> 374.94447 | E12: =depo!K12/depo!E12*100 -> 8.5238532 | F12: =depo!L12/depo!F12*100 -> 10.967363 | G12: =depo!G12/depo!D12*100 -> 1321.3905 | H12: =depo!H12/depo!E12*100 -> 1812.5076 | I12: =depo!I12/depo!F12*100 -> 6069.9863 | J12: =('income '!D12-expenditure!D12)/'assets '!D12*100 -> 4.6409227 | K12: =('income '!E12-expenditure!E12)/'assets '!E12*100 -> 5.9362994 | L12: =('income '!F12-expenditure!F12)/'assets '!F12*100 -> 6.0046719
B13: 9 | C13: Barclays Bank PLC | D13: =depo!J13/depo!D13*100 -> 74.777928 | E13: =depo!K13/depo!E13*100 -> 41.748002 | F13: =depo!L13/depo!F13*100 -> 52.961627 | G13: =depo!G13/depo!D13*100 -> 232.4234 | H13: =depo!H13/depo!E13*100 -> 153.26807 | I13: =depo!I13/depo!F13*100 -> 222.82914 | J13: =('income '!D13-expenditure!D13)/'assets '!D13*100 -> 2.7753944 | K13: =('income '!E13-expenditure!E13)/'assets '!E13*100 -> 3.035391 | L13: =('income '!F13-expenditure!F13)/'assets '!F13*100 -> 2.5433716
B14: 10 | C14: BNP Paribas | D14: =depo!J14/depo!D14*100 -> 61.335043 | E14: =depo!K14/depo!E14*100 -> 66.6538 | F14: =depo!L14/depo!F14*100 -> 57.904841 | G14: =depo!G14/depo!D14*100 -> 150.55645 | H14: =depo!H14/depo!E14*100 -> 156.24179 | I14: =depo!I14/depo!F14*100 -> 184.67936 | J14: =('income '!D14-expenditure!D14)/'assets '!D14*100 -> 1.933249 | K14: =('income '!E14-expenditure!E14)/'assets '!E14*100 -> 2.2138718 | L14: =('income '!F14-expenditure!F14)/'assets '!F14*100 -> 1.8789573
B15: 11 | C15: Citibank N.A. | D15: =depo!J15/depo!D15*100 -> 33.901847 | E15: =depo!K15/depo!E15*100 -> 35.646407 | F15: =depo!L15/depo!F15*100 -> 36.164966 | G15: =depo!G15/depo!D15*100 -> 78.031476 | H15: =depo!H15/depo!E15*100 -> 57.799608 | I15: =depo!I15/depo!F15*100 -> 66.142394 | J15: =('income '!D15-expenditure!D15)/'assets '!D15*100 -> 4.9992688 | K15: =('income '!E15-expenditure!E15)/'assets '!E15*100 -> 4.1822213 | L15: =('income '!F15-expenditure!F15)/'assets '!F15*100 -> 4.3344737
B16: 12 | C16: Cooperatieve Rabobank U.A. | D16: =depo!J16/depo!D16*100 -> 151.02273 | E16: 0 | F16: 0 | G16: =depo!G16/depo!D16*100 -> 106.97861 | H16: 0 | I16: 0 | J16: =('income '!D16-expenditure!D16)/'assets '!D16*100 -> 7.6538284 | K16: =('income '!E16-expenditure!E16)/'assets '!E16*100 -> 8.5331097 | L16: =('income '!F16-expenditure!F16)/'assets '!F16*100 -> 5.8421264
B17: 13 | C17: Credit Agricole Corporate & Investment Bank | D17: =depo!J17/depo!D17*100 -> 60.505217 | E17: =depo!K17/depo!E17*100 -> 54.419022 | F17: =depo!L17/depo!F17*100 -> 87.207501 | G17: =depo!G17/depo!D17*100 -> 78.821249 | H17: =depo!H17/depo!E17*100 -> 111.03668 | I17: =depo!I17/depo!F17*100 -> 173.71779 | J17: =('income '!D17-expenditure!D17)/'assets '!D17*100 -> 2.086692 | K17: =('income '!E17-expenditure!E17)/'assets '!E17*100 -> 2.4206224 | L17: =('income '!F17-expenditure!F17)/'assets '!F17*100 -> 1.8146223
B18: 14 | C18: UBS AG (earlier Credit Suisse) | D18: =depo!J18/depo!D18*100 -> 38.737257 | E18: =depo!K18/depo!E18*100 -> 93.26109 | F18: =depo!L18/depo!F18*100 -> 63.909735 | G18: =depo!G18/depo!D18*100 -> 853.41659 | H18: =depo!H18/depo!E18*100 -> 117.65738 | I18: =depo!I18/depo!F18*100 -> 180.62813 | J18: =('income '!D18-expenditure!D18)/'assets '!D18*100 -> 3.4689028 | K18: =('income '!E18-expenditure!E18)/'assets '!E18*100 -> 5.5351426 | L18: =('income '!F18-expenditure!F18)/'assets '!F18*100 -> 4.0997995
B19: 15 | C19: CTBC Bank Co. Ltd. | D19: =depo!J19/depo!D19*100 -> 80.631708 | E19: =depo!K19/depo!E19*100 -> 93.788677 | F19: =depo!L19/depo!F19*100 -> 77.752375 | G19: =depo!G19/depo!D19*100 -> 44.497742 | H19: =depo!H19/depo!E19*100 -> 45.541719 | I19: =depo!I19/depo!F19*100 -> 42.623209 | J19: =('income '!D19-expenditure!D19)/'assets '!D19*100 -> 2.1635482 | K19: =('income '!E19-expenditure!E19)/'assets '!E19*100 -> 3.0537607 | L19: =('income '!F19-expenditure!F19)/'assets '!F19*100 -> 2.5912642
B20: 16 | C20: DBS Bank Ltd. | D20: =depo!J20/depo!D20*100 -> 76.838242 | E20: =depo!K20/depo!E20*100 -> 65.712977 | F20: =depo!L20/depo!F20*100 -> 64.782717 | G20: =depo!G20/depo!D20*100 -> 70.17637 | H20: =depo!H20/depo!E20*100 -> 69.64973 | I20: =depo!I20/depo!F20*100 -> 67.418938 | J20: =('income '!D20-expenditure!D20)/'assets '!D20*100 -> 2.1357699 | K20: =('income '!E20-expenditure!E20)/'assets '!E20*100 -> 2.0827568 | L20: =('income '!F20-expenditure!F20)/'assets '!F20*100 -> 2.228084
B21: 17 | C21: Deutsche Bank AG | D21: =depo!J21/depo!D21*100 -> 81.627431 | E21: =depo!K21/depo!E21*100 -> 78.241249 | F21: =depo!L21/depo!F21*100 -> 72.350067 | G21: =depo!G21/depo!D21*100 -> 66.846944 | H21: =depo!H21/depo!E21*100 -> 76.936272 | I21: =depo!I21/depo!F21*100 -> 67.66167 | J21: =('income '!D21-expenditure!D21)/'assets '!D21*100 -> 3.8691947 | K21: =('income '!E21-expenditure!E21)/'assets '!E21*100 -> 3.9418569 | L21: =('income '!F21-expenditure!F21)/'assets '!F21*100 -> 3.713836
B22: 18 | C22: Doha Bank | D22: =depo!J22/depo!D22*100 -> 77.033564 | E22: =depo!K22/depo!E22*100 -> 77.477969 | F22: =depo!L22/depo!F22*100 -> 82.563458 | G22: =depo!G22/depo!D22*100 -> 45.509212 | H22: =depo!H22/depo!E22*100 -> 46.842913 | I22: =depo!I22/depo!F22*100 -> 35.785113 | J22: =('income '!D22-expenditure!D22)/'assets '!D22*100 -> 3.5810721 | K22: =('income '!E22-expenditure!E22)/'assets '!E22*100 -> 3.2320243 | L22: =('income '!F22-expenditure!F22)/'assets '!F22*100 -> 2.6109781
B23: 19 | C23: Emirates NBD Bank (PJSC) | D23: =depo!J23/depo!D23*100 -> 103.27892 | E23: =depo!K23/depo!E23*100 -> 99.886591 | F23: =depo!L23/depo!F23*100 -> 84.15856 | G23: =depo!G23/depo!D23*100 -> 58.591415 | H23: =depo!H23/depo!E23*100 -> 41.781062 | I23: =depo!I23/depo!F23*100 -> 43.844286 | J23: =('income '!D23-expenditure!D23)/'assets '!D23*100 -> 2.4167192 | K23: =('income '!E23-expenditure!E23)/'assets '!E23*100 -> 2.502571 | L23: =('income '!F23-expenditure!F23)/'assets '!F23*100 -> 1.6102655
B24: 20 | C24: First Abu Dhabi Bank | D24: =depo!J24/depo!D24*100 -> 155.22622 | E24: =depo!K24/depo!E24*100 -> 237.6484 | F24: =depo!L24/depo!F24*100 -> 151.60299 | G24: =depo!G24/depo!D24*100 -> 920.02878 | H24: =depo!H24/depo!E24*100 -> 1156.6689 | I24: =depo!I24/depo!F24*100 -> 329.10205 | J24: =('income '!D24-expenditure!D24)/'assets '!D24*100 -> 2.8329998 | K24: =('income '!E24-expenditure!E24)/'assets '!E24*100 -> 2.3291106 | L24: =('income '!F24-expenditure!F24)/'assets '!F24*100 -> 1.7102163
B25: 21 | C25: FirstRand Bank Ltd. | D25: - | E25: - | F25: - | G25: - | H25: - | I25: - | J25: =('income '!D25-expenditure!D25)/'assets '!D25*100 -> 4.8863636 | K25: =('income '!E25-expenditure!E25)/'assets '!E25*100 -> 5.7015164 | L25: =('income '!F25-expenditure!F25)/'assets '!F25*100 -> 5.6416452
B26: 22 | C26: Hongkong and Shanghai Banking Corpn. Ltd. (HSBC) | D26: =depo!J26/depo!D26*100 -> 55.136332 | E26: =depo!K26/depo!E26*100 -> 54.27725 | F26: =depo!L26/depo!F26*100 -> 61.903101 | G26: =depo!G26/depo!D26*100 -> 64.389955 | H26: =depo!H26/depo!E26*100 -> 73.812083 | I26: =depo!I26/depo!F26*100 -> 71.754436 | J26: =('income '!D26-expenditure!D26)/'assets '!D26*100 -> 3.2384267 | K26: =('income '!E26-expenditure!E26)/'assets '!E26*100 -> 3.8116719 | L26: =('income '!F26-expenditure!F26)/'assets '!F26*100 -> 3.3914306
B27: 23 | C27: Industrial Bank of Korea | D27: =depo!J27/depo!D27*100 -> 75.04119 | E27: =depo!K27/depo!E27*100 -> 165.50379 | F27: =depo!L27/depo!F27*100 -> 213.82729 | G27: =depo!G27/depo!D27*100 -> 10.476449 | H27: =depo!H27/depo!E27*100 -> 20.3501 | I27: =depo!I27/depo!F27*100 -> 24.030759 | J27: =('income '!D27-expenditure!D27)/'assets '!D27*100 -> 3.5724299 | K27: =('income '!E27-expenditure!E27)/'assets '!E27*100 -> 5.688949 | L27: =('income '!F27-expenditure!F27)/'assets '!F27*100 -> 4.4545958
B28: 24 | C28: Industrial & Commercial Bank of China Limited (ICBC) | D28: =depo!J28/depo!D28*100 -> 33.365345 | E28: =depo!K28/depo!E28*100 -> 45.966314 | F28: =depo!L28/depo!F28*100 -> 42.333667 | G28: =depo!G28/depo!D28*100 -> 118.88303 | H28: =depo!H28/depo!E28*100 -> 121.37959 | I28: =depo!I28/depo!F28*100 -> 104.11489 | J28: =('income '!D28-expenditure!D28)/'assets '!D28*100 -> 1.6545703 | K28: =('income '!E28-expenditure!E28)/'assets '!E28*100 -> 1.7749184 | L28: =('income '!F28-expenditure!F28)/'assets '!F28*100 -> 2.4393495
B29: 25 | C29: JPMorgan Chase Bank | D29: =depo!J29/depo!D29*100 -> 28.953868 | E29: =depo!K29/depo!E29*100 -> 17.340877 | F29: =depo!L29/depo!F29*100 -> 19.05635 | G29: =depo!G29/depo!D29*100 -> 120.07548 | H29: =depo!H29/depo!E29*100 -> 126.32995 | I29: =depo!I29/depo!F29*100 -> 129.36821 | J29: =('income '!D29-expenditure!D29)/'assets '!D29*100 -> 2.9090254 | K29: =('income '!E29-expenditure!E29)/'assets '!E29*100 -> 3.3655984 | L29: =('income '!F29-expenditure!F29)/'assets '!F29*100 -> 2.731792
B30: 26 | C30: JSC VTB Bank | D30: =depo!J30/depo!D30*100 -> 0 | E30: =depo!K30/depo!E30*100 -> 0 | F30: =depo!L30/depo!F30*100 -> 0 | G30: =depo!G30/depo!D30*100 -> 415.79663 | H30: =depo!H30/depo!E30*100 -> 41.488359 | I30: =depo!I30/depo!F30*100 -> 15.047633 | J30: =('income '!D30-expenditure!D30)/'assets '!D30*100 -> 0.28402526 | K30: =('income '!E30-expenditure!E30)/'assets '!E30*100 -> 2.7176729 | L30: =('income '!F30-expenditure!F30)/'assets '!F30*100 -> 4.1500331
B31: 27 | C31: KEB Hana Bank | D31: =depo!J31/depo!D31*100 -> 92.840089 | E31: =depo!K31/depo!E31*100 -> 116.41212 | F31: =depo!L31/depo!F31*100 -> 77.152117 | G31: =depo!G31/depo!D31*100 -> 9.0322581 | H31: =depo!H31/depo!E31*100 -> 14.659476 | I31: =depo!I31/depo!F31*100 -> 10.478173 | J31: =('income '!D31-expenditure!D31)/'assets '!D31*100 -> 2.2419662 | K31: =('income '!E31-expenditure!E31)/'assets '!E31*100 -> 2.7027791 | L31: =('income '!F31-expenditure!F31)/'assets '!F31*100 -> 2.2722798
B32: 28 | C32: Kookmin Bank | D32: =depo!J32/depo!D32*100 -> 55.091804 | E32: =depo!K32/depo!E32*100 -> 77.852319 | F32: =depo!L32/depo!F32*100 -> 75.436507 | G32: =depo!G32/depo!D32*100 -> 69.89927 | H32: =depo!H32/depo!E32*100 -> 140.89293 | I32: =depo!I32/depo!F32*100 -> 105.48359 | J32: =('income '!D32-expenditure!D32)/'assets '!D32*100 -> 2.1670066 | K32: =('income '!E32-expenditure!E32)/'assets '!E32*100 -> 1.3377716 | L32: =('income '!F32-expenditure!F32)/'assets '!F32*100 -> 1.1923909
B33: 29 | C33: Krung Thai Bank Public Company Ltd. | D33: 0 | E33: - | F33: - | G33: 0 | H33: - | I33: - | J33: =('income '!D33-expenditure!D33)/'assets '!D33*100 -> 3.6289666 | K33: - | L33: -
B34: 30 | C34: Mashreqbank psc | D34: =depo!J34/depo!D34*100 -> 801.20709 | E34: =depo!K34/depo!E34*100 -> 483.55198 | F34: =depo!L34/depo!F34*100 -> 620.18563 | G34: =depo!G34/depo!D34*100 -> 288.42295 | H34: =depo!H34/depo!E34*100 -> 108.36289 | I34: =depo!I34/depo!F34*100 -> 94.313986 | J34: =('income '!D34-expenditure!D34)/'assets '!D34*100 -> 5.734279 | K34: =('income '!E34-expenditure!E34)/'assets '!E34*100 -> 7.1159282 | L34: =('income '!F34-expenditure!F34)/'assets '!F34*100 -> 3.7370739
B35: 31 | C35: Mizuho Bank Ltd. | D35: =depo!J35/depo!D35*100 -> 71.35545 | E35: =depo!K35/depo!E35*100 -> 83.281226 | F35: =depo!L35/depo!F35*100 -> 72.300906 | G35: =depo!G35/depo!D35*100 -> 31.033532 | H35: =depo!H35/depo!E35*100 -> 54.203586 | I35: =depo!I35/depo!F35*100 -> 76.752726 | J35: =('income '!D35-expenditure!D35)/'assets '!D35*100 -> 2.1075814 | K35: =('income '!E35-expenditure!E35)/'assets '!E35*100 -> 2.4911361 | L35: =('income '!F35-expenditure!F35)/'assets '!F35*100 -> 2.3745807
B36: 32 | C36: MUFG Bank Ltd | D36: =depo!J36/depo!D36*100 -> 91.992708 | E36: =depo!K36/depo!E36*100 -> 81.297362 | F36: =depo!L36/depo!F36*100 -> 94.65421 | G36: =depo!G36/depo!D36*100 -> 39.738369 | H36: =depo!H36/depo!E36*100 -> 50.242263 | I36: =depo!I36/depo!F36*100 -> 47.572653 | J36: =('income '!D36-expenditure!D36)/'assets '!D36*100 -> 2.3408755 | K36: =('income '!E36-expenditure!E36)/'assets '!E36*100 -> 2.7853472 | L36: =('income '!F36-expenditure!F36)/'assets '!F36*100 -> 2.9531362
B37: 33 | C37: NatWest Markets PLC | D37: - | E37: - | F37: - | G37: - | H37: - | I37: - | J37: =('income '!D37-expenditure!D37)/'assets '!D37*100 -> 1.8333701 | K37: =('income '!E37-expenditure!E37)/'assets '!E37*100 -> 2.2602104 | L37: =('income '!F37-expenditure!F37)/'assets '!F37*100 -> 2.10241
B38: 34 | C38: NongHyup Bank | D38: - | E38: 0 | F38: =depo!L38/depo!F38*100 -> 1026.0528 | G38: - | H38: =depo!H38/depo!E38*100 -> 0 | I38: =depo!I38/depo!F38*100 -> 0 | J38: - | K38: =('income '!E38-expenditure!E38)/'assets '!E38*100 -> 6.0526435 | L38: =('income '!F38-expenditure!F38)/'assets '!F38*100 -> 6.533525
B39: 35 | C39: PT Bank Maybank Indonesia TBK | D39: =depo!J39/depo!D39*100 -> 455.4915 | E39: =depo!K39/depo!E39*100 -> 401.57938 | F39: =depo!L39/depo!F39*100 -> 233.13348 | G39: =depo!G39/depo!D39*100 -> 196.13722 | H39: =depo!H39/depo!E39*100 -> 263.17539 | I39: =depo!I39/depo!F39*100 -> 103.68112 | J39: =('income '!D39-expenditure!D39)/'assets '!D39*100 -> 4.4650662 | K39: =('income '!E39-expenditure!E39)/'assets '!E39*100 -> 4.3650588 | L39: =('income '!F39-expenditure!F39)/'assets '!F39*100 -> 4.9304911
B40: 36 | C40: Qatar National Bank | D40: =depo!J40/depo!D40*100 -> 75.816521 | E40: =depo!K40/depo!E40*100 -> 86.732065 | F40: =depo!L40/depo!F40*100 -> 86.54217 | G40: =depo!G40/depo!D40*100 -> 41.829805 | H40: =depo!H40/depo!E40*100 -> 31.861283 | I40: =depo!I40/depo!F40*100 -> 31.102178 | J40: =('income '!D40-expenditure!D40)/'assets '!D40*100 -> 2.0975013 | K40: =('income '!E40-expenditure!E40)/'assets '!E40*100 -> 1.7626825 | L40: =('income '!F40-expenditure!F40)/'assets '!F40*100 -> 1.9962741
B41: 37 | C41: Sberbank | D41: =depo!J41/depo!D41*100 -> 6.2766379 | E41: =depo!K41/depo!E41*100 -> 0.64742437 | F41: NA | G41: =depo!G41/depo!D41*100 -> 365.2407 | H41: =depo!H41/depo!E41*100 -> 97.588311 | I41: NA | J41: =('income '!D41-expenditure!D41)/'assets '!D41*100 -> 1.9237658 | K41: =('income '!E41-expenditure!E41)/'assets '!E41*100 -> 11.953913 | L41: NA
B42: 38 | C42: SBM Bank (India) Ltd. | D42: =depo!J42/depo!D42*100 -> 66.077887 | E42: =depo!K42/depo!E42*100 -> 65.741832 | F42: =depo!L42/depo!F42*100 -> 60.440942 | G42: =depo!G42/depo!D42*100 -> 50.456991 | H42: =depo!H42/depo!E42*100 -> 42.983146 | I42: =depo!I42/depo!F42*100 -> 28.725344 | J42: =('income '!D42-expenditure!D42)/'assets '!D42*100 -> 2.0965388 | K42: =('income '!E42-expenditure!E42)/'assets '!E42*100 -> 2.5194503 | L42: =('income '!F42-expenditure!F42)/'assets '!F42*100 -> 2.0427638
B43: 39 | C43: Shinhan Bank | D43: =depo!J43/depo!D43*100 -> 81.690915 | E43: =depo!K43/depo!E43*100 -> 81.823761 | F43: =depo!L43/depo!F43*100 -> 79.60939 | G43: =depo!G43/depo!D43*100 -> 34.5884 | H43: =depo!H43/depo!E43*100 -> 26.964457 | I43: =depo!I43/depo!F43*100 -> 23.492188 | J43: =('income '!D43-expenditure!D43)/'assets '!D43*100 -> 1.9140801 | K43: =('income '!E43-expenditure!E43)/'assets '!E43*100 -> 1.9331548 | L43: =('income '!F43-expenditure!F43)/'assets '!F43*100 -> 1.7577815
B44: 40 | C44: Societe Generale | D44: =depo!J44/depo!D44*100 -> 66.141194 | E44: =depo!K44/depo!E44*100 -> 85.954707 | F44: =depo!L44/depo!F44*100 -> 40.154375 | G44: =depo!G44/depo!D44*100 -> 256.84022 | H44: =depo!H44/depo!E44*100 -> 315.71689 | I44: =depo!I44/depo!F44*100 -> 290.08424 | J44: =('income '!D44-expenditure!D44)/'assets '!D44*100 -> 2.3456857 | K44: =('income '!E44-expenditure!E44)/'assets '!E44*100 -> 2.6511165 | L44: =('income '!F44-expenditure!F44)/'assets '!F44*100 -> 2.951381
B45: 41 | C45: Sonali Bank Ltd. | D45: =depo!J45/depo!D45*100 -> 38.481942 | E45: =depo!K45/depo!E45*100 -> 10.608955 | F45: =depo!L45/depo!F45*100 -> 5.1642119 | G45: =depo!G45/depo!D45*100 -> 36.696593 | H45: =depo!H45/depo!E45*100 -> 26.550598 | I45: =depo!I45/depo!F45*100 -> 31.236517 | J45: =('income '!D45-expenditure!D45)/'assets '!D45*100 -> 2.1201027 | K45: =('income '!E45-expenditure!E45)/'assets '!E45*100 -> 2.7576001 | L45: =('income '!F45-expenditure!F45)/'assets '!F45*100 -> 4.0183176
B46: 42 | C46: Standard Chartered Bank | D46: =depo!J46/depo!D46*100 -> 64.774349 | E46: =depo!K46/depo!E46*100 -> 60.431668 | F46: =depo!L46/depo!F46*100 -> 58.232002 | G46: =depo!G46/depo!D46*100 -> 71.913264 | H46: =depo!H46/depo!E46*100 -> 76.376207 | I46: =depo!I46/depo!F46*100 -> 76.036506 | J46: =('income '!D46-expenditure!D46)/'assets '!D46*100 -> 3.5924215 | K46: =('income '!E46-expenditure!E46)/'assets '!E46*100 -> 3.9176427 | L46: =('income '!F46-expenditure!F46)/'assets '!F46*100 -> 3.6688027
B47: 43 | C47: Sumitomo Mitsui Banking Corporation (SMBC) | D47: =depo!J47/depo!D47*100 -> 72.000115 | E47: =depo!K47/depo!E47*100 -> 71.712937 | F47: =depo!L47/depo!F47*100 -> 74.987601 | G47: =depo!G47/depo!D47*100 -> 49.572823 | H47: =depo!H47/depo!E47*100 -> 45.672278 | I47: =depo!I47/depo!F47*100 -> 41.364718 | J47: =('income '!D47-expenditure!D47)/'assets '!D47*100 -> 2.4692594 | K47: =('income '!E47-expenditure!E47)/'assets '!E47*100 -> 2.4728761 | L47: =('income '!F47-expenditure!F47)/'assets '!F47*100 -> 2.5646824
B48: 44 | C48: United Overseas Bank Ltd. | D48: =depo!J48/depo!D48*100 -> 86.582964 | E48: =depo!K48/depo!E48*100 -> 90.596798 | F48: =depo!L48/depo!F48*100 -> 438.21503 | G48: =depo!G48/depo!D48*100 -> 33.905349 | H48: =depo!H48/depo!E48*100 -> 45.876353 | I48: =depo!I48/depo!F48*100 -> 278.40853 | J48: =('income '!D48-expenditure!D48)/'assets '!D48*100 -> 2.7181069 | K48: =('income '!E48-expenditure!E48)/'assets '!E48*100 -> 3.1502789 | L48: =('income '!F48-expenditure!F48)/'assets '!F48*100 -> 4.8312971
B49: 45 | C49: Woori Bank | D49: =depo!J49/depo!D49*100 -> 69.550796 | E49: =depo!K49/depo!E49*100 -> 87.39932 | F49: =depo!L49/depo!F49*100 -> 81.05693 | G49: =depo!G49/depo!D49*100 -> 63.980105 | H49: =depo!H49/depo!E49*100 -> 60.679831 | I49: =depo!I49/depo!F49*100 -> 47.158177 | J49: =('income '!D49-expenditure!D49)/'assets '!D49*100 -> 1.5244408 | K49: =('income '!E49-expenditure!E49)/'assets '!E49*100 -> 1.5707494 | L49: =('income '!F49-expenditure!F49)/'assets '!F49*100 -> 1.6778293
B50: Total of Foreign Banks in India | D50: =depo!J50/depo!D50*100 -> 57.374964 | E50: =depo!K50/depo!E50*100 -> 54.402612 | F50: =depo!L50/depo!F50*100 -> 56.394996 | G50: =depo!G50/depo!D50*100 -> 78.763423 | H50: =depo!H50/depo!E50*100 -> 80.082566 | I50: =depo!I50/depo!F50*100 -> 84.135166 | J50: =('income '!D50-expenditure!D50)/'assets '!D50*100 -> 3.2937534 | K50: =('income '!E50-expenditure!E50)/'assets '!E50*100 -> 3.4616923 | L50: =('income '!F50-expenditure!F50)/'assets '!F50*100 -> 3.1511598
B52: 6

Sheet ratio1
B1: Statement VII : Foreign Banks in India : Ratios
B2: As on March 31 | L2: (Per Cent)
B3: S. No | C3: Name of the Bank | D3: Operating Expenses as % to Total Expenses | G3: Return on Assets (%) | J3: Capital Adequacy Ratio (CAR) Basel-III
D4: 2023 | E4: 2024 | F4: 2025 | G4: 2023 | H4: 2024 | I4: 2025 | J4: 2023 | K4: 2024 | L4: 2025
B5: 1 | C5: AB Bank Ltd. | D5: =expenditure!G5/expenditure!J5*100 -> 96.248535 | E5: =expenditure!H5/expenditure!K5*100 -> 95.983716 | F5: =expenditure!I5/expenditure!L5*100 -> 98.324893 | G5: 2.71 | H5: 4.64 | I5: 5.1 | J5: 70.55 | K5: 96.32 | L5: 87.97
B6: 2 | C6: American Express Banking Corporation | D6: =expenditure!G6/expenditure!J6*100 -> 92.536178 | E6: =expenditure!H6/expenditure!K6*100 -> 90.144837 | F6: =expenditure!I6/expenditure!L6*100 -> 88.197152 | G6: 0.77 | H6: 0.65 | I6: 0.12 | J6: 32.34 | K6: 23.48 | L6: 17.2
B7: 3 | C7: Australia & New Zealand Banking Group Ltd. (ANZ) | D7: =expenditure!G7/expenditure!J7*100 -> 33.628129 | E7: =expenditure!H7/expenditure!K7*100 -> 15.841499 | F7: =expenditure!I7/expenditure!L7*100 -> 12.48036 | G7: 0.77 | H7: 0.66 | I7: 0.87 | J7: 20.11 | K7: 20.43 | L7: 17.91
B8: 4 | C8: Bank of America NA | D8: =expenditure!G8/expenditure!J8*100 -> 52.607228 | E8: =expenditure!H8/expenditure!K8*100 -> 35.120951 | F8: =expenditure!I8/expenditure!L8*100 -> 27.840272 | G8: 1.49 | H8: 2.09 | I8: 2.39 | J8: 19.82 | K8: 18.46 | L8: 19.14
B9: 5 | C9: Bank of Bahrain and Kuwait B.S.C. | D9: =expenditure!G9/expenditure!J9*100 -> 31.873703 | E9: =expenditure!H9/expenditure!K9*100 -> 30.11412 | F9: =expenditure!I9/expenditure!L9*100 -> 29.527171 | G9: 0.64 | H9: 0.22 | I9: 0.01 | J9: 22.13 | K9: 22.87 | L9: 29.49
B10: 6 | C10: Bank of Ceylon | D10: =expenditure!G10/expenditure!J10*100 -> 44.533516 | E10: =expenditure!H10/expenditure!K10*100 -> 41.661314 | F10: =expenditure!I10/expenditure!L10*100 -> 44.865505 | G10: 2.09 | H10: 1.4 | I10: 1.55 | J10: 30.75 | K10: 33.26 | L10: 27.47
B11: 7 | C11: Bank of China | D11: =expenditure!G11/expenditure!J11*100 -> 94.630501 | E11: =expenditure!H11/expenditure!K11*100 -> 92.955826 | F11: =expenditure!I11/expenditure!L11*100 -> 97.967672 | G11: 1.68 | H11: 0.53 | I11: 0.64 | J11: 108.59 | K11: 133.61 | L11: 125.15
B12: 8 | C12: Bank of Nova Scotia | D12: =expenditure!G12/expenditure!J12*100 -> 73.214707 | E12: =expenditure!H12/expenditure!K12*100 -> 98.70624 | F12: =expenditure!I12/expenditure!L12*100 -> 98.409133 | G12: -0.65 | H12: 3.17 | I12: 2.03 | J12: 132.27 | K12: 510.88 | L12: 477.89
B13: 9 | C13: Barclays Bank PLC | D13: =expenditure!G13/expenditure!J13*100 -> 41.85009 | E13: =expenditure!H13/expenditure!K13*100 -> 31.18653 | F13: =expenditure!I13/expenditure!L13*100 -> 29.576325 | G13: 1.47 | H13: 1.55 | I13: 1.68 | J13: 17.28 | K13: 15.93 | L13: 19.16
B14: 10 | C14: BNP Paribas | D14: =expenditure!G14/expenditure!J14*100 -> 30.908319 | E14: =expenditure!H14/expenditure!K14*100 -> 26.778262 | F14: =expenditure!I14/expenditure!L14*100 -> 24.114085 | G14: 0.95 | H14: 1.18 | I14: 1.01 | J14: 15.83 | K14: 17 | L14: 16.62
B15: 11 | C15: Citibank N.A. | D15: =expenditure!G15/expenditure!J15*100 -> 61.072022 | E15: =expenditure!H15/expenditure!K15*100 -> 48.376921 | F15: =expenditure!I15/expenditure!L15*100 -> 53.33476 | G15: 1.92 | H15: 2.52 | I15: 2.29 | J15: 20.68 | K15: 18.71 | L15: 20.38
B16: 12 | C16: Cooperatieve Rabobank U.A. # | D16: =expenditure!G16/expenditure!J16*100 -> 68.430212 | E16: =expenditure!H16/expenditure!K16*100 -> 95.446837 | F16: =expenditure!I16/expenditure!L16*100 -> 100 | G16: 0.87 | H16: 4.12 | I16: 1.68 | J16: 74.4 | K16: 160.76 | L16: 187.44
... B32: 28 | C32: Kookmin Bank | D32: =expenditure!G32/expenditure!J32*100 -> 20.928323 | E32: =expenditure!H32/expenditure!K32*100 -> 14.371388 | F32: =expenditure!I32/expenditure!L32*100 -> 21.310425 | G32: 0.03 | H32: 0.13 | I32: -0.02 | J32: 43.9 | K32: 35.02 | L32: 29.41
B33: 29 | C33: Krung Thai Bank Public Company Ltd. | D33: =expenditure!G33/expenditure!J33*100 -> 100 | E33: - | F33: - | G33: -2.86 | H33: - | I33: - | J33: 232.72 | K33: - | L33: -
B34: 30 | C34: Mashreqbank psc | D34: =expenditure!G34/expenditure!J34*100 -> 93.292851 | E34: =expenditure!H34/expenditure!K34*100 -> 89.536741 | F34: =expenditure!I34/expenditure!L34*100 -> 57.498464 | G34: 2.35 | H34: 3 | I34: 1.97 | J34: 69.51 | K34: 66.31 | L34: 36.71
B35: 31 | C35: Mizuho Bank Ltd. | D35: =expenditure!G35/expenditure!J35*100 -> 32.435421 | E35: =expenditure!H35/expenditure!K35*100 -> 30.409997 | F35: =expenditure!I35/expenditure!L35*100 -> 19.34585 | G35: 1.07 | H35: 1.4 | I35: 1.57 | J35: 18.21 | K35: 23.37 | L35: 21.95
B36: 32 | C36: MUFG Bank Ltd. | D36: =expenditure!G36/expenditure!J36*100 -> 33.21895 | E36: =expenditure!H36/expenditure!K36*100 -> 40.57474 | F36: =expenditure!I36/expenditure!L36*100 -> 35.652716 | G36: 1.55 | H36: 1.07 | I36: 1.68 | J36: 24.28 | K36: 22.87 | L36: 16.51
B37: 33 | C37: NatWest Markets PLC | D37: =expenditure!G37/expenditure!J37*100 -> 43.497788 | E37: =expenditure!H37/expenditure!K37*100 -> 15.768372 | F37: =expenditure!I37/expenditure!L37*100 -> -76.21877 | G37: -1.69 | H37: -1.79 | I37: 1.31 | J37: 348.15 | K37: 313.42 | L37: 378.4
B38: 34 | C38: NongHyup Bank | D38: - | E38: =expenditure!H38/expenditure!K38*100 -> 99.984104 | F38: =expenditure!I38/expenditure!L38*100 -> 98.100079 | G38: - | H38: -0.1 | I38: -0.17 | J38: - | K38: 123.01 | L38: 82.86
B39: 35 | C39: PT Bank Maybank Indonesia TBK | D39: =expenditure!G39/expenditure!J39*100 -> 88.609543 | E39: =expenditure!H39/expenditure!K39*100 -> 85.88626 | F39: =expenditure!I39/expenditure!L39*100 -> 76.097156 | G39: 0.61 | H39: 3.1 | I39: 3.64 | J39: 60.13 | K39: 90.77 | L39: 74.87
B40: 36 | C40: Qatar National Bank | D40: =expenditure!G40/expenditure!J40*100 -> 35.129942 | E40: =expenditure!H40/expenditure!K40*100 -> 36.272563 | F40: =expenditure!I40/expenditure!L40*100 -> 29.038125 | G40: 0.01 | H40: -0.53 | I40: 0.61 | J40: 52.3 | K40: 42.06 | L40: 37.79
B41: 37 | C41: Sberbank | D41: =expenditure!G41/expenditure!J41*100 -> 97.024155 | E41: =expenditure!H41/expenditure!K41*100 -> 99.394501 | F41: NA | G41: 8.47 | H41: 6.38 | I41: NA | J41: 135.34 | K41: 143.99 | L41: NA
B42: 38 | C42: SBM Bank (India) Ltd. # | D42: =expenditure!G42/expenditure!J42*100 -> 45.333205 | E42: =expenditure!H42/expenditure!K42*100 -> 44.836049 | F42: =expenditure!I42/expenditure!L42*100 -> 44.331859 | G42: 0.22 | H42: -0.49 | I42: -0.98 | J42: 16.16 | K42: 16.9 | L42: 15.52
B43: 39 | C43: Shinhan Bank | D43: =expenditure!G43/expenditure!J43*100 -> 23.218643 | E43: =expenditure!H43/expenditure!K43*100 -> 22.976569 | F43: =expenditure!I43/expenditure!L43*100 -> 20.415934 | G43: 0.52 | H43: 0.45 | I43: 0.72 | J43: 21.14 | K43: 18.01 | L43: 16.94
B44: 40 | C44: Societe Generale | D44: =expenditure!G44/expenditure!J44*100 -> 52.951384 | E44: =expenditure!H44/expenditure!K44*100 -> 45.28271 | F44: =expenditure!I44/expenditure!L44*100 -> 49.37937 | G44: 0.44 | H44: 0.73 | I44: 1.06 | J44: 23.64 | K44: 29.26 | L44: 26.01
B45: 41 | C45: Sonali Bank Ltd. | D45: =expenditure!G45/expenditure!J45*100 -> 78.663239 | E45: =expenditure!H45/expenditure!K45*100 -> 76.31172 | F45: =expenditure!I45/expenditure!L45*100 -> 88.063901 | G45: 2.51 | H45: 2.53 | I45: 0.86 | J45: 67.82 | K45: 127.41 | L45: 168.68
B46: 42 | C46: Standard Chartered Bank | D46: =expenditure!G46/expenditure!J46*100 -> 49.55055 | E46: =expenditure!H46/expenditure!K46*100 -> 52.904445 | F46: =expenditure!I46/expenditure!L46*100 -> 54.347363 | G46: 2.35 | H46: 1.63 | I46: 0.75 | J46: 17.29 | K46: 16.19 | L46: 15.16
B47: 43 | C47: Sumitomo Mitsui Banking Corporation (SMBC) | D47: =expenditure!G47/expenditure!J47*100 -> 25.287296 | E47: =expenditure!H47/expenditure!K47*100 -> 22.681962 | F47: =expenditure!I47/expenditure!L47*100 -> 17.760758 | G47: 1.59 | H47: 1.26 | I47: 1.34 | J47: 35.14 | K47: 20.33 | L47: 23.29
B48: 44 | C48: United Overseas Bank Ltd. | D48: =expenditure!G48/expenditure!J48*100 -> 55.632356 | E48: =expenditure!H48/expenditure!K48*100 -> 49.520649 | F48: =expenditure!I48/expenditure!L48*100 -> 57.66905 | G48: 1.69 | H48: 1.28 | I48: 1.78 | J48: 180.93 | K48: 148.81 | L48: 167.78
B49: 45 | C49: Woori Bank | D49: =expenditure!G49/expenditure!J49*100 -> 19.098955 | E49: =expenditure!H49/expenditure!K49*100 -> 19.572648 | F49: =expenditure!I49/expenditure!L49*100 -> 19.946551 | G49: 0.49 | H49: 0.38 | I49: -0.04 | J49: 53.5 | K49: 34.89 | L49: 37.75
B50: Total of Foreign Banks in India | D50: =expenditure!G50/expenditure!J50*100 -> 46.881288 | E50: =expenditure!H50/expenditure!K50*100 -> 42.481627 | F50: =expenditure!I50/expenditure!L50*100 -> 40.818419
B52: # Return on Assets is computed with reference to Average Working Funds ( excluding accumulated losses, if any).
B54: 7

Sheet ratio2
B1: Statement VIII: Foreign Banks in India : Ratios
B2: As on March 31 | M2: (Per Cent)
B3: Sr. No | C3: Name of the Bank | D3: Net NPA as % to Net Advances | G3: Business per Employee (In Crore) | J3: Profit per Employee (In Lacs)
D4: 2023 | E4: 2024 | F4: 2025 | G4: 2023 | H4: 2024 | I4: 2025 | J4: 2023 | K4: 2024 | M4: 2025
B5: 1 | C5: AB Bank Limited | D5: ='assets '!J5/depo!J5*100 -> 0 | E5: 0 | F5: 0 | G5: 2.92 | H5: 3.0545 | I5: 3.0458 | J5: 31 | K5: 63.43 | L5: c | M5: 73.68 | O5: ='assets '!J5/depo!J5*100-D5 -> 0 | P5: ='assets '!K5/depo!K5*100-E5 -> 0 | Q5: ='assets '!L5/depo!L5*100-F5 -> 0
B6: 2 | C6: American Express Banking Corporation | D6: ='assets '!J6/depo!J6*100 -> 1.0426163 | E6: 0.81 | F6: 0.61 | G6: 4.83 | H6: 5.86 | I6: 7.09 | J6: 4.81 | K6: 4.76 | L6: c | M6: 0.93 | O6: ='assets '!J6/depo!J6*100-D6 -> 0 | P6: ='assets '!K6/depo!K6*100-E6 -> -0.0019423963 | Q6: ='assets '!L6/depo!L6*100-F6 -> 0.00035419317
B7: 3 | C7: Australia & New Zealand Banking Group Ltd. (ANZ) | D7: ='assets '!J7/depo!J7*100 -> 0 | E7: 0 | F7: 0 | G7: 122.84 | H7: 145.768 | I7: 150.5147 | J7: 171.55 | K7: 183.4 | L7: c | M7: 340.73 | O7: ='assets '!J7/depo!J7*100-D7 -> 0 | P7: ='assets '!K7/depo!K7*100-E7 -> 0 | Q7: ='assets '!L7/depo!L7*100-F7 -> 0
B8: 4 | C8: Bank of America NA | D8: ='assets '!J8/depo!J8*100 -> 0 | E8: 0 | F8: 0 | G8: 148.1 | H8: 175.739 | I8: 201.2356 | J8: 237.14 | K8: 383.96 | L8: c | M8: 517.17 | O8: ='assets '!J8/depo!J8*100-D8 -> 0 | P8: ='assets '!K8/depo!K8*100-E8 -> 0 | Q8: ='assets '!L8/depo!L8*100-F8 -> 0
B9: 5 | C9: Bank of Bahrain and Kuwait B.S.C. | D9: 0.71 | E9: 0.13 | F9: 0 | G9: 38.51 | H9: 36.04 | I9: 37.64 | J9: 16.66 | K9: 6 | L9: c | M9: 0 | O9: ='assets '!J9/depo!J9*100-D9 -> 0.064498803 | P9: ='assets '!K9/depo!K9*100-E9 -> 0.071488084 | Q9: ='assets '!L9/depo!L9*100-F9 -> 0.0063601274
B10: 6 | C10: Bank of Ceylon | D10: 4.1 | E10: 3.36 | F10: 1.96 | G10: 25.83 | H10: 23.4 | I10: 22.67 | J10: 43 | K10: 32 | M10: 33 | O10: ='assets '!J10/depo!J10*100-D10 -> -0.0051560001 | P10: ='assets '!K10/depo!K10*100-E10 -> 0.0041398622 | Q10: ='assets '!L10/depo!L10*100-F10 -> 0.0011423316
B11: 7 | C11: Bank of China | D11: ='assets '!J11/depo!J11*100 -> 0 | E11: 0 | F11: 0 | G11: 5.85 | H11: 3.774 | I11: 5.5487 | J11: 23.58 | K11: 5.78 | L11: c | M11: 8.44 | O11: ='assets '!J11/depo!J11*100-D11 -> 0 | P11: ='assets '!K11/depo!K11*100-E11 -> 0 | Q11: ='assets '!L11/depo!L11*100-F11 -> 0
B12: 8 | C12: Bank of Nova Scotia | D12: ='assets '!J12/depo!J12*100 -> 0 | E12: 0 | F12: 0 | G12: 2.91 | H12: 0.62 | I12: 0.54 | J12: -30.04 | K12: 115.12 | L12: c | M12: 102.04 | O12: ='assets '!J12/depo!J12*100-D12 -> 0 | P12: ='assets '!K12/depo!K12*100-E12 -> 0 | Q12: ='assets '!L12/depo!L12*100-F12 -> 0
B13: 9 | C13: Barclays Bank PLC | D13: ='assets '!J13/depo!J13*100 -> 0 | E13: 0 | F13: 0 | G13: 75.87 | H13: 84.737 | I13: 103.5563 | J13: 214.8 | K13: 253.7 | L13: c | M13: 354.31 | O13: ='assets '!J13/depo!J13*100-D13 -> 0 | P13: ='assets '!K13/depo!K13*100-E13 -> 0 | Q13: ='assets '!L13/depo!L13*100-F13 -> 0
B14: 10 | C14: BNP Paribas | D14: ='assets '!J14/depo!J14*100 -> 0 | E14: 0 | F14: 0 | G14: 83.12 | H14: 91.86 | I14: 118.75 | J14: 133.73 | K14: 169 | L14: c | M14: 194 | O14: ='assets '!J14/depo!J14*100-D14 -> 0 | P14: ='assets '!K14/depo!K14*100-E14 -> 0 | Q14: ='assets '!L14/depo!L14*100-F14 -> 0
B15: 11 | C15: Citibank N.A. | D15: 0 | E15: 0 | F15: 0 | G15: 45.71 | H15: 121.49 | I15: 150.805 | J15: 96 | K15: 341 | M15: 361.76 | O15: ='assets '!J15/depo!J15*100-D15 -> 0 | P15: ='assets '!K15/depo!K15*100-E15 -> 0 | Q15: ='assets '!L15/depo!L15*100-F15 -> 0
B16: 12 | C16: Cooperatieve Rabobank U.A. ^ | D16: ='assets '!J16/depo!J16*100 -> 16.788386 | E16: 0 | F16: 0 | G16: 14.44 | H16: 0 | I16: 0 | J16: 158.21 | K16: 448.19 | L16: c | M16: 160.4 | O16: ='assets '!J16/depo!J16*100-D16 -> 0 | P16: ='assets '!K16/depo!K16*100-E16 -> #DIV/0! | Q16: ='assets '!L16/depo!L16*100-F16 -> #DIV/0!
B17: 13 | C17: Credit Agricole Corporate & Investment Bank | D17: ='assets '!J17/depo!J17*100 -> 0 | E17: 0 | F17: 0 | G17: 133.51 | H17: 130.91 | I17: 132.13 | J17: 79.94 | K17: 124 | L17: c | M17: 193 | O17: ='assets '!J17/depo!J17*100-D17 -> 0 | P17: ='assets '!K17/depo!K17*100-E17 -> 0 | Q17: ='assets '!L17/depo!L17*100-F17 -> 0
B18: 14 | C18: UBS AG (earlier Credit Suisse) | D18: ='assets '!J18/depo!J18*100 -> 0 | E18: 0 | F18: 0 | G18: 31.37 | H18: 71.19 | I18: 75.83 | J18: 348 | K18: 304 | L18: c | M18: 392 | O18: ='assets '!J18/depo!J18*100-D18 -> 0 | P18: ='assets '!K18/depo!K18*100-E18 -> 0 | Q18: ='assets '!L18/depo!L18*100-F18 -> 0
B19: 15 | C19: CTBC Bank Co. Ltd. | D19: ='assets '!J19/depo!J19*100 -> 0 | E19: 0 | F19: 0 | G19: 43.74 | H19: 43.85 | I19: 57.07 | J19: 11.22 | K19: 33 | L19: c | M19: 33 | O19: ='assets '!J19/depo!J19*100-D19 -> 0 | P19: ='assets '!K19/depo!K19*100-E19 -> 0 | Q19: ='assets '!L19/depo!L19*100-F19 -> 0
B20: 16 | C20: DBS Bank Ltd. | D20: ='assets '!J20/depo!J20*100 -> 1.1671445 | E20: 0.24 | F20: 0.27 | G20: 16.61 | H20: 19.13 | I20: 18.853 | J20: 347 | K20: 543 | L20: c | M20: 932.43 | O20: ='assets '!J20/depo!J20*100-D20 -> 0 | P20: ='assets '!K20/depo!K20*100-E20 -> -0.0002015902 | Q20: ='assets '!L20/depo!L20*100-F20 -> 0.0088109789
B21: 17 | C21: Deutsche Bank AG | D21: ='assets '!J21/depo!J21*100 -> 0.90974766 | E21: 0.32 | F21: 0.28 | G21: 68.75 | H21: 77.145 | I21: 87.547 | J21: 80.38 | K21: 113.22 | L21: c | M21: 170.75 | O21: ='assets '!J21/depo!J21*100-D21 -> 0 | P21: ='assets '!K21/depo!K21*100-E21 -> -0.0037684679 | Q21: ='assets '!L21/depo!L21*100-F21 -> -0.0020882279
B22: 18 | C22: Doha Bank | D22: ='assets '!J22/depo!J22*100 -> 0 | E22: 0.8 | F22: 0.51 | G22: 24 | H22: 26.54 | I22: 37.0712 | J22: 0.61 | K22: 49.49 | L22: c | M22: 22.79 | O22: ='assets '!J22/depo!J22*100-D22 -> 0 | P22: ='assets '!K22/depo!K22*100-E22 -> 0.0013149784 | Q22: ='assets '!L22/depo!L22*100-F22 -> -0.0034636134
B23: 19 | C23: Emirates NBD Bank (PJSC) | D23: ='assets '!J23/depo!J23*100 -> 0 | E23: 0 | F23: 0 | G23: 76.43 | H23: 87.63 | I23: 95.184 | J23: 47.39 | K23: 69.89 | L23: c | M23: 55.42 | O23: ='assets '!J23/depo!J23*100-D23 -> 0 | P23: ='assets '!K23/depo!K23*100-E23 -> 0 | Q23: ='assets '!L23/depo!L23*100-F23 -> 0
B24: 20 | C24: First Abu Dhabi Bank | D24: ='assets '!J24/depo!J24*100 -> 0 | E24: 0 | F24: 0 | G24: 42.05 | H24: 31.67 | I24: 64.02 | J24: -69.18 | K24: 212.6 | L24: c | M24: 87.82 | O24: ='assets '!J24/depo!J24*100-D24 -> 0 | P24: ='assets '!K24/depo!K24*100-E24 -> 0 | Q24: ='assets '!L24/depo!L24*100-F24 -> 0
B25: 21 | C25: FirstRand Bank Ltd. | D25: 0 | E25: 0 | F25: 0 | G25: 0 | H25: 0 | I25: 0 | J25: 172.26 | K25: 0 | L25: c | M25: 0 | O25: ='assets '!J25/depo!J25*100-D25 -> #DIV/0! | P25: ='assets '!K25/depo!K25*100-E25 -> #DIV/0! | Q25: ='assets '!L25/depo!L25*100-F25 -> #DIV/0!
B26: 22 | C26: Hongkong and Shanghai Banking Corpn. Ltd. (HSBC) | D26: ='assets '!J26/depo!J26*100 -> 0.080135748 | E26: 0.05 | F26: 0.03 | G26: 82.78 | H26: 79.226 | I26: 83.7231 | J26: 98.36 | K26: 139.08 | L26: c | M26: 144.47 | O26: ='assets '!J26/depo!J26*100-D26 -> 0 | P26: ='assets '!K26/depo!K26*100-E26 -> -0.0039445339 | Q26: ='assets '!L26/depo!L26*100-F26 -> -0.0020879318
B27: 23 | C27: Industrial Bank of Korea | D27: ='assets '!J27/depo!J27*100 -> 0 | E27: 0 | F27: 0 | G27: 38.17 | H27: 30.35 | I27: 29.36 | J27: 61.21 | K27: 63 | L27: c | M27: 68 | O27: ='assets '!J27/depo!J27*100-D27 -> 0 | P27: ='assets '!K27/depo!K27*100-E27 -> 0 | Q27: ='assets '!L27/depo!L27*100-F27 -> 0
B28: 24 | C28: Industrial & Commercial Bank of China Limited (ICBC) | D28: ='assets '!J28/depo!J28*100 -> 0 | E28: 0 | F28: 0 | G28: 61.46 | H28: 92.198 | I28: 97.924 | J28: 27.43 | K28: 100.88 | L28: c | M28: 124.57 | O28: ='assets '!J28/depo!J28*100-D28 -> 0 | P28: ='assets '!K28/depo!K28*100-E28 -> 0 | Q28: ='assets '!L28/depo!L28*100-F28 -> 0
B29: 25 | C29: JPMorgan Chase Bank | D29: ='assets '!J29/depo!J29*100 -> 0 | E29: 0 | F29: 0 | G29: 164.32 | H29: 178.459 | I29: 196.9543 | J29: 463.39 | K29: 581.34 | L29: c | M29: 762.75 | O29: ='assets '!J29/depo!J29*100-D29 -> 0 | P29: ='assets '!K29/depo!K29*100-E29 -> 0 | Q29: ='assets '!L29/depo!L29*100-F29 -> 0
B30: 26 | C30: JSC VTB Bank | D30: 0 | E30: 0 | F30: 0 | G30: 2.83 | H30: 32.68 | I30: 76.61 | J30: 44.24 | K30: 209 | L30: c | M30: 382 | O30: ='assets '!J30/depo!J30*100-D30 -> #DIV/0! | P30: ='assets '!K30/depo!K30*100-E30 -> #DIV/0! | Q30: ='assets '!L30/depo!L30*100-F30 -> #DIV/0!
B31: 27 | C31: KEB Hana Bank | D31: 0 | E31: 0 | F31: 0 | G31: 113.48 | H31: 120.93 | I31: 153.97 | J31: 61 | K31: 125 | L31: c | M31: 223 | O31: ='assets '!J31/depo!J31*100-D31 -> 0 | P31: ='assets '!K31/depo!K31*100-E31 -> 0 | Q31: ='assets '!L31/depo!L31*100-F31 -> 0
B32: 28 | C32: Kookmin Bank | D32: ='assets '!J32/depo!J32*100 -> 0 | E32: 0 | F32: 0 | G32: 125.6 | H32: 71.19 | I32: 56.48 | J32: 4 | K32: 12 | M32: -1 | O32: ='assets '!J32/depo!J32*100-D32 -> 0 | P32: ='assets '!K32/depo!K32*100-E32 -> 0 | Q32: ='assets '!L32/depo!L32*100-F32 -> 0
B33: 29 | C33: Krung Thai Bank Public Company Ltd. | D33: 0 | E33: - | F33: - | G33: 0 | H33: - | I33: - | J33: -44.6 | K33: - | M33: - | O33: ='assets '!J33/depo!J33*100-D33 -> #DIV/0! | P33: ='assets '!K33/depo!K33*100-E33 -> #VALUE! | Q33: ='assets '!L33/depo!L33*100-F33 -> #VALUE!
B34: 30 | C34: Mashreqbank psc | D34: ='assets '!J34/depo!J34*100 -> 0 | E34: 0 | F34: 0 | G34: 31.58 | H34: 30.85 | I34: 56.133 | J34: 103.49 | K34: 112.45 | L34: c | M34: 83.38 | O34: ='assets '!J34/depo!J34*100-D34 -> 0 | P34: ='assets '!K34/depo!K34*100-E34 -> 0 | Q34: ='assets '!L34/depo!L34*100-F34 -> 0
B35: 31 | C35: Mizuho Bank Ltd. | D35: ='assets '!J35/depo!J35*100 -> 0 | E35: 0 | F35: 0 | G35: 102.27 | H35: 122.27 | I35: 159.36 | J35: 91 | K35: 134 | L35: c | M35: 234 | O35: ='assets '!J35/depo!J35*100-D35 -> 0 | P35: ='assets '!K35/depo!K35*100-E35 -> 0 | Q35: ='assets '!L35/depo!L35*100-F35 -> 0
B36: 32 | C36: MUFG Bank | D36: ='assets '!J36/depo!J36*100 -> 0 | E36: 0 | F36: 0 | G36: 85.337 | H36: 130.19 | I36: 134.95 | J36: 119.91 | K36: 130 | L36: c | M36: 222 | O36: ='assets '!J36/depo!J36*100-D36 -> 0 | P36: ='assets '!K36/depo!K36*100-E36 -> 0 | Q36: ='assets '!L36/depo!L36*100-F36 -> 0
B37: 33 | C37: NatWest Markets PLC | D37: 0 | E37: 0 | F37: 0 | G37: 0 | H37: 0 | I37: 0 | J37: -390.71 | K37: -433.41 | L37: c | M37: 324.3 | O37: ='assets '!J37/depo!J37*100-D37 -> #DIV/0! | P37: ='assets '!K37/depo!K37*100-E37 -> #DIV/0! | Q37: ='assets '!L37/depo!L37*100-F37 -> #DIV/0!
B38: 34 | C38: NongHyup Bank | D38: - | E38: 0 | F38: 0 | G38: - | H38: 7.73 | I38: 9.47 | J38: - | K38: -2 | M38: -4 | O38: ='assets '!J38/depo!J38*100-D38 -> #VALUE! | P38: ='assets '!K38/depo!K38*100-E38 -> 0 | Q38: ='assets '!L38/depo!L38*100-F38 -> 0
B39: 35 | C39: PT Bank Maybank Indonesia TBK | D39: ='assets '!J39/depo!J39*100 -> 0 | E39: 0 | F39: 0 | G39: 7.72 | H39: 9.239 | I39: 14.42 | J39: 6.26 | K39: 31.24 | L39: c | M39: 57 | O39: ='assets '!J39/depo!J39*100-D39 -> 0 | P39: ='assets '!K39/depo!K39*100-E39 -> 0 | Q39: ='assets '!L39/depo!L39*100-F39 -> 0
B40: 36 | C40: Qatar National Bank # | D40: 0 | E40: 0 | F40: 0 | G40: 58.5 | H40: 9 | I40: 11 | J40: 0.36 | K40: 0 | L40: c | M40: 0 | O40: ='assets '!J40/depo!J40*100-D40 -> 0 | P40: ='assets '!K40/depo!K40*100-E40 -> 0 | Q40: ='assets '!L40/depo!L40*100-F40 -> 0
B41: 37 | C41: Sberbank | D41: ='assets '!J41/depo!J41*100 -> 0 | E41: 0 | F41: NA | G41: 9.36 | H41: 15.16 | I41: NA | J41: 853.37 | K41: 528.104 | L41: c | M41: NA | O41: ='assets '!J41/depo!J41*100-D41 -> 0 | P41: ='assets '!K41/depo!K41*100-E41 -> 0 | Q41: ='assets '!L41/depo!L41*100-F41 -> #VALUE!
B42: 38 | C42: SBM Bank (India) Ltd. | D42: ='assets '!J42/depo!J42*100 -> 0.34305707 | E42: 0.61 | F42: 0.99 | G42: 23.94 | H42: 17.01 | I42: 17.36 | J42: 4.23 | K42: -6 | L42: c | M42: -13 | O42: ='assets '!J42/depo!J42*100-D42 -> 0 | P42: ='assets '!K42/depo!K42*100-E42 -> 0.0028902845 | Q42: ='assets '!L42/depo!L42*100-F42 -> -0.0028131651
B43: 39 | C43: Shinhan Bank | D43: 0.16 | E43: 0.07 | F43: 0.15 | G43: 41.44 | H43: 50.13 | I43: 62.1 | J43: 17.99 | K43: 14 | L43: c | M43: 26 | O43: ='assets '!J43/depo!J43*100-D43 -> -0.0051766349 | P43: ='assets '!K43/depo!K43*100-E43 -> 0.0021056076 | Q43: ='assets '!L43/depo!L43*100-F43 -> 0.0017936581
B44: 40 | C44: Societe Generale | D44: ='assets '!J44/depo!J44*100 -> 0 | E44: 0 | F44: 0 | G44: 43.32 | H44: 45.268 | I44: 43.736 | J44: 67.55 | K44: 101.59 | L44: c | M44: 154.24 | O44: ='assets '!J44/depo!J44*100-D44 -> 0 | P44: ='assets '!K44/depo!K44*100-E44 -> 0 | Q44: ='assets '!L44/depo!L44*100-F44 -> 0
B45: 41 | C45: Sonali Bank Ltd. | D45: 0.02 | E45: 1.53 | F45: 12.36 | G45: 5.3856 | H45: 5.8984 | I45: 3.936 | J45: 17.26 | K45: 25.69 | L45: c | M45: 8.8 | O45: ='assets '!J45/depo!J45*100-D45 -> -0.02 | P45: ='assets '!K45/depo!K45*100-E45 -> -0.010474092 | Q45: ='assets '!L45/depo!L45*100-F45 -> -0.0026950916
B46: 42 | C46: Standard Chartered Bank | D46: ='assets '!J46/depo!J46*100 -> 0.43686733 | E46: 0.35 | F46: 0.34 | G46: 32.74 | H46: 35.3448 | I46: 39.0424 | J46: 69.93 | K46: 57.59 | L46: c | M46: 32.14 | O46: ='assets '!J46/depo!J46*100-D46 -> 0 | P46: ='assets '!K46/depo!K46*100-E46 -> -0.0033154211 | Q46: ='assets '!L46/depo!L46*100-F46 -> -0.0038714987
B47: 43 | C47: Sumitomo Mitsui Banking Corporation (SMBC) | D47: ='assets '!J47/depo!J47*100 -> 0 | E47: 0 | F47: 0 | G47: 105.4 | H47: 135.81 | I47: 132.72 | J47: 148.93 | K47: 141 | L47: c | M47: 166 | O47: ='assets '!J47/depo!J47*100-D47 -> 0 | P47: ='assets '!K47/depo!K47*100-E47 -> 0 | Q47: ='assets '!L47/depo!L47*100-F47 -> 0
B48: 44 | C48: United Overseas Bank Ltd. | D48: ='assets '!J48/depo!J48*100 -> 0 | E48: 0 | F48: 0 | G48: 37.38 | H48: 45.41 | I48: 33.717 | J48: 98.64 | K48: 76.59 | L48: c | M48: 103.84 | O48: ='assets '!J48/depo!J48*100-D48 -> 0 | P48: ='assets '!K48/depo!K48*100-E48 -> 0 | Q48: ='assets '!L48/depo!L48*100-F48 -> 0
B49: 45 | C49: Woori Bank | D49: 0.33 | E49: 1.89 | F49: 0 | G49: 64.17 | H49: 68.64 | I49: 61.05 | J49: 35.83 | K49: 22 | L49: c | M49: -2 | O49: ='assets '!J49/depo!J49*100-D49 -> 0.0016340936 | P49: ='assets '!K49/depo!K49*100-E49 -> 0.012365057 | Q49: ='assets '!L49/depo!L49*100-F49 -> 0
B50: Total of Foreign Banks in India | D50: ='assets '!J50/depo!J50*100 -> 0.34045833 | E50: ='assets '!K50/depo!K50*100 -> 0.14798942 | F50: ='assets '!L50/depo!L50*100 -> 0.12517433 | O50: ='assets '!J50/depo!J50*100-D50 -> 0 | P50: ='assets '!K50/depo!K50*100-E50 -> 0 | Q50: ='assets '!L50/depo!L50*100-F50 -> 0
B52: ^ Business is calculated as net advances plus deposits excluding interbank deposits.
B53: # Business per emplyee inter bank deposits is excluded.
B55: 8
