Workbook

Sheet DEPO
B1: Statement I : Private Sector Banks : Deposits/Investments/Advances
B2: As on March 31 | L2: (₹ Crore)
B3: S.No | C3: Banks | D3: Deposits | G3: Investments | J3: Advances
B4: I | C4: OLD PRIVATE SECTOR BANKS | D4: 2023 | E4: 2024 | F4: 2025 | G4: 2023 | H4: 2024 | I4: 2025 | J4: 2023 | K4: 2024 | L4: 2025
B5: 1 | C5: City Union Bank Ltd. | D5: 52397.85 | E5: 55656.64 | F5: 63525.954 | G5: 14332.62 | H5: 15664.11 | I5: 17336.144 | J5: 43053.34 | K5: 45525.719 | L5: 52081.255
B6: 2 | C6: Tamilnad Mercantile Bank Ltd. | D6: 47766 | E6: 49515.07 | F6: 53688.96 | G6: 14156 | H6: 15262.6 | I6: 15100.8 | J6: 37290 | K6: 39733.75 | L6: 43983.67
B7: 3 | C7: CSB Bank Ltd. | D7: 24505.81 | E7: 29718.8 | F7: 36861.49 | G7: 5848.7 | H7: 7551.43 | I7: 11389.34 | J7: 20650.65 | K7: 24335.58 | L7: 31507.05
B8: 4 | C8: Dhanlaxmi Bank Ltd | D8: 13351.65 | E8: 14290.31 | F8: 16013.45 | G8: 3888.64 | H8: 3942.4 | I8: 3955.15 | J8: 9451.52 | K8: 10102.16 | L8: 11959.49
B9: 5 | C9: The Federal Bank Ltd. | D9: 213386.04 | E9: 252534.02 | F9: 283647.47 | G9: 48983.35 | H9: 60859.53 | I9: 66245.61 | J9: 174446.88 | K9: 209403.33 | L9: 234836.39
B10: 6 | C10: The Jammu & Kashmir Bank Ltd. | D10: 122038 | E10: 134776.32 | F10: 148569.46 | G10: 34829.15 | H10: 34986.71 | I10: 41212.66 | J10: 82285.45 | K10: 93762.51 | L10: 104198.72
B11: 7 | C11: The Karnataka Bank Ltd. | D11: 87368.01 | E11: 97988.22 | F11: 104807.49 | G11: 23326.37 | H11: 24302.05 | I11: 24536.51 | J11: 59951.62 | K11: 71508.64 | L11: 76541.48
B12: 8 | C12: The Karur Vysya Bank Ltd. | D12: 76637.58 | E12: 89112.72 | F12: 102077.99 | G12: 18808.32 | H12: 22343.52 | I12: 23831.25 | J12: 63134.14 | K12: 73667.48 | L12: 84004.54
B13: 9 | C13: Nainital Bank Ltd. | D13: 7681.82 | E13: 8267.7444 | F13: 8255.8188 | G13: 21302.238 | H13: 1989.0734 | I13: 1856.8862 | J13: 4317.038 | K13: 4517.8444 | L13: 4663.9371
B14: 10 | C14: RBL Bank | D14: 84886.52 | E14: 103493.6 | F14: 110943.53 | G14: 28875.45 | H14: 29575.85 | I14: 32164.75 | J14: 70209.35 | K14: 83986.92 | L14: 92618.27
B15: 11 | C15: The South Indian Bank Ltd. | D15: 91651.35 | E15: 101920.26 | F15: 107525.6 | G15: 24641.8 | H15: 23977.02 | I15: 21777.18 | J15: 69804.44 | K15: 78060.65 | L15: 85682.07
B16: TOTAL OF OLD PVT BANKS [I] | D16: =SUM(D5:D15) -> 821670.63 | E16: =SUM(E5:E15) -> 937273.7 | F16: =SUM(F5:F15) -> 1035917.2 | G16: =SUM(G5:G15) -> 238992.64 | H16: =SUM(H5:H15) -> 240454.29 | I16: =SUM(I5:I15) -> 259406.28 | J16: =SUM(J5:J15) -> 634594.43 | K16: =SUM(K5:K15) -> 734604.58 | L16: =SUM(L5:L15) -> 822076.87
B17: II | C17: NEW PRIVATE SECTOR BANKS
B18: 12 | C18: Axis Bank Ltd. | D18: 946945.21 | E18: 1068641.4 | F18: 1172952 | G18: 288814.83 | H18: 331527.25 | I18: 396141.79 | J18: 845302.84 | K18: 965068.38 | L18: 1040811.3
B19: 13 | C19: DCB Bank Ltd. | D19: 41238.91 | E19: 49353.03 | F19: 60030.95 | G19: 12582.46 | H19: 16210.85 | I19: 20149.9 | J19: 34378.04 | K19: 40924.56 | L19: 51046.91
B20: 14 | C20: HDFC Bank Ltd. | D20: 1883394.6 | E20: 2379786.3 | F20: 2714714.9 | G20: 517001.43 | H20: 702414.96 | I20: 836359.68 | J20: 1600585.9 | K20: 2484861.5 | L20: 2619608.6
B21: 15 | C21: ICICI Bank Ltd. | D21: 1180840.7 | E21: 1412824.9 | F21: 1610348 | G21: 362329.73 | H21: 461942.27 | I21: 504756.74 | J21: 1019638.3 | K21: 1184406.4 | L21: 1341766.2
B22: 16 | C22: Indusind Bank Ltd. | D22: 336438.14 | E22: 384792.92 | F22: 411078.14 | G22: 83116.2 | H22: 106526.71 | I22: 114496.8 | J22: 289923.68 | K22: 343298.27 | L22: 345018.63
B23: 17 | C23: Kotak Mahindra Bank Ltd. | D23: 363096.05 | E23: 448953.75 | F23: 499055.13 | G23: 121403.73 | H23: 155403.76 | I23: 181907.45 | J23: 319861.21 | K23: 376075.27 | L23: 426909.2
B24: 18 | C24: YES Bank | D24: 217501.86 | E24: 266372.17 | F24: 284525.13 | G24: 76888.3 | H24: 90235.13 | I24: 85104.48 | J24: 203269.44 | K24: 227799.47 | L24: 246188.47
B25: 19 | C25: Bandhan Bank | D25: 108064.69 | E25: 135201.98 | F25: 151212.5 | G25: 32365.89 | H25: 29287.578 | I25: 40712.276 | J25: 104756.77 | K25: 121136.78 | L25: 131987.32
B26: 20 | C26: IDFC First Bank Ltd. | D26: 144637.31 | E26: 200576.31 | F26: 252065.25 | G26: 61123.55 | H26: 74710.39 | I26: 80715.52 | J26: 151794.53 | K26: 194592.37 | L26: 233112.53
B27: 21 | C27: IDBI Ltd. | D27: 255490.05 | E27: 277657.22 | F27: 310294 | G27: 99689.74 | H27: 114934.24 | I27: 117468 | J27: 162567.72 | K27: 188620.61 | L27: 218399
B28: TOTAL OF NEW PVT BANKS [II] | D28: =SUM(D18:D27) -> 5477647.6 | E28: =SUM(E18:E27) -> 6624160 | F28: =SUM(F18:F27) -> 7466276 | G28: =SUM(G18:G27) -> 1655315.9 | H28: =SUM(H18:H27) -> 2083193.1 | I28: =SUM(I18:I27) -> 2377812.6 | J28: =SUM(J18:J27) -> 4732078.4 | K28: =SUM(K18:K27) -> 6126783.6 | L28: =SUM(L18:L27) -> 6654848.1
B29: TOTAL OF PVT BANKS [I+II] | D29: =D28+D16 -> 6299318.2 | E29: =E28+E16 -> 7561433.7 | F29: =F28+F16 -> 8502193.3 | G29: =G28+G16 -> 1894308.5 | H29: =H28+H16 -> 2323647.4 | I29: =I28+I16 -> 2637218.9 | J29: =J28+J16 -> 5366672.9 | K29: =K28+K16 -> 6861388.2 | L29: =L28+L16 -> 7476925
D30: =SUM(D29-#REF!)/#REF!*100 -> #REF! | E30: =SUM(E29-D29)/D29*100 -> 20.035748 | G30: =SUM(G29-#REF!)/#REF!*100 -> #REF! | H30: =SUM(H29-G29)/G29*100 -> 22.664679 | J30: =SUM(J29-#REF!)/#REF!*100 -> #REF! | K30: =SUM(K29-J29)/J29*100 -> 27.851806
B32: : 1 :
E33: =(E16-D16)/D16*100 -> 14.069272 | F33: =(F16-E16)/E16*100 -> 10.524515 | H33: =(H16-G16)/G16*100 -> 0.61159014 | I33: =(I16-H16)/H16*100 -> 7.8817417 | K33: =(K16-J16)/J16*100 -> 15.759696 | L33: =(L16-K16)/K16*100 -> 11.907398
E34: =(E28-D28)/D28*100 -> 20.930745 | F34: =(F28-E28)/E28*100 -> 12.712797 | H34: =(H28-G28)/G28*100 -> 25.848679 | I34: =(I28-H28)/H28*100 -> 14.142688 | K34: =(K28-J28)/J28*100 -> 29.473416 | L34: =(L28-K28)/K28*100 -> 8.6189518
E35: =(E29-D29)/D29*100 -> 20.035748 | F35: =(F29-E29)/E29*100 -> 12.44155 | H35: =(H29-G29)/G29*100 -> 22.664679 | I35: =(I29-H29)/H29*100 -> 13.494796 | K35: =(K29-J29)/J29*100 -> 27.851806 | L35: =(L29-K29)/K29*100 -> 8.9710244

Sheet Assets
B1: Statement II : Private Sector Banks : Assets/Gross and Net Non-Performing Assets
B2: As on March 31 | L2: (₹ Crore)
B3: S.No | C3: Banks | D3: Total Assets | G3: Gross NPA | J3: Net NPA
B4: I | C4: OLD PRIVATE SECTOR BANKS | D4: 2023 | E4: 2024 | F4: 2025 | G4: 2023 | H4: 2024 | I4: 2025 | J4: 2023 | K4: 2024 | L4: 2025
B5: 1 | C5: City Union Bank Ltd. | D5: 66594.56 | E5: 70825.868 | F5: 77623.215 | G5: 1920.16 | H5: 1854.43 | I5: 1638.1689 | J5: 1017.63 | K5: 898.677 | L5: 653.0666
B6: 2 | C6: Tamilnad Mercantile Bank Ltd. | D6: 57895 | E6: 61552.46 | F6: 66449.87 | G6: 521 | H6: 575.06 | I6: 556.13 | J6: 230 | K6: 335.82 | L6: 160.45
B7: 3 | C7: CSB Bank Ltd. | D7: 29162.28 | E7: 36055.99 | F7: 47836.27 | G7: 262.56 | H7: 361.07 | I7: 498.46 | J7: 71.82 | K7: 124.9 | L7: 163.53
B8: 4 | C8: Dhanlaxmi Bank Ltd | D8: 15132.13 | E8: 15961.89 | F8: 17936.94 | G8: 511.14 | H8: 421.21 | I8: 364.11 | J8: 109.2 | K8: 126.47 | L8: 117.94
B9: 5 | C9: The Federal Bank Ltd. | D9: 260341.83 | E9: 308311.8 | F9: 349004.8 | G9: 4183.77 | H9: 4528.87 | I9: 4375.54 | J9: 1205.01 | K9: 1255.33 | L9: 1040.38
B10: 6 | C10: The Jammu & Kashmir Bank Ltd. | D10: 145962.26 | E10: 154526.59 | F10: 169468.47 | G10: 5204.43 | H10: 3956.19 | I10: 3604.84 | J10: 1334.24 | K10: 736.85 | L10: 818.07
B11: 7 | C11: The Karnataka Bank Ltd. | D11: 99058.34 | E11: 116084.57 | F11: 120861.78 | G11: 2292.91 | H11: 2578.42 | I11: 2402.08 | J11: 1021.27 | K11: 1129.18 | L11: 1004.55
B12: 8 | C12: The Karur Vysya Bank Ltd. | D12: 90179.42 | E12: 105453.26 | F12: 119367.42 | G12: 1458.15 | H12: 1041.64 | I12: 641.8 | J12: 468.15 | K12: 297.97 | L12: 166.21
B13: 9 | C13: Nainital Bank Ltd. * | D13: 8656.6741 | E13: 9306.822 | F13: 9360.4822 | G13: 443.26 | H13: 398.67 | I13: 386.2 | J13: 78.33 | K13: 41.88 | L13: 25.92
B14: 10 | C14: RBL Bank | D14: 115876.18 | E14: 138432.21 | F14: 146725.48 | G14: 2419.86 | H14: 2270.97 | I14: 2465.47 | J14: 772.54 | K14: 619.3 | L14: 270.79
B15: 11 | C15: The South Indian Bank Ltd. | D15: 107698.18 | E15: 117412.79 | F15: 124655.12 | G15: 3708.26 | H15: 3620.34 | I15: 2799.83 | J15: 1293.61 | K15: 1134.58 | L15: 790.52
B16: TOTAL OF OLD PVT BANKS [I] | D16: =SUM(D5:D15) -> 996556.85 | E16: =SUM(E5:E15) -> 1133924.2 | F16: =SUM(F5:F15) -> 1249289.8 | G16: =SUM(G5:G15) -> 22925.5 | H16: =SUM(H5:H15) -> 21606.87 | I16: =SUM(I5:I15) -> 19732.629 | J16: =SUM(J5:J15) -> 7601.8 | K16: =SUM(K5:K15) -> 6700.957 | L16: =SUM(L5:L15) -> 5211.4266
B17: II | C17: NEW PRIVATE SECTOR BANKS
B18: 12 | C18: Axis Bank Ltd. | D18: 1317325.5 | E18: 1477208.6 | F18: 1609929.9 | G18: 18604.23 | H18: 15127.12 | I18: 14490.11 | J18: 3558.92 | K18: 3247.47 | L18: 3685.45
B19: 13 | C19: DCB Bank Ltd. | D19: 52365.87 | E19: 63036.97 | F19: 76809.78 | G19: 1122.84 | H19: 1353.47 | I19: 1554.43 | J19: 356.92 | K19: 454.33 | L19: 571.55
B20: 14 | C20: HDFC Bank Ltd. | D20: 2466081.5 | E20: 3617623.1 | F20: 3910198.9 | G20: 18019.03 | H20: 31173.32 | I20: 35222.64 | J20: 4368.43 | K20: 8091.74 | L20: 11320.43
B21: 15 | C21: ICICI Bank Ltd. | D21: 1584206.6 | E21: 1871514.6 | F21: 2118240 | G21: 31183.7 | H21: 27961.68 | I21: 24166.18 | J21: 5155.07 | K21: 5377.79 | L21: 5589.41
B22: 16 | C22: Indusind Bank Ltd. | D22: 457804.05 | E22: 514935.15 | F22: 554018.43 | G22: 5826.27 | H22: 6693.38 | I22: 11046.39 | J22: 1714.96 | K22: 1968.9 | L22: 3287.14
B23: 17 | C23: Kotak Mahindra Bank Ltd. | D23: 489862.48 | E23: 600357.05 | F23: 693624.18 | G23: 5768.32 | H23: 5274.78 | I23: 6133.85 | J23: 1193.3 | K23: 1270.57 | L23: 1343.44
B24: 18 | C24: YES Bank | D24: 354786.13 | E24: 405492.99 | F24: 423422.3 | G24: 4394.57 | H24: 3982.56 | I24: 3935.61 | J24: 1658.09 | K24: 1329.73 | L24: 800.14
B25: 19 | C25: Bandhan Bank | D25: 156037.09 | E25: 177841.66 | F25: 191476.29 | G25: 5298.62 | H25: 4784.88 | I25: 6435.56 | J25: 1228.27 | K25: 1347.61 | L25: 1692.8492
B26: 20 | C26: IDFC First Bank Ltd. | D26: 239941.66 | E26: 296115.1 | F26: 343818.65 | G26: 3884.45 | H26: 3718.36 | I26: 4433.58 | J26: 1304.05 | K26: 1160.46 | L26: 1229.92
B27: 21 | C27: IDBI Ltd. | D27: 330502.17 | E27: 363578 | F27: 411661 | G27: 10969 | H27: 8917 | I27: 6695 | J27: 1495 | K27: 644 | L27: 337
B28: TOTAL OF NEW PVT BANKS [II] | D28: =SUM(D18:D27) -> 7448913.1 | E28: =SUM(E18:E27) -> 9387703.2 | F28: =SUM(F18:F27) -> 10333199 | G28: =SUM(G18:G27) -> 105071.03 | H28: =SUM(H18:H27) -> 108986.55 | I28: =SUM(I18:I27) -> 114113.35 | J28: =SUM(J18:J27) -> 22033.01 | K28: =SUM(K18:K27) -> 24892.6 | L28: =SUM(L18:L27) -> 29857.329
B29: TOTAL OF PVT BANKS [I+II] | D29: =SUM(D16+D28) -> 8445470 | E29: =SUM(E16+E28) -> 10521627 | F29: =SUM(F16+F28) -> 11582489 | G29: =SUM(G16+G28) -> 127996.53 | H29: =SUM(H16+H28) -> 130593.42 | I29: =SUM(I16+I28) -> 133845.98 | J29: =SUM(J16+J28) -> 29634.81 | K29: =SUM(K16+K28) -> 31593.557 | L29: =SUM(L16+L28) -> 35068.756
B31: * Gross NPA amount excludes interest suspense amount.
B32: : 2 :
E33: =(E16-D16)/D16*100 -> 13.784201 | F33: =(F16-E16)/E16*100 -> 10.174013 | H33: =(H16-G16)/G16*100 -> -5.7518048 | I33: =(I16-H16)/H16*100 -> -8.6742832 | K33: =(K16-J16)/J16*100 -> -11.850391 | L33: =(L16-K16)/K16*100 -> -22.228622
E34: =(E28-D28)/D28*100 -> 26.027825 | F34: =(F28-E28)/E28*100 -> 10.071646 | H34: =(H28-G28)/G28*100 -> 3.7265457 | I34: =(I28-H28)/H28*100 -> 4.7040667 | K34: =(K28-J28)/J28*100 -> 12.978662 | L34: =(L28-K28)/K28*100 -> 19.944599
E35: =(E29-D29)/D29*100 -> 24.583089 | F35: =(F29-E29)/E29*100 -> 10.082678 | H35: =(H29-G29)/G29*100 -> 2.0288753 | I35: =(I29-H29)/H29*100 -> 2.4905994 | K35: =(K29-J29)/J29*100 -> 6.6096155 | L35: =(L29-K29)/K29*100 -> 10.999707

Sheet INCOME
B1: Statement III : Private Sector Banks : Income
B2: As on March 31 | L2: (₹ Crore)
B3: S.No | C3: Banks | D3: Interest Income | G3: Other Income | J3: Total Income
B4: I | C4: OLD PRIVATE SECTOR BANKS | D4: 2023 | E4: 2024 | F4: 2025 | G4: 2023 | H4: 2024 | I4: 2025 | J4: 2023 | K4: 2024 | L4: 2025
B5: 1 | C5: City Union Bank Ltd. | D5: 4714.33 | E5: 5270.565 | F5: 5834.0426 | G5: 810.36 | H5: 741.655 | I5: 898.0623 | J5: =D5+G5 -> 5524.69 | K5: =E5+H5 -> 6012.22 | L5: =F5+I5 -> 6732.1049
B6: 2 | C6: Tamilnad Mercantile Bank Ltd. | D6: 4081.04 | E6: 4847.91 | F6: 5291.26 | G6: 629.11 | H6: 644.94 | I6: 850.49 | J6: =D6+G6 -> 4710.15 | K6: =E6+H6 -> 5492.85 | L6: =F6+I6 -> 6141.75
B7: 3 | C7: CSB Bank Ltd. | D7: 2319.65 | E7: 2927.54 | F7: 3597.14 | G7: 315.68 | H7: 584.29 | I7: 972.06 | J7: =D7+G7 -> 2635.33 | K7: =E7+H7 -> 3511.83 | L7: =F7+I7 -> 4569.2
B8: 4 | C8: Dhanlaxmi Bank Ltd | D8: 1071.223 | E8: 1206.99 | F8: 1319.88 | G8: 74.52 | H8: 152.56 | I8: 169.2 | J8: =D8+G8 -> 1145.743 | K8: =E8+H8 -> 1359.55 | L8: =F8+I8 -> 1489.08
B9: 5 | C9: The Federal Bank Ltd. | D9: 16803.63 | E9: 22188.26 | F9: 26365.25 | G9: 2330 | H9: 3079.27 | I9: 3801.25 | J9: =D9+G9 -> 19133.63 | K9: =E9+H9 -> 25267.53 | L9: 30166.5
B10: 6 | C10: The Jammu & Kashmir Bank Ltd. | D10: 9355.11 | E10: 11212.37 | F10: 12535.86 | G10: 756.81 | H10: 825.48 | I10: 1136.81 | J10: =D10+G10 -> 10111.92 | K10: =E10+H10 -> 12037.85 | L10: =F10+I10 -> 13672.67
B11: 7 | C11: The Karnataka Bank Ltd. | D11: 7220.23 | E11: 8298.5 | F11: 9013.6 | G11: 992.58 | H11: 1318.92 | I11: 1269.52 | J11: =D11+G11 -> 8212.81 | K11: =E11+H11 -> 9617.42 | L11: =F11+I11 -> 10283.12
B12: 8 | C12: The Karur Vysya Bank Ltd. | D12: 6516.55 | E12: 8213.16 | F12: 9678.04 | G12: 1158.94 | H12: 1649.47 | I12: 1829.55 | J12: =D12+G12 -> 7675.49 | K12: =E12+H12 -> 9862.63 | L12: =F12+I12 -> 11507.59
B13: 9 | C13: Nainital Bank Ltd. | D13: 587.73 | E13: 692.1326 | F13: 710.4143 | G13: 14.82 | H13: 62.7883 | I13: 41.4398 | J13: =D13+G13 -> 602.55 | K13: =E13+H13 -> 754.9209 | L13: =F13+I13 -> 751.8541
B14: 10 | C14: RBL Bank | D14: 9676.58 | E14: 12394.3 | F14: 14039.07 | G14: 2489.43 | H14: 3042.89 | I14: 3806.18 | J14: =D14+G14 -> 12166.01 | K14: =E14+H14 -> 15437.19 | L14: =F14+I14 -> 17845.25
B15: 11 | C15: The South Indian Bank Ltd. | D15: 7233.18 | E15: 8612.8 | F15: 9413.31 | G15: 812.63 | H15: 1515.52 | I15: 1813.43 | J15: =D15+G15 -> 8045.81 | K15: =E15+H15 -> 10128.32 | L15: =F15+I15 -> 11226.74
B16: TOTAL OF OLD PVT BANKS [I] | D16: =SUM(D5:D15) -> 69579.253 | E16: =SUM(E5:E15) -> 85864.528 | F16: =SUM(F5:F15) -> 97797.867 | G16: =SUM(G5:G15) -> 10384.88 | H16: =SUM(H5:H15) -> 13617.783 | I16: =SUM(I5:I15) -> 16587.992 | J16: =SUM(J5:J15) -> 79964.133 | K16: =SUM(K5:K15) -> 99482.311 | L16: =SUM(L5:L15) -> 114385.86
B17: II | C17: NEW PRIVATE SECTOR BANKS
B18: 12 | C18: Axis Bank Ltd. | D18: 85163.77 | E18: 109368.63 | F18: 122677.04 | G18: 16143.42 | H18: 22441.96 | I18: 25257.06 | J18: =D18+G18 -> 101307.19 | K18: =E18+H18 -> 131810.59 | L18: =F18+I18 -> 147934.1
B19: 13 | C19: DCB Bank Ltd. | D19: 4200.27 | E19: 5362.04 | F19: 6470.59 | G19: 409.39 | H19: 474.24 | I19: 750.51 | J19: =D19+G19 -> 4609.66 | K19: =E19+H19 -> 5836.28 | L19: =F19+I19 -> 7221.1
B20: 14 | C20: HDFC Bank Ltd. | D20: 161585.55 | E20: 258340.56 | F20: 300517.04 | G20: 31214.83 | H20: 49240.99 | I20: 45632.28 | J20: =D20+G20 -> 192800.38 | K20: =E20+H20 -> 307581.55 | L20: =F20+I20 -> 346149.32
B21: 15 | C21: ICICI Bank Ltd. | D21: 109231.34 | E21: 142890.94 | F21: 163263.78 | G21: 19831.45 | H21: 22957.77 | I21: 28506.7 | J21: =D21+G21 -> 129062.79 | K21: =E21+H21 -> 165848.71 | L21: =F21+I21 -> 191770.48
B22: 16 | C22: Indusind Bank Ltd. | D22: 36367.91 | E22: 45748.21 | F22: 48667.67 | G22: 8166.37 | H22: 9387.85 | I22: 7684.19 | J22: =D22+G22 -> 44534.28 | K22: =E22+H22 -> 55136.06 | L22: =F22+I22 -> 56351.86
B23: 17 | C23: Kotak Mahindra Bank Ltd. | D23: 34250.85 | E23: 45798.91 | F23: 52919.73 | G23: 7083.05 | H23: 10273.1 | I23: 11418.49 | J23: =D23+G23 -> 41333.9 | K23: =E23+H23 -> 56072.01 | L23: =F23+I23 -> 64338.22
B24: 18 | C24: YES Bank | D24: 22697.43 | E24: 27585.94 | F24: 30894.91 | G24: 3685.06 | H24: 5114.3 | I24: 5856.86 | J24: =D24+G24 -> 26382.49 | K24: =E24+H24 -> 32700.24 | L24: =F24+I24 -> 36751.77
B25: 19 | C25: Bandhan Bank | D25: 15904.699 | E25: 18869.618 | F25: 21948.228 | G25: 2468.55 | H25: 2171.4199 | I25: 2966.6 | J25: 18373.25 | K25: =E25+H25 -> 21041.038 | L25: =F25+I25 -> 24914.828
B26: 20 | C26: IDFC First Bank Ltd. | D26: 22727.54 | E26: 30322.5 | F26: 36501.49 | G26: 4466.97 | H26: 6002 | I26: 7021.71 | J26: =D26+G26 -> 27194.51 | K26: =E26+H26 -> 36324.5 | L26: =F26+I26 -> 43523.2
B27: 21 | C27: IDBI Ltd. | D27: 20569.78 | E27: 26426.134 | F27: 28902 | G27: 4371.98 | H27: 3610.907 | I27: 4924 | J27: =D27+G27 -> 24941.76 | K27: =E27+H27 -> 30037.041 | L27: =F27+I27 -> 33826
B28: TOTAL OF NEW PVT BANKS [II] | D28: =SUM(D18:D27) -> 512699.14 | E28: =SUM(E18:E27) -> 710713.48 | F28: =SUM(F18:F27) -> 812762.48 | G28: =SUM(G18:G27) -> 97841.07 | H28: =SUM(H18:H27) -> 131674.54 | I28: =SUM(I18:I27) -> 140018.4 | J28: =SUM(J18:J27) -> 610540.21 | K28: =SUM(K18:K27) -> 842388.02 | L28: =SUM(L18:L27) -> 952780.88
B29: TOTAL OF PVT BANKS [I+II] | D29: =SUM(D16+D28) -> 582278.39 | E29: =SUM(E16+E28) -> 796578.01 | F29: =SUM(F16+F28) -> 910560.34 | G29: =SUM(G16+G28) -> 108225.95 | H29: =SUM(H16+H28) -> 145292.32 | I29: =SUM(I16+I28) -> 156606.39 | J29: =SUM(J16+J28) -> 690504.34 | K29: =SUM(K16+K28) -> 941870.33 | L29: =SUM(L16+L28) -> 1067166.7
B31: : 3 :
E32: =(E16-D16)/D16*100 -> 23.40536 | F32: =(F16-E16)/E16*100 -> 13.897869 | H32: =(H16-G16)/G16*100 -> 31.130868 | I32: =(I16-H16)/H16*100 -> 21.81125 | K32: =(K16-J16)/J16*100 -> 24.408666 | L32: =(L16-K16)/K16*100 -> 14.981104
E33: =(E28-D28)/D28*100 -> 38.621938 | F33: =(F28-E28)/E28*100 -> 14.358669 | H33: =(H28-G28)/G28*100 -> 34.580025 | I33: =(I28-H28)/H28*100 -> 6.3367324 | K33: =(K28-J28)/J28*100 -> 37.974208 | L33: =(L28-K28)/K28*100 -> 13.104752
E34: =(E29-D29)/D29*100 -> 36.803636 | F34: =(F29-E29)/E29*100 -> 14.308998 | H34: =(H29-G29)/G29*100 -> 34.24906 | I34: =(I29-H29)/H29*100 -> 7.7871094 | K34: =(K29-J29)/J29*100 -> 36.403245 | L34: =(L29-K29)/K29*100 -> 13.302936

Sheet EXP
B1: Statement IV : Private Sector Banks : Expenditure
B2: As on March 31 | L2: (₹ Crore)
B3: S.No | C3: Banks | D3: Interest Expended | G3: Operating Expenses | J3: Total Expenditure *
B4: I | C4: OLD PRIVATE SECTOR BANKS | D4: 2023 | E4: 2024 | F4: 2025 | G4: 2023 | H4: 2024 | I4: 2025 | J4: 2023 | K4: 2024 | L4: 2025
B5: 1 | C5: City Union Bank Ltd. | D5: 2551.54 | E5: 3147.1 | F5: 3518.3292 | G5: 1155.17 | H5: 1348.388 | I5: 1535.1495 | J5: =D5+G5 -> 3706.71 | K5: =E5+H5 -> 4495.488 | L5: =F5+I5 -> 5053.4787
B6: 2 | C6: Tamilnad Mercantile Bank Ltd. | D6: 1986.92 | E6: 2697.02 | F6: 2990.34 | G6: 1150.39 | H6: 1314.05 | I6: 1405.67 | J6: =D6+G6 -> 3137.31 | K6: =E6+H6 -> 4011.07 | L6: =F6+I6 -> 4396.01
B7: 3 | C7: CSB Bank Ltd. | D7: 985.81 | E7: 1451.13 | F7: 2120.97 | G7: 942.12 | H7: 1280.78 | I7: 1537.99 | J7: =D7+G7 -> 1927.93 | K7: =E7+H7 -> 2731.91 | L7: =F7+I7 -> 3658.96
B8: 4 | C8: Dhanlaxmi Bank Ltd | D8: 595.48 | E8: 748.54 | F8: 836.59 | G8: 427.07 | H8: 541.75 | I8: 557.39 | J8: =D8+G8 -> 1022.55 | K8: =E8+H8 -> 1290.29 | L8: =F8+I8 -> 1393.98
B9: 5 | C9: The Federal Bank Ltd. | D9: 9571.47 | E9: 13894.78 | F9: 16897.26 | G9: 4767.77 | H9: 6198.27 | I9: 7168.11 | J9: =D9+G9 -> 14339.24 | K9: =E9+H9 -> 20093.05 | L9: =F9+I9 -> 24065.37
B10: 6 | C10: The Jammu & Kashmir Bank Ltd. | D10: 4609.83 | E10: 6008.68 | F10: 6742.04 | G10: 3643.6 | H10: 3752.29 | I10: 4000.84 | J10: =D10+G10 -> 8253.43 | K10: =E10+H10 -> 9760.97 | L10: =F10+I10 -> 10742.88
B11: 7 | C11: The Karnataka Bank Ltd. | D11: 4035.13 | E11: 4999.78 | F11: 5703.22 | G11: 1969.45 | H11: 2454.33 | I11: 2752.86 | J11: =D11+G11 -> 6004.58 | K11: =E11+H11 -> 7454.11 | L11: =F11+I11 -> 8456.08
B12: 8 | C12: The Karur Vysya Bank Ltd. | D12: 3167.74 | E12: 4394.74 | F12: 5418.12 | G12: 2031.96 | H12: 2638.75 | I12: 2877.14 | J12: =D12+G12 -> 5199.7 | K12: =E12+H12 -> 7033.49 | L12: =F12+I12 -> 8295.26
B13: 9 | C13: Nainital Bank Ltd. | D13: 308.71 | E13: 372.0458 | F13: 399.5899 | G13: 216.9 | H13: 275.5897 | I13: 263.2381 | J13: =D13+G13 -> 525.61 | K13: =E13+H13 -> 647.6355 | L13: =F13+I13 -> 662.828
B14: 10 | C14: RBL Bank | D14: 4678.39 | E14: 6351.41 | F14: 7576.05 | G14: 5285.17 | H14: 6055.03 | I14: 6642.41 | J14: =D14+G14 -> 9963.56 | K14: =E14+H14 -> 12406.44 | L14: =F14+I14 -> 14218.46
B15: 11 | C15: The South Indian Bank Ltd. | D15: 4221.1 | E15: 5280.75 | F15: 5927.67 | G15: 2317.38 | H15: 2979.9 | I15: 3028.99 | J15: =D15+G15 -> 6538.48 | K15: =E15+H15 -> 8260.65 | L15: =F15+I15 -> 8956.66
B16: TOTAL OF OLD PVT BANKS [I] | D16: =SUM(D5:D15) -> 36712.12 | E16: =SUM(E5:E15) -> 49345.976 | F16: =SUM(F5:F15) -> 58130.179 | G16: =SUM(G5:G15) -> 23906.98 | H16: =SUM(H5:H15) -> 28839.128 | I16: =SUM(I5:I15) -> 31769.788 | J16: =SUM(J5:J15) -> 60619.1 | K16: =SUM(K5:K15) -> 78185.103 | L16: =SUM(L5:L15) -> 89899.967
B17: II | C17: NEW PRIVATE SECTOR BANKS
B18: 12 | C18: Axis Bank Ltd. | D18: 42218.02 | E18: 59474.15 | F18: 68329.22 | G18: 27040.86 | H18: 35213.28 | I18: 37499.95 | J18: =D18+G18 -> 69258.88 | K18: =E18+H18 -> 94687.43 | L18: =F18+I18 -> 105829.17
B19: 13 | C19: DCB Bank Ltd. | D19: 2483.26 | E19: 3434.14 | F19: 4364.02 | G19: 1339.67 | H19: 1537.7 | I19: 1820.08 | J19: =D19+G19 -> 3822.93 | K19: =E19+H19 -> 4971.84 | L19: =F19+I19 -> 6184.1
B20: 14 | C20: HDFC Bank Ltd. | D20: 74743.31 | E20: 149808.1 | F20: 177846.95 | G20: 47652.09 | H20: 63386.01 | I20: 68174.89 | J20: =D20+G20 -> 122395.4 | K20: =E20+H20 -> 213194.11 | L20: =F20+I20 -> 246021.84
B21: 15 | C21: ICICI Bank Ltd. | D21: 47102.74 | E21: 68585.22 | F21: 82099.34 | G21: 32873.24 | H21: 39132.73 | I21: 42372.32 | J21: =D21+G21 -> 79975.98 | K21: =E21+H21 -> 107717.95 | L21: =F21+I21 -> 124471.66
B22: 16 | C22: Indusind Bank Ltd. | D22: 18775.8 | E22: 25132.3 | F22: 29636.35 | G22: 11412 | H22: 14263.49 | I22: 16070.65 | J22: =D22+G22 -> 30187.8 | K22: =E22+H22 -> 39395.79 | L22: =F22+I22 -> 45707
B23: 17 | C23: Kotak Mahindra Bank Ltd. | D23: 12698.93 | E23: 19805.71 | F23: 24577.95 | G23: =5519.83+8267.16 -> 13786.99 | H23: =6856.37+9822.48 -> 16678.85 | I23: 18753.7 | J23: =D23+G23 -> 26485.92 | K23: =E23+H23 -> 36484.56 | L23: =F23+I23 -> 43331.65
B24: 18 | C24: YES Bank | D24: 14779.86 | E24: 19491.32 | F24: 21950.56 | G24: 8419.87 | H24: 9822.66 | I24: 10547.26 | J24: =D24+G24 -> 23199.73 | K24: =E24+H24 -> 29313.98 | L24: =F24+I24 -> 32497.82
B25: 19 | C25: Bandhan Bank | D25: 6645.08 | E25: 8550.7766 | F25: 10457.645 | G25: 4636.819 | H25: 5850.777 | I25: 7068.4951 | J25: =D25+G25 -> 11281.899 | K25: =E25+H25 -> 14401.554 | L25: =F25+I25 -> 17526.14
B26: 20 | C26: IDFC First Bank Ltd. | D26: 10092.21 | E26: 13871.75 | F26: 17209.52 | G26: 12170.35 | H26: 16215.78 | I26: 18898.83 | J26: =D26+G26 -> 22262.56 | K26: =E26+H26 -> 30087.53 | L26: =F26+I26 -> 36108.35
B27: 21 | C27: IDBI Ltd. | D27: 9139.2316 | E27: 12239.695 | F27: 14276 | G27: 7066.7 | H27: 8205.296 | I27: 8472 | J27: =D27+G27 -> 16205.932 | K27: =E27+H27 -> 20444.991 | L27: =F27+I27 -> 22748
B28: TOTAL OF NEW PVT BANKS [II] | D28: =SUM(D18:D27) -> 238678.44 | E28: =SUM(E18:E27) -> 380393.16 | F28: =SUM(F18:F27) -> 450747.56 | G28: =SUM(G18:G27) -> 166398.59 | H28: =SUM(H18:H27) -> 210306.57 | I28: =SUM(I18:I27) -> 229678.18 | J28: =SUM(J18:J27) -> 405077.03 | K28: =SUM(K18:K27) -> 590699.73 | L28: =SUM(L18:L27) -> 680425.73
B29: TOTAL OF PVT BANKS [I+II] | D29: =D28+D16 -> 275390.56 | E29: =E28+E16 -> 429739.14 | F29: =F28+F16 -> 508877.73 | G29: =G28+G16 -> 190305.57 | H29: =H28+H16 -> 239145.7 | I29: =I28+I16 -> 261447.96 | J29: =J28+J16 -> 465696.13 | K29: =K28+K16 -> 668884.84 | L29: =L28+L16 -> 770325.7
B31: * Excludes provisions & contingencies.
B32: : 4 :
E33: =(E16-D16)/D16*100 -> 34.41331 | F33: =(F16-E16)/E16*100 -> 17.801256 | H33: =(H16-G16)/G16*100 -> 20.630576 | I33: =(I16-H16)/H16*100 -> 10.162096 | K33: =(K16-J16)/J16*100 -> 28.977671 | L33: =(L16-K16)/K16*100 -> 14.983498
E34: =(E28-D28)/D28*100 -> 59.374747 | F34: =(F28-E28)/E28*100 -> 18.495178 | H34: =(H28-G28)/G28*100 -> 26.387233 | I34: =(I28-H28)/H28*100 -> 9.2111254 | K34: =(K28-J28)/J28*100 -> 45.824051 | L34: =(L28-K28)/K28*100 -> 15.189781
E35: =(E29-D29)/D29*100 -> 56.047155 | F35: =(F29-E29)/E29*100 -> 18.415497 | H35: =(H29-G29)/G29*100 -> 25.664058 | I35: =(I29-H29)/H29*100 -> 9.3258051 | K35: =(K29-J29)/J29*100 -> 43.631178 | L35: =(L29-K29)/K29*100 -> 15.165669

Sheet Profit
B1: Statement V : Private Sector Banks : Profit
B2: As on March 31 | L2: (₹ Crore)
B3: S.No | C3: Banks | D3: Operating Profit | G3: Provisions & Contingencies | J3: Net Profit
B4: I | C4: OLD PRIVATE SECTOR BANKS | D4: 2023 | E4: 2024 | F4: 2025 | G4: 2023 | H4: 2024 | I4: 2025 | J4: 2023 | K4: 2024 | L4: 2025
B5: 1 | C5: City Union Bank Ltd. | D5: 1817.97 | E5: 1516.73 | F5: 1678.6262 | G5: =640.5+240 -> 880.5 | H5: =286+215 -> 501 | I5: =262+293 -> 555 | J5: 937.47 | K5: 1015.73 | L5: 1123.6262
B6: 2 | C6: Tamilnad Mercantile Bank Ltd. | D6: 1572.84 | E6: 1481.78 | F6: 1745.74 | G6: =179.2+364.38 -> 543.58 | H6: =88.2+321.55 -> 409.75 | I6: =170.85+392.28 -> 563.13 | J6: 1029.26 | K6: 1072.03 | L6: 1182.61
B7: 3 | C7: CSB Bank Ltd. | D7: 707.4 | E7: 779.92 | F7: 910.24 | G7: =-26.21+186.25 -> 160.04 | H7: =18.48+194.62 -> 213.1 | I7: =110.71+205.73 -> 316.44 | J7: 547.36 | K7: 566.82 | L7: 593.8
B8: 4 | C8: Dhanlaxmi Bank Ltd | D8: 123.2 | E8: =INCOME!K8-EXP!K8 -> 69.26 | F8: =INCOME!L8-EXP!L8 -> 95.1 | G8: =91.59-17.75 -> 73.84 | H8: =12.66-1.22 -> 11.44 | I8: =23.48+4.98 -> 28.46 | J8: 49.36 | K8: 57.82 | L8: 66.64
B9: 5 | C9: The Federal Bank Ltd. | D9: 4794.39 | E9: 5174.48 | F9: =INCOME!L9-EXP!L9 -> 6101.13 | G9: =749.89+1033.91 -> 1783.8 | H9: =196.1+1257.78 -> 1453.88 | I9: =733.06+1316.18 -> 2049.24 | J9: 3010.59 | K9: 3720.6 | L9: 4051.89
B10: 6 | C10: The Jammu & Kashmir Bank Ltd. | D10: 1858.49 | E10: 2276.88 | F10: =INCOME!L10-EXP!L10 -> 2929.79 | G10: =74.13+586.98 -> 661.11 | H10: =617.3-107.69 -> 509.61 | I10: =851.24-3.91 -> 847.33 | J10: 1197.38 | K10: 1767.27 | L10: 2082.46
B11: 7 | C11: The Karnataka Bank Ltd. | D11: 2208.23 | E11: 2163.31 | F11: =INCOME!L11-EXP!L11 -> 1827.04 | G11: =767.19+260.8 -> 1027.99 | H11: =600.58+256.45 -> 857.03 | I11: =186.44+368.23 -> 554.67 | J11: 1180.24 | K11: 1306.28 | L11: 1272.37
B12: 8 | C12: The Karur Vysya Bank Ltd. | D12: 2475.79 | E12: 2829.14 | F12: =INCOME!L12-EXP!L12 -> 3212.33 | G12: =1038.93+330.77 -> 1369.7 | H12: =728.95+495.38 -> 1224.33 | I12: =621.6+649.09 -> 1270.69 | J12: 1106.09 | K12: 1604.81 | L12: 1941.64
B13: 9 | C13: Nainital Bank Ltd. | D13: =INCOME!J13-EXP!J13 -> 76.94 | E13: =INCOME!K13-EXP!K13 -> 107.2854 | F13: =INCOME!L13-EXP!L13 -> 89.0261 | G13: 30.6267 | H13: 60.1868 | I13: 38.4161 | J13: 46.31 | K13: 47.0966 | L13: 50.61
B14: 10 | C14: RBL Bank | D14: 2202.45 | E14: 3030.75 | F14: 3626.79 | G14: =1021.94+297.78 -> 1319.72 | H14: =1778.47+84.36 -> 1862.83 | I14: =2958.66-27.24 -> 2931.42 | J14: 882.73 | K14: 1167.92 | L14: 695.37
B15: 11 | C15: The South Indian Bank Ltd. | D15: =INCOME!J15-EXP!J15 -> 1507.33 | E15: =INCOME!K15-EXP!K15 -> 1867.67 | F15: =INCOME!L15-EXP!L15 -> 2270.08 | G15: =399.12+333.12 -> 732.24 | H15: =338.92+458.67 -> 797.59 | I15: =513.19+454.01 -> 967.2 | J15: 775.09 | K15: 1070.08 | L15: 1302.88
B16: TOTAL OF OLD PVT BANKS [I] | D16: =SUM(D5:D15) -> 19345.03 | E16: =SUM(E5:E15) -> 21297.205 | F16: =SUM(F5:F15) -> 24485.892 | G16: =SUM(G5:G15) -> 8583.1467 | H16: =SUM(H5:H15) -> 7900.7468 | I16: =SUM(I5:I15) -> 10121.996 | J16: =SUM(J5:J15) -> 10761.88 | K16: =SUM(K5:K15) -> 13396.457 | L16: =SUM(L5:L15) -> 14363.896
B17: II | C17: NEW PRIVATE SECTOR BANKS
B18: 12 | C18: Axis Bank Ltd. | D18: =INCOME!J18-EXP!J18 -> 32048.31 | E18: =INCOME!K18-EXP!K18 -> 37123.16 | F18: 42104.93 | G18: =2652.64+12489.82+7326.17 -> 22468.63 | H18: =4063.09+8198.64 -> 12261.73 | I18: 15731.45 | J18: 9579.68 | K18: 24861.43 | L18: 26373.48
B19: 13 | C19: DCB Bank Ltd. | D19: =INCOME!J19-EXP!J19 -> 786.73 | E19: =INCOME!K19-EXP!K19 -> 864.44 | F19: =INCOME!L19-EXP!L19 -> 1037 | G19: =159.17+162 -> 321.17 | H19: =142.48+185.99 -> 328.47 | I19: =208.39+213.28 -> 421.67 | J19: 465.56 | K19: 535.97 | L19: 615.33
B20: 14 | C20: HDFC Bank Ltd. | D20: 70404.98 | E20: 94387.44 | F20: 100127.48 | G20: =11919.67+14376.6 -> 26296.27 | H20: =23492.14+10083.03 -> 33575.17 | I20: =11649.42+21130.7 -> 32780.12 | J20: 44108.71 | K20: 60812.27 | L20: 67347.36
B21: 15 | C21: ICICI Bank Ltd. | D21: =INCOME!J21-EXP!J21 -> 49086.81 | E21: =INCOME!K21-EXP!K21 -> 58130.76 | F21: =INCOME!L21-EXP!L21 -> 67298.82 | G21: =6665.58+10524.73 -> 17190.31 | H21: =3642.93+13599.56 -> 17242.49 | I21: =4682.62+15389.21 -> 20071.83 | J21: 31896.5 | K21: 40888.27 | L21: 47226.99
B22: 16 | C22: Indusind Bank Ltd. | D22: 14346.48 | E22: =INCOME!K22-EXP!K22 -> 15740.27 | F22: =INCOME!L22-EXP!L22 -> 10644.86 | G22: =4486.83+2469.93 -> 6956.76 | H22: =3798.74+2991.75 -> 6790.49 | I22: =7030.14+971.82 -> 8001.96 | J22: 7389.72 | K22: 8949.78 | L22: 2642.9
B23: 17 | C23: Kotak Mahindra Bank Ltd. | D23: =INCOME!J23-EXP!J23 -> 14847.98 | E23: =INCOME!K23-EXP!K23 -> 19587.45 | F23: =INCOME!L23-EXP!L23 -> 21006.57 | G23: =456.99+3451.69 -> 3908.68 | H23: =1573.73+4232.14 -> 5805.87 | I23: =2942.36+5134.03-3519.9 -> 4556.49 | J23: 10939.3 | K23: 13781.58 | L23: 16450.08
B24: 18 | C24: YES Bank | D24: 3182.76 | E24: =INCOME!K24-EXP!K24 -> 3386.26 | F24: =INCOME!L24-EXP!L24 -> 4253.95 | G24: =2219.85+245.51 -> 2465.36 | H24: =1886.28+248.9 -> 2135.18 | I24: =1085.61+762.48 -> 1848.09 | J24: 717.4 | K24: 1251.08 | L24: 2405.86
B25: 19 | C25: Bandhan Bank | D25: 7091.349 | E25: =INCOME!K25-EXP!K25 -> 6639.4843 | F25: =INCOME!L25-EXP!L25 -> 7388.6878 | G25: =4198.365+698.346 -> 4896.711 | H25: =3696.571+713.349 -> 4409.92 | I25: =3765.4115+877.9815 -> 4643.393 | J25: 2194.638 | K25: 2229.562 | L25: 2745.2955
B26: 20 | C26: IDFC First Bank Ltd. | D26: 4931.95 | E26: 6236.97 | F26: 7414.85 | G26: =1664.82+830 -> 2494.82 | H26: =2381.65+898.81 -> 3280.46 | I26: =5514.73+375.27 -> 5890 | J26: 2437.13 | K26: 2956.51 | L26: 1524.85
B27: 21 | C27: IDBI Ltd. | D27: =INCOME!J27-EXP!J27 -> 8735.8284 | E27: =INCOME!K27-EXP!K27 -> 9592.0501 | F27: =INCOME!L27-EXP!L27 -> 11078 | G27: =3497.86+1592.88 -> 5090.74 | H27: 3957.95 | I27: =510+3053 -> 3563 | J27: 3645.09 | K27: 5634.09 | L27: 7515
B28: TOTAL OF NEW PVT BANKS [II] | D28: =SUM(D18:D27) -> 205463.18 | E28: =SUM(E18:E27) -> 251688.28 | F28: =SUM(F18:F27) -> 272355.15 | G28: =SUM(G18:G27) -> 92089.451 | H28: =SUM(H18:H27) -> 89787.73 | I28: =SUM(I18:I27) -> 97508.003 | J28: =SUM(J18:J27) -> 113373.73 | K28: =SUM(K18:K27)+0.01 -> 161900.55 | L28: =SUM(L18:L27) -> 174847.15
B29: TOTAL OF PVT BANKS [I+II] | D29: =D28+D16 -> 224808.21 | E29: =E28+E16 -> 272985.49 | F29: =F28+F16 -> 296841.04 | G29: =G28+G16 -> 100672.6 | H29: =H28+H16 -> 97688.477 | I29: =I28+I16 -> 107630 | J29: =J28+J16 -> 124135.61 | K29: =K28+K16 -> 175297.01 | L29: =L28+L16 -> 189211.04
E31: =(E16-D16)/D16*100 -> 10.091354 | F31: =(F16-E16)/E16*100 -> 14.972325 | H31: =(H16-G16)/G16*100 -> -7.950463 | I31: =(I16-H16)/H16*100 -> 28.114422 | K31: =(K16-J16)/J16*100 -> 24.480635 | L31: =(L16-K16)/K16*100 -> 7.2216081
E32: =(E28-D28)/D28*100 -> 22.498001 | F32: =(F28-E28)/E28*100 -> 8.2112934 | H32: =(H28-G28)/G28*100 -> -2.4994405 | I32: =(I28-H28)/H28*100 -> 8.5983608 | K32: =(K28-J28)/J28*100 -> 42.80253 | L32: =(L28-K28)/K28*100 -> 7.9966333
E33: =(E29-D29)/D29*100 -> 21.430393 | F33: =(F29-E29)/E29*100 -> 8.7387613 | H33: =(H29-G29)/G29*100 -> -2.9641839 | I33: =(I29-H29)/H29*100 -> 10.17676 | K33: =(K29-J29)/J29*100 -> 41.214122 | L33: =(L29-K29)/K29*100 -> 7.9374048
B34: : 5 :

Sheet CDRatio
B1: Statement VI : Private Sector Banks : Ratios
B2: As on March 31 | L2: (In Per cent)
B3: S.No | C3: Banks | D3: Credit Deposit Ratio | G3: Investment Deposit Ratio | J3: Spread as % of Assets | N3: Provisioning Coverage Ratio
B4: I | C4: OLD PRIVATE SECTOR BANKS | D4: 2023 | E4: 2024 | F4: 2025 | G4: 2023 | H4: 2024 | I4: 2025 | J4: 2023 | K4: 2024 | L4: 2025 | N4: 2024 | O4: 2025
B5: 1 | C5: City Union Bank Ltd. | D5: =(DEPO!J5/DEPO!D5)*100 -> 82.166234 | E5: =(DEPO!K5/DEPO!E5)*100 -> 81.797462 | F5: =(DEPO!L5/DEPO!F5)*100 -> 81.984215 | G5: =(DEPO!G5/DEPO!D5)*100 -> 27.353451 | H5: =(DEPO!H5/DEPO!E5)*100 -> 28.144189 | I5: =(DEPO!I5/DEPO!F5)*100 -> 27.28986 | J5: =(INCOME!D5-EXP!D5)/Assets!D5*100 -> 3.2476977 | K5: =(INCOME!E5-EXP!E5)/Assets!E5*100 -> 2.9981489 | L5: =(INCOME!F5-EXP!F5)/Assets!F5*100 -> 2.9832743 | N5: 72 | O5: 78
B6: 2 | C6: Tamilnad Mercantile Bank Ltd. | D6: =(DEPO!J6/DEPO!D6)*100 -> 78.068082 | E6: =(DEPO!K6/DEPO!E6)*100 -> 80.245772 | F6: =(DEPO!L6/DEPO!F6)*100 -> 81.923118 | G6: =(DEPO!G6/DEPO!D6)*100 -> 29.636143 | H6: =(DEPO!H6/DEPO!E6)*100 -> 30.824151 | I6: =(DEPO!I6/DEPO!F6)*100 -> 28.126453 | J6: =(INCOME!D6-EXP!D6)/Assets!D6*100 -> 3.6170999 | K6: =(INCOME!E6-EXP!E6)/Assets!E6*100 -> 3.4944014 | L6: =(INCOME!F6-EXP!F6)/Assets!F6*100 -> 3.4626403 | N6: 87.52 | O6: 71.02
B7: 3 | C7: CSB Bank Ltd. | D7: =(DEPO!J7/DEPO!D7)*100 -> 84.268384 | E7: =(DEPO!K7/DEPO!E7)*100 -> 81.886146 | F7: =(DEPO!L7/DEPO!F7)*100 -> 85.474163 | G7: =(DEPO!G7/DEPO!D7)*100 -> 23.866585 | H7: =(DEPO!H7/DEPO!E7)*100 -> 25.409606 | I7: =(DEPO!I7/DEPO!F7)*100 -> 30.897666 | J7: =(INCOME!D7-EXP!D7)/Assets!D7*100 -> 4.5738536 | K7: =(INCOME!E7-EXP!E7)/Assets!E7*100 -> 4.0947704 | L7: =(INCOME!F7-EXP!F7)/Assets!F7*100 -> 3.0858802 | N7: 86.44 | O7: 83.71
B8: 4 | C8: Dhanlaxmi Bank Ltd | D8: =(DEPO!J8/DEPO!D8)*100 -> 70.789153 | E8: =(DEPO!K8/DEPO!E8)*100 -> 70.692378 | F8: =(DEPO!L8/DEPO!F8)*100 -> 74.684031 | G8: =(DEPO!G8/DEPO!D8)*100 -> 29.12479 | H8: =(DEPO!H8/DEPO!E8)*100 -> 27.587925 | I8: =(DEPO!I8/DEPO!F8)*100 -> 24.698925 | J8: =(INCOME!D8-EXP!D8)/Assets!D8*100 -> 3.1439262 | K8: =(INCOME!E8-EXP!E8)/Assets!E8*100 -> 2.8721536 | L8: =(INCOME!F8-EXP!F8)/Assets!F8*100 -> 2.6943838 | N8: 88.32
B9: 5 | C9: The Federal Bank Ltd. | D9: =(DEPO!J9/DEPO!D9)*100 -> 81.751777 | E9: =(DEPO!K9/DEPO!E9)*100 -> 82.92084 | F9: =(DEPO!L9/DEPO!F9)*100 -> 82.791639 | G9: =(DEPO!G9/DEPO!D9)*100 -> 22.955274 | H9: =(DEPO!H9/DEPO!E9)*100 -> 24.099537 | I9: =(DEPO!I9/DEPO!F9)*100 -> 23.35491 | J9: =(INCOME!D9-EXP!D9)/Assets!D9*100 -> 2.7779477 | K9: =(INCOME!E9-EXP!E9)/Assets!E9*100 -> 2.6899652 | L9: =(INCOME!F9-EXP!F9)/Assets!F9*100 -> 2.7128538 | N9: 82.68 | O9: 75.37
B10: 6 | C10: The Jammu & Kashmir Bank Ltd. | D10: =(DEPO!J10/DEPO!D10)*100 -> 67.426089 | E10: =(DEPO!K10/DEPO!E10)*100 -> 69.568979 | F10: =(DEPO!L10/DEPO!F10)*100 -> 70.134683 | G10: =(DEPO!G10/DEPO!D10)*100 -> 28.539594 | H10: =(DEPO!H10/DEPO!E10)*100 -> 25.959093 | I10: =(DEPO!I10/DEPO!F10)*100 -> 27.739658 | J10: =(INCOME!D10-EXP!D10)/Assets!D10*100 -> 3.2510322 | K10: =(INCOME!E10-EXP!E10)/Assets!E10*100 -> 3.3675046 | L10: =(INCOME!F10-EXP!F10)/Assets!F10*100 -> 3.4188189 | N10: 91.58 | O10: 90.28
B11: 7 | C11: The Karnataka Bank Ltd. | D11: =(DEPO!J11/DEPO!D11)*100 -> 68.619647 | E11: =(DEPO!K11/DEPO!E11)*100 -> 72.976772 | F11: =(DEPO!L11/DEPO!F11)*100 -> 73.030544 | G11: =(DEPO!G11/DEPO!D11)*100 -> 26.698983 | H11: =(DEPO!H11/DEPO!E11)*100 -> 24.800991 | I11: =(DEPO!I11/DEPO!F11)*100 -> 23.411027 | J11: =(INCOME!D11-EXP!D11)/Assets!D11*100 -> 3.2153779 | K11: =(INCOME!E11-EXP!E11)/Assets!E11*100 -> 2.8416524 | L11: =(INCOME!F11-EXP!F11)/Assets!F11*100 -> 2.73898 | N11: 79.22 | O11: 78
B12: 8 | C12: The Karur Vysya Bank Ltd. | D12: =(DEPO!J12/DEPO!D12)*100 -> 82.380133 | E12: =(DEPO!K12/DEPO!E12)*100 -> 82.667749 | F12: =(DEPO!L12/DEPO!F12)*100 -> 82.294469 | G12: =(DEPO!G12/DEPO!D12)*100 -> 24.541902 | H12: =(DEPO!H12/DEPO!E12)*100 -> 25.073323 | I12: =(DEPO!I12/DEPO!F12)*100 -> 23.34612 | J12: =(INCOME!D12-EXP!D12)/Assets!D12*100 -> 3.7134969 | K12: =(INCOME!E12-EXP!E12)/Assets!E12*100 -> 3.6209597 | L12: =(INCOME!F12-EXP!F12)/Assets!F12*100 -> 3.568746 | N12: 94.85
B13: 9 | C13: Nainital Bank Ltd. | D13: =(DEPO!J13/DEPO!D13)*100 -> 56.198115 | E13: =(DEPO!K13/DEPO!E13)*100 -> 54.64422 | F13: =(DEPO!L13/DEPO!F13)*100 -> 56.492726 | G13: =(DEPO!G13/DEPO!D13)*100 -> 277.30717 | H13: =(DEPO!H13/DEPO!E13)*100 -> 24.058235 | I13: =(DEPO!I13/DEPO!F13)*100 -> 22.491848 | J13: =(INCOME!D13-EXP!D13)/Assets!D13*100 -> 3.2231778 | K13: =(INCOME!E13-EXP!E13)/Assets!E13*100 -> 3.4392707 | L13: =(INCOME!F13-EXP!F13)/Assets!F13*100 -> 3.3206024 | N13: 89.22 | O13: 92.67
B14: 10 | C14: RBL Bank | D14: =(DEPO!J14/DEPO!D14)*100 -> 82.709658 | E14: =(DEPO!K14/DEPO!E14)*100 -> 81.151801 | F14: =(DEPO!L14/DEPO!F14)*100 -> 83.482354 | G14: =(DEPO!G14/DEPO!D14)*100 -> 34.016532 | H14: =(DEPO!H14/DEPO!E14)*100 -> 28.577468 | I14: =(DEPO!I14/DEPO!F14)*100 -> 28.992002 | J14: =(INCOME!D14-EXP!D14)/Assets!D14*100 -> 4.3133887 | K14: =(INCOME!E14-EXP!E14)/Assets!E14*100 -> 4.3652341 | L14: =(INCOME!F14-EXP!F14)/Assets!F14*100 -> 4.4048382 | N14: 72.73 | O14: 96.4
B15: 11 | C15: The South Indian Bank Ltd. | D15: =(DEPO!J15/DEPO!D15)*100 -> 76.163024 | E15: =(DEPO!K15/DEPO!E15)*100 -> 76.589924 | F15: =(DEPO!L15/DEPO!F15)*100 -> 79.685275 | G15: =(DEPO!G15/DEPO!D15)*100 -> 26.886456 | H15: =(DEPO!H15/DEPO!E15)*100 -> 23.525274 | I15: =(DEPO!I15/DEPO!F15)*100 -> 20.253019 | J15: =(INCOME!D15-EXP!D15)/Assets!D15*100 -> 2.7967789 | K15: =(INCOME!E15-EXP!E15)/Assets!E15*100 -> 2.8378936 | L15: =(INCOME!F15-EXP!F15)/Assets!F15*100 -> 2.7962269 | N15: 79.1
B16: AVERAGE OF OLD PVT BANKS [I] | D16: =(DEPO!J16/DEPO!D16)*100 -> 77.232215 | E16: =(DEPO!K16/DEPO!E16)*100 -> 78.376741 | F16: =(DEPO!L16/DEPO!F16)*100 -> 79.357391 | G16: =(DEPO!G16/DEPO!D16)*100 -> 29.086185 | H16: =(DEPO!H16/DEPO!E16)*100 -> 25.654651 | I16: =(DEPO!I16/DEPO!F16)*100 -> 25.041217 | J16: =(INCOME!D16-EXP!D16)/Assets!D16*100 -> 3.298069 | K16: =(INCOME!E16-EXP!E16)/Assets!E16*100 -> 3.220546 | L16: =(INCOME!F16-EXP!F16)/Assets!F16*100 -> 3.1752189
B17: II | C17: NEW PRIVATE SECTOR BANKS
B18: 12 | C18: Axis Bank Ltd. | D18: =(DEPO!J18/DEPO!D18)*100 -> 89.266288 | E18: =(DEPO!K18/DEPO!E18)*100 -> 90.307973 | F18: =(DEPO!L18/DEPO!F18)*100 -> 88.734347 | G18: =(DEPO!G18/DEPO!D18)*100 -> 30.499635 | H18: =(DEPO!H18/DEPO!E18)*100 -> 31.023246 | I18: =(DEPO!I18/DEPO!F18)*100 -> 33.77306 | J18: =(INCOME!D18-EXP!D18)/Assets!D18*100 -> 3.2600712 | K18: =(INCOME!E18-EXP!E18)/Assets!E18*100 -> 3.3776191 | L18: =(INCOME!F18-EXP!F18)/Assets!F18*100 -> 3.375788 | N18: 94.07 | O18: 75
B19: 13 | C19: DCB Bank Ltd. | D19: =(DEPO!J19/DEPO!D19)*100 -> 83.363115 | E19: =(DEPO!K19/DEPO!E19)*100 -> 82.922082 | F19: =(DEPO!L19/DEPO!F19)*100 -> 85.03432 | G19: =(DEPO!G19/DEPO!D19)*100 -> 30.511136 | H19: =(DEPO!H19/DEPO!E19)*100 -> 32.846717 | I19: =(DEPO!I19/DEPO!F19)*100 -> 33.565852 | J19: =(INCOME!D19-EXP!D19)/Assets!D19*100 -> 3.2788723 | K19: =(INCOME!E19-EXP!E19)/Assets!E19*100 -> 3.058364 | L19: =(INCOME!F19-EXP!F19)/Assets!F19*100 -> 2.7425804 | N19: 77.3 | O19: 74.48
B20: 14 | C20: HDFC Bank Ltd. | D20: =(DEPO!J20/DEPO!D20)*100 -> 84.984095 | E20: =(DEPO!K20/DEPO!E20)*100 -> 104.41532 | F20: =(DEPO!L20/DEPO!F20)*100 -> 96.496638 | G20: =(DEPO!G20/DEPO!D20)*100 -> 27.45051 | H20: =(DEPO!H20/DEPO!E20)*100 -> 29.515884 | I20: =(DEPO!I20/DEPO!F20)*100 -> 30.80838 | J20: =(INCOME!D20-EXP!D20)/Assets!D20*100 -> 3.5214668 | K20: =(INCOME!E20-EXP!E20)/Assets!E20*100 -> 3.0001042 | L20: =(INCOME!F20-EXP!F20)/Assets!F20*100 -> 3.1371828 | N20: 74.04 | O20: 76.2
B21: 15 | C21: ICICI Bank Ltd. | D21: =(DEPO!J21/DEPO!D21)*100 -> 86.348507 | E21: =(DEPO!K21/DEPO!E21)*100 -> 83.832494 | F21: =(DEPO!L21/DEPO!F21)*100 -> 83.321502 | G21: =(DEPO!G21/DEPO!D21)*100 -> 30.684048 | H21: =(DEPO!H21/DEPO!E21)*100 -> 32.696356 | I21: =(DEPO!I21/DEPO!F21)*100 -> 31.344575 | J21: =(INCOME!D21-EXP!D21)/Assets!D21*100 -> 3.9217485 | K21: =(INCOME!E21-EXP!E21)/Assets!E21*100 -> 3.9703522 | L21: =(INCOME!F21-EXP!F21)/Assets!F21*100 -> 3.8316924 | N21: 80.31 | O21: 76.2
B22: 16 | C22: Indusind Bank Ltd. | D22: =(DEPO!J22/DEPO!D22)*100 -> 86.174439 | E22: =(DEPO!K22/DEPO!E22)*100 -> 89.216369 | F22: =(DEPO!L22/DEPO!F22)*100 -> 83.930182 | G22: =(DEPO!G22/DEPO!D22)*100 -> 24.70475 | H22: =(DEPO!H22/DEPO!E22)*100 -> 27.684166 | I22: =(DEPO!I22/DEPO!F22)*100 -> 27.852807 | J22: =(INCOME!D22-EXP!D22)/Assets!D22*100 -> 3.8427161 | K22: =(INCOME!E22-EXP!E22)/Assets!E22*100 -> 4.0035935 | L22: =(INCOME!F22-EXP!F22)/Assets!F22*100 -> 3.435142 | N22: 70.58
B23: 17 | C23: Kotak Mahindra Bank Ltd. | D23: =(DEPO!J23/DEPO!D23)*100 -> 88.092726 | E23: =(DEPO!K23/DEPO!E23)*100 -> 83.767041 | F23: =(DEPO!L23/DEPO!F23)*100 -> 85.543495 | G23: =(DEPO!G23/DEPO!D23)*100 -> 33.435707 | H23: =(DEPO!H23/DEPO!E23)*100 -> 34.614648 | I23: =(DEPO!I23/DEPO!F23)*100 -> 36.450372 | J23: =(INCOME!D23-EXP!D23)/Assets!D23*100 -> 4.3995858 | K23: =(INCOME!E23-EXP!E23)/Assets!E23*100 -> 4.3296235 | L23: =(INCOME!F23-EXP!F23)/Assets!F23*100 -> 4.0860427 | N23: 80.07 | O23: 78
B24: 18 | C24: YES Bank | D24: =(DEPO!J24/DEPO!D24)*100 -> 93.456415 | E24: =(DEPO!K24/DEPO!E24)*100 -> 85.519245 | F24: =(DEPO!L24/DEPO!F24)*100 -> 86.52609 | G24: =(DEPO!G24/DEPO!D24)*100 -> 35.35064 | H24: =(DEPO!H24/DEPO!E24)*100 -> 33.875585 | I24: =(DEPO!I24/DEPO!F24)*100 -> 29.911059 | J24: =(INCOME!D24-EXP!D24)/Assets!D24*100 -> 2.2316459 | K24: =(INCOME!E24-EXP!E24)/Assets!E24*100 -> 1.9962417 | L24: =(INCOME!F24-EXP!F24)/Assets!F24*100 -> 2.1123946 | N24: 66.61
B25: 19 | C25: Bandhan Bank | D25: =(DEPO!J25/DEPO!D25)*100 -> 96.938944 | E25: =(DEPO!K25/DEPO!E25)*100 -> 89.5969 | F25: =(DEPO!L25/DEPO!F25)*100 -> 87.285984 | G25: =(DEPO!G25/DEPO!D25)*100 -> 29.950477 | H25: =(DEPO!H25/DEPO!E25)*100 -> 21.662093 | I25: =(DEPO!I25/DEPO!F25)*100 -> 26.923882 | J25: =(INCOME!D25-EXP!D25)/Assets!D25*100 -> 5.9342422 | K25: =(INCOME!E25-EXP!E25)/Assets!E25*100 -> 5.8022633 | L25: =(INCOME!F25-EXP!F25)/Assets!F25*100 -> 6.0010474 | N25: 84.49 | O25: 86.5
B26: 20 | C26: IDFC First Bank Ltd. | D26: =(DEPO!J26/DEPO!D26)*100 -> 104.94839 | E26: =(DEPO!K26/DEPO!E26)*100 -> 97.016627 | F26: =(DEPO!L26/DEPO!F26)*100 -> 92.481026 | G26: =(DEPO!G26/DEPO!D26)*100 -> 42.259877 | H26: =(DEPO!H26/DEPO!E26)*100 -> 37.247863 | I26: =(DEPO!I26/DEPO!F26)*100 -> 32.021677 | J26: =(INCOME!D26-EXP!D26)/Assets!D26*100 -> 5.2660009 | K26: =(INCOME!E26-EXP!E26)/Assets!E26*100 -> 5.5555255 | L26: =(INCOME!F26-EXP!F26)/Assets!F26*100 -> 5.6110889 | N26: 86.58 | O26: 72.3
B27: 21 | C27: IDBI Ltd. | D27: =(DEPO!J27/DEPO!D27)*100 -> 63.629766 | E27: =(DEPO!K27/DEPO!E27)*100 -> 67.932903 | F27: =(DEPO!L27/DEPO!F27)*100 -> 70.384539 | G27: =(DEPO!G27/DEPO!D27)*100 -> 39.01903 | H27: =(DEPO!H27/DEPO!E27)*100 -> 41.394292 | I27: =(DEPO!I27/DEPO!F27)*100 -> 37.857 | J27: =(INCOME!D27-EXP!D27)/Assets!D27*100 -> 3.4585396 | K27: =(INCOME!E27-EXP!E27)/Assets!E27*100 -> 3.901897 | L27: =(INCOME!F27-EXP!F27)/Assets!F27*100 -> 3.5529234 | N27: 99.09 | O27: 99.48
B28: AVERAGE OF NEW PVT BANKS [II] | D28: =(DEPO!J28/DEPO!D28)*100 -> 86.388881 | E28: =(DEPO!K28/DEPO!E28)*100 -> 92.49148 | F28: =(DEPO!L28/DEPO!F28)*100 -> 89.132094 | G28: =(DEPO!G28/DEPO!D28)*100 -> 30.219466 | H28: =(DEPO!H28/DEPO!E28)*100 -> 31.448412 | I28: =(DEPO!I28/DEPO!F28)*100 -> 31.847371 | J28: =(INCOME!D28-EXP!D28)/Assets!D28*100 -> 3.6786668 | K28: =(INCOME!E28-EXP!E28)/Assets!E28*100 -> 3.518649 | L28: =(INCOME!F28-EXP!F28)/Assets!F28*100 -> 3.5034156
B29: AVERAGE OF PVT BANKS [I+II] | D29: =(DEPO!J29/DEPO!D29)*100 -> 85.194504 | E29: =(DEPO!K29/DEPO!E29)*100 -> 90.741895 | F29: =(DEPO!L29/DEPO!F29)*100 -> 87.941132 | G29: =(DEPO!G29/DEPO!D29)*100 -> 30.071643 | H29: =(DEPO!H29/DEPO!E29)*100 -> 30.730249 | I29: =(DEPO!I29/DEPO!F29)*100 -> 31.018101 | J29: =(INCOME!D29-EXP!D29)/Assets!D29*100 -> 3.6337567 | K29: =(INCOME!E29-EXP!E29)/Assets!E29*100 -> 3.4865222 | L29: =(INCOME!F29-EXP!F29)/Assets!F29*100 -> 3.4680163
B31: : 6 :

Sheet CRAR
B1: Statement VII : Private Sector Banks : Ratios
B2: As on March 31 | D2: (In Per Cent)
B3: S.No | C3: Banks | D3: Operating Expenses as % to Total Expenses | G3: Return on Assets (%) | J3: Capital Adequacy Ratio - Basel III (%)
B4: I | C4: OLD PRIVATE SECTOR BANKS | D4: 2023 | E4: 2024 | F4: 2025 | G4: 2023 | H4: 2024 | I4: 2025 | J4: 2023 | K4: 2024 | L4: 2025
B5: 1 | C5: City Union Bank Ltd. | D5: =(EXP!G5/EXP!J5)*100 -> 31.164294 | E5: =(EXP!H5/EXP!K5)*100 -> 29.994252 | F5: =(EXP!I5/EXP!L5)*100 -> 30.378074 | G5: 1.46 | H5: 1.52 | I5: 1.55 | J5: 22.34 | K5: 23.73 | L5: 23.75
B6: 2 | C6: Tamilnad Mercantile Bank Ltd. | D6: =(EXP!G6/EXP!J6)*100 -> 36.668037 | E6: =(EXP!H6/EXP!K6)*100 -> 32.760585 | F6: =(EXP!I6/EXP!L6)*100 -> 31.976042 | G6: 1.97 | H6: 1.84 | I6: 1.88 | J6: 26.26 | K6: 29.37 | L6: 32.71
B7: 3 | C7: CSB Bank Ltd. | D7: =(EXP!G7/EXP!J7)*100 -> 48.866919 | E7: =(EXP!H7/EXP!K7)*100 -> 46.882218 | F7: =(EXP!I7/EXP!L7)*100 -> 42.033529 | G7: 2.06 | H7: 1.79 | I7: 1.49 | J7: 27.1 | K7: 24.47 | L7: 22.46
B8: 4 | C8: Dhanlaxmi Bank Ltd | D8: =(EXP!G8/EXP!J8)*100 -> 41.765195 | E8: =(EXP!H8/EXP!K8)*100 -> 41.986685 | F8: =(EXP!I8/EXP!L8)*100 -> 39.985509 | G8: 0.34 | H8: 0.38 | I8: 0.41 | J8: 12.32 | K8: 12.71 | L8: 16.12
B9: 5 | C9: The Federal Bank Ltd. | D9: =(EXP!G9/EXP!J9)*100 -> 33.24981 | E9: =(EXP!H9/EXP!K9)*100 -> 30.84783 | F9: =(EXP!I9/EXP!L9)*100 -> 29.785995 | G9: 1.28 | H9: 1.32 | I9: 1.23 | J9: 14.81 | K9: 16.13 | L9: 16.4
B10: 6 | C10: The Jammu & Kashmir Bank Ltd. | D10: =(EXP!G10/EXP!J10)*100 -> 44.146494 | E10: =(EXP!H10/EXP!K10)*100 -> 38.441774 | F10: =(EXP!I10/EXP!L10)*100 -> 37.241782 | G10: 0.89 | H10: 1.22 | I10: 1.32 | J10: 15.39 | K10: 15.33 | L10: 16.29
B11: 7 | C11: The Karnataka Bank Ltd. | D11: =(EXP!G11/EXP!J11)*100 -> 32.79913 | E11: =(EXP!H11/EXP!K11)*100 -> 32.925862 | F11: =(EXP!I11/EXP!L11)*100 -> 32.554801 | G11: 1.21 | H11: 1.19 | I11: 1.05 | J11: 17.45 | K11: 18 | L11: 19.85
B12: 8 | C12: The Karur Vysya Bank Ltd. | D12: =(EXP!G12/EXP!J12)*100 -> 39.078408 | E12: =(EXP!H12/EXP!K12)*100 -> 37.516937 | F12: =(EXP!I12/EXP!L12)*100 -> 34.684145 | G12: 1.27 | H12: 1.63 | I12: 1.72 | J12: 18.56 | K12: 16.67 | L12: 18.17
B13: 9 | C13: Nainital Bank Ltd. | D13: =(EXP!G13/EXP!J13)*100 -> 41.266338 | E13: =(EXP!H13/EXP!K13)*100 -> 42.553211 | F13: =(EXP!I13/EXP!L13)*100 -> 39.71439 | G13: 0.54 | H13: 0.52 | I13: 0.61 | J13: 16.24 | K13: 15.22 | L13: 16.76
B14: 10 | C14: RBL Bank | D14: =(EXP!G14/EXP!J14)*100 -> 53.044996 | E14: =(EXP!H14/EXP!K14)*100 -> 48.80554 | F14: =(EXP!I14/EXP!L14)*100 -> 46.716803 | G14: 0.83 | H14: 0.96 | I14: 0.51 | J14: 16.92 | K14: 16.18 | L14: 15.54
B15: 11 | C15: The South Indian Bank Ltd. | D15: =(EXP!G15/EXP!J15)*100 -> 35.442182 | E15: =(EXP!H15/EXP!K15)*100 -> 36.073432 | F15: =(EXP!I15/EXP!L15)*100 -> 33.818298 | G15: 0.73 | H15: 0.93 | I15: 1.06 | J15: 17.25 | K15: 19.91 | L15: 19.31
B16: AVERAGE OF OLD PVT BANKS [I] | D16: =(EXP!G16/EXP!J16)*100 -> 39.438032 | E16: =(EXP!H16/EXP!K16)*100 -> 36.885706 | F16: =(EXP!I16/EXP!L16)*100 -> 35.339043
B17: II | C17: NEW PRIVATE SECTOR BANKS
B18: 12 | C18: Axis Bank Ltd. | D18: =(EXP!G18/EXP!J18)*100 -> 39.043167 | E18: =(EXP!H18/EXP!K18)*100 -> 37.18897 | F18: =(EXP!I18/EXP!L18)*100 -> 35.434418 | G18: 0.8 | H18: 1.83 | I18: 1.74 | J18: 17.64 | K18: 16.63 | L18: 17.07
B19: 13 | C19: DCB Bank Ltd. | D19: =(EXP!G19/EXP!J19)*100 -> 35.043017 | E19: =(EXP!H19/EXP!K19)*100 -> 30.928188 | F19: =(EXP!I19/EXP!L19)*100 -> 29.431607 | G19: 0.97 | H19: 0.93 | I19: 0.89 | J19: 17.55 | K19: 16.59 | L19: 16.77
B20: 14 | C20: HDFC Bank Ltd. | D20: =(EXP!G20/EXP!J20)*100 -> 38.932909 | E20: =(EXP!H20/EXP!K20)*100 -> 29.731595 | F20: =(EXP!I20/EXP!L20)*100 -> 27.71091 | G20: 2.07 | H20: 1.98 | I20: 1.91 | J20: 19.26 | K20: 18.8 | L20: 19.55
B21: 15 | C21: ICICI Bank Ltd. | D21: =(EXP!G21/EXP!J21)*100 -> 41.103891 | E21: =(EXP!H21/EXP!K21)*100 -> 36.328885 | F21: =(EXP!I21/EXP!L21)*100 -> 34.041741 | G21: 2.16 | H21: 2.37 | I21: 2.41 | J21: 18.34 | K21: 16.33 | L21: 16.55
B22: 16 | C22: Indusind Bank Ltd. | D22: =(EXP!G22/EXP!J22)*100 -> 37.803351 | E22: =(EXP!H22/EXP!K22)*100 -> 36.20562 | F22: =(EXP!I22/EXP!L22)*100 -> 35.160151 | G22: 1.81 | H22: 1.9 | I22: 0.5 | J22: 17.86 | K22: 17.23 | L22: 16.24
B23: 17 | C23: Kotak Mahindra Bank Ltd. | D23: =(EXP!G23/EXP!J23)*100 -> 52.054035 | E23: =(EXP!H23/EXP!K23)*100 -> 45.714817 | F23: =(EXP!I23/EXP!L23)*100 -> 43.27945 | G23: 2.47 | H23: 2.61 | I23: 2.65 | J23: 21.8 | K23: 20.55 | L23: 22.25
B24: 18 | C24: YES Bank | D24: =(EXP!G24/EXP!J24)*100 -> 36.292965 | E24: =(EXP!H24/EXP!K24)*100 -> 33.508449 | F24: =(EXP!I24/EXP!L24)*100 -> 32.455285 | G24: 0.2 | H24: 0.3 | I24: 0.6 | J24: 17.9 | K24: 15.4 | L24: 15.6
B25: 19 | C25: Bandhan Bank | D25: =(EXP!G25/EXP!J25)*100 -> 41.099632 | E25: =(EXP!H25/EXP!K25)*100 -> 40.626013 | F25: =(EXP!I25/EXP!L25)*100 -> 40.331157 | G25: 1.56 | H25: 1.44 | I25: 1.53 | J25: 19.76 | K25: 14.69 | L25: 18.71
B26: 20 | C26: IDFC First Bank Ltd. | D26: =(EXP!G26/EXP!J26)*100 -> 54.667343 | E26: =(EXP!H26/EXP!K26)*100 -> 53.895351 | F26: =(EXP!I26/EXP!L26)*100 -> 52.339223 | G26: 1.13 | H26: 1.1 | I26: 0.48 | J26: 16.82 | K26: 16.11 | L26: 15.48
B27: 21 | C27: IDBI Ltd. | D27: =(EXP!G27/EXP!J27)*100 -> 43.605639 | E27: =(EXP!H27/EXP!K27)*100 -> 40.133527 | F27: =(EXP!I27/EXP!L27)*100 -> 37.242835 | G27: 1.2 | H27: 1.44 | I27: 2.11 | J27: 20.44 | K27: 22.26 | L27: 25.05
B28: AVERAGE OF NEW PVT BANKS [II] | D28: =(EXP!G28/EXP!J28)*100 -> 41.078258 | E28: =(EXP!H28/EXP!K28)*100 -> 35.602957 | F28: =(EXP!I28/EXP!L28)*100 -> 33.755069
B29: AVERAGE OF PVT BANKS [I+II] | D29: =(EXP!G29/EXP!J29)*100 -> 40.864752 | E29: =(EXP!H29/EXP!K29)*100 -> 35.752896 | F29: =(EXP!I29/EXP!L29)*100 -> 33.939925
B31: : 7 :

Sheet NetNPAtoNetADV
B1: Statement VIII : Private Sector Banks : Ratios
B2: As on March 31 | D2: (In Per Cent) | G2: (₹ Crore) | J2: (₹ Lacs)
B3: S.No | C3: Banks | D3: Net NPA as % to Net Advances | G3: Business per Employee | J3: Profit per Employee
B4: I | C4: OLD PRIVATE SECTOR BANKS | D4: 2023 | E4: 2024 | F4: 2025 | G4: 2023 | H4: 2024 | I4: 2025 | J4: 2023 | K4: 2024 | L4: 2025
B5: 1 | C5: City Union Bank Ltd. | D5: =(Assets!J5/DEPO!J5)*100 -> 2.3636494 | E5: =(Assets!K5/DEPO!K5)*100 -> 1.9739985 | F5: 1.25 | G5: 15.98 | H5: 14.21 | I5: 15.32 | J5: 15.58 | K5: 14.13 | L5: 14.77
B6: 2 | C6: Tamilnad Mercantile Bank Ltd. | D6: =(Assets!J6/DEPO!J6)*100 -> 0.61678734 | E6: =(Assets!K6/DEPO!K6)*100 -> 0.8451757 | F6: 0.36 | G6: 19.1 | H6: 19.44 | I6: 20.67 | J6: 23.04 | K6: 23.29 | L6: 24.93
B7: 3 | C7: CSB Bank Ltd. | D7: =(Assets!J7/DEPO!J7)*100 -> 0.34778566 | E7: =(Assets!K7/DEPO!K7)*100 -> 0.51324028 | F7: 0.52 | G7: 6.47 | H7: 6.56 | I7: 8.38 | J7: 8.01 | K7: 7.21 | L7: 7.8
B8: 4 | C8: Dhanlaxmi Bank Ltd | D8: =(Assets!J8/DEPO!J8)*100 -> 1.1553697 | E8: 1.25 | F8: 0.99 | G8: 13.13 | H8: 14.64 | I8: 16.07 | J8: 2.79 | K8: 3.43 | L8: 3.8
B9: 5 | C9: The Federal Bank Ltd. | D9: =(Assets!J9/DEPO!J9)*100 -> 0.69076042 | E9: =(Assets!K9/DEPO!K9)*100 -> 0.59947948 | F9: 0.44 | G9: 29.55 | H9: 32.23 | I9: 32.41 | J9: 22.94 | K9: 25.96 | L9: 26.12
B10: 6 | C10: The Jammu & Kashmir Bank Ltd. | D10: =(Assets!J10/DEPO!J10)*100 -> 1.6214774 | E10: =(Assets!K10/DEPO!K10)*100 -> 0.78586847 | F10: =(Assets!L10/DEPO!L10)*100 -> 0.78510561 | G10: 15.57 | H10: 17.81 | I10: 20.18 | J10: 9.06 | K10: 13.75 | L10: 16.65
B11: 7 | C11: The Karnataka Bank Ltd. | D11: =(Assets!J11/DEPO!J11)*100 -> 1.7034902 | E11: 1.58 | F11: 1.31 | G11: 17.03 | H11: 19.21 | I11: 20.89 | J11: 13.64 | K11: 14.67 | L11: 14.54
B12: 8 | C12: The Karur Vysya Bank Ltd. | D12: =(Assets!J12/DEPO!J12)*100 -> 0.7415164 | E12: =(Assets!K12/DEPO!K12)*100 -> 0.4044797 | F12: 0.2 | G12: 18.11 | H12: 18 | I12: 18.91 | J12: 14.25 | K12: 17.66 | L12: 19.68
B13: 9 | C13: Nainital Bank Ltd. | D13: 1.84 | E13: 0.94 | F13: 0.56 | G13: 10.99 | H13: 10.79 | I13: 10.81 | J13: 4.26 | K13: 4 | L13: 4
B14: 10 | C14: RBL Bank | D14: =(Assets!J14/DEPO!J14)*100 -> 1.1003378 | E14: =(Assets!K14/DEPO!K14)*100 -> 0.73737672 | F14: 0.29 | G14: 13.11 | H14: 14.03 | I14: 13.38 | J14: 8 | K14: 9 | L14: 5
B15: 11 | C15: The South Indian Bank Ltd. | D15: =(Assets!J15/DEPO!J15)*100 -> 1.8531916 | E15: =(Assets!K15/DEPO!K15)*100 -> 1.4534596 | F15: =(Assets!L15/DEPO!L15)*100 -> 0.9226201 | G15: 16.28 | H15: 17.65 | I15: 20.36 | J15: 8.18 | K15: 11.09 | L15: 14.15
B16: AVERAGE OF OLD PVT BANKS [I] | D16: =(Assets!J16/DEPO!J16)*100 -> 1.197899 | E16: =(Assets!K16/DEPO!K16)*100 -> 0.91218557 | F16: =(Assets!L16/DEPO!L16)*100 -> 0.63393422
B17: II | C17: NEW PRIVATE SECTOR BANKS
B18: 12 | C18: Axis Bank Ltd. | D18: 0.39 | E18: 0.31 | F18: 0.33 | G18: 20 | H18: 20.19 | I18: 20.88 | J18: 10.94 | K18: 25.29 | L18: 25.45
B19: 13 | C19: DCB Bank Ltd. | D19: =(Assets!J19/DEPO!J19)*100 -> 1.0382209 | E19: =(Assets!K19/DEPO!K19)*100 -> 1.1101647 | F19: =(Assets!L19/DEPO!L19)*100 -> 1.1196564 | G19: 7.8 | H19: 8.37 | I19: 8.97 | J19: 5.08 | K19: 5.25 | L19: 5.31
B20: 14 | C20: HDFC Bank Ltd. | D20: =(Assets!J20/DEPO!J20)*100 -> 0.27292693 | E20: =(Assets!K20/DEPO!K20)*100 -> 0.32564149 | F20: 0.43 | G20: 19.74 | H20: 21.49 | I20: 23.62 | J20: 27.73 | K20: 31.2 | L20: 32
B21: 15 | C21: ICICI Bank Ltd. | D21: 0.48 | E21: 0.42 | F21: 0.39 | G21: 17.07 | H21: 16.84 | I21: 20.06 | J21: 27.52 | K21: 29.42 | L21: 35
B22: 16 | C22: Indusind Bank Ltd. | D22: =(Assets!J22/DEPO!J22)*100 -> 0.59152119 | E22: =(Assets!K22/DEPO!K22)*100 -> 0.57352459 | F22: 0.95 | G22: 16.95 | H22: 16.98 | I22: 16.61 | J22: 20.6 | K22: 21.355 | L22: 6
B23: 17 | C23: Kotak Mahindra Bank Ltd. | D23: =(Assets!J23/DEPO!J23)*100 -> 0.37306806 | E23: =(Assets!K23/DEPO!K23)*100 -> 0.33784992 | F23: =(Assets!L23/DEPO!L23)*100 -> 0.31468987 | G23: 8.73 | H23: 9.63 | I23: 10.89 | J23: 15 | K23: 18 | L23: 21
B24: 18 | C24: YES Bank | D24: =(Assets!J24/DEPO!J24)*100 -> 0.81571042 | E24: =(Assets!K24/DEPO!K24)*100 -> 0.58372831 | F24: =(Assets!L24/DEPO!L24)*100 -> 0.32501116 | G24: 15.67 | H24: 17.42 | I24: 18.4 | J24: 2.8 | K24: 4.51 | L24: 8.49
B25: 19 | C25: Bandhan Bank | D25: =(Assets!J25/DEPO!J25)*100 -> 1.172497 | E25: =(Assets!K25/DEPO!K25)*100 -> 1.1124697 | F25: 1.28 | G25: 3.02 | H25: 3.19 | I25: 3.35 | J25: 3.36 | K25: 3 | L25: 3.53
B26: 20 | C26: IDFC First Bank Ltd. | D26: =(Assets!J26/DEPO!J26)*100 -> 0.85908893 | E26: =(Assets!K26/DEPO!K26)*100 -> 0.59635432 | F26: 0.53 | G26: 8.11 | H26: 8.67 | I26: 10.31 | J26: 7.75 | K26: 7.56 | L26: 3.66
B27: 21 | C27: IDBI Ltd. | D27: =(Assets!J27/DEPO!J27)*100 -> 0.91961676 | E27: 0.34 | F27: 0.15 | G27: 22.31 | H27: 23.5 | I27: 25.65 | J27: 20.42 | K27: 29.63 | L27: 38.09
B28: AVERAGE OF NEW PVT BANKS [II] | D28: =(Assets!J28/DEPO!J28)*100 -> 0.46560957 | E28: =(Assets!K28/DEPO!K28)*100 -> 0.40629148 | F28: =(Assets!L28/DEPO!L28)*100 -> 0.4486553
B29: AVERAGE OF PVT BANKS [I+II] | D29: =(Assets!J29/DEPO!J29)*100 -> 0.55220079 | E29: =(Assets!K29/DEPO!K29)*100 -> 0.4604543 | F29: =(Assets!L29/DEPO!L29)*100 -> 0.46902645
B31: : 8 :
