Workbook

Sheet DEPO
B2: Statement I : Small Finance Banks : Deposits/Investments/Advances
B3: As on March 31 | D3: (₹ Crore)
B4: Sr. No. | C4: Banks | D4: Deposits | G4: Investments | J4: Advances
D5: 2023 | E5: 2024 | F5: 2025 | G5: 2023 | H5: 2024 | I5: 2025 | J5: 2023 | K5: 2024 | L5: 2025
B6: 1 | C6: Au Small Finance Bank Ltd. # | D6: 69364.99 | E6: 87182.116 | F6: 124268.54 | G6: 20072 | H6: 27133.365 | I6: 37847.52 | J6: 58421.54 | K6: 73162.655 | L6: 107092.48
B7: 2 | C7: Capital Small Finance Bank Ltd. | D7: 6560.62 | E7: 7477.74 | F7: 8322.6 | G7: 1488.58 | H7: 1705.71 | I7: 1819.45 | J7: 5428.69 | K7: 6074.69 | L7: 7090.39
B8: 3 | C8: Equitas Small Finance Bank Ltd. | D8: 25348.48 | E8: 36129.202 | F8: 43106.72 | G8: 6664.56 | H8: 9065.2723 | I8: 9288.6851 | J8: 25798.55 | K8: 30964.3 | L8: 36208.888
B9: 4 | C9: ESAF Small Finance Bank Ltd. | D9: 14665.63 | E9: 19867.8 | F9: 23276.44 | G9: 4888.53 | H9: 5541.02 | I9: 5995.26 | J9: 13924.33 | K9: 18293.11 | L9: 18027.87
B10: 5 | C10: Fincare Small Finance Bank Ltd. | D10: 8033.19 | E10: 10521.7 | F10: - | G10: 2522.84 | H10: 3184.61 | I10: - | J10: 8702.42 | K10: 12357.78 | L10: -
B11: 6 | C11: Jana Small Finance Bank Ltd. | D11: 16334.02 | E11: 22571.25 | F11: 29119.78 | G11: 5221.22 | H11: 6737.69 | I11: 5944.58 | J11: 17759.56 | K11: 23111.27 | L11: 27155.48
B12: 7 | C12: Slice Small Finance Bank Ltd.(earlier North East SFB) | D12: 2039.63 | E12: 1519.57 | F12: 2418.38 | G12: 348.29 | H12: 550.19 | I12: 778.13 | J12: 1603.25 | K12: 802.43 | L12: 2904.87
B13: 8 | C13: Suryoday Small Finance Bank Ltd. | D13: 5166.72 | E13: 7777.27 | F13: 10579.61 | G13: 2570.19 | H13: 2599.3 | I13: 3137.48 | J13: 6015.05 | K13: 8077.97 | L13: 9974.35
B14: 9 | C14: Ujjivan Small Finance Bank Ltd. | D14: 25537.68 | E14: 31462.36 | F14: 37630.48 | G14: 8510.31 | H14: 9766.02 | I14: 11729.99 | J14: 21289.66 | K14: 26882.92 | L14: 31390
B15: 10 | C15: Utkarsh Small Finance Bank Ltd. | D15: 13710.14 | E15: 17472.598 | F15: 21565.699 | G15: 2859.42 | H15: 3679.4652 | I15: 4957.8851 | J15: 13068.75 | K15: 16364.809 | L15: 18716.476
B16: 11 | C16: Shivalik Small Finance Bank Ltd. | D16: 1894.26 | E16: 2409.66 | F16: 3161.06 | G16: 533.35 | H16: 495.63 | I16: 634.529 | J16: 1407.37 | K16: 2095.38 | L16: 2934.5595
B17: 12 | C17: Unity Small Finance Bank Ltd. | D17: 2684.62 | E17: 6505 | F17: 11951.89 | G17: 2435.8 | H17: 3825 | I17: 5151.99 | J17: 4468.19 | K17: 7961 | L17: 10985.18
C18: TOTAL OF SMALL FINANCE BANKS [I] | D18: =SUM(D6:D17) -> 191339.98 | E18: =SUM(E6:E17) -> 250896.27 | F18: =SUM(F6:F17) -> 315401.2 | G18: =SUM(G6:G17) -> 58115.09 | H18: =SUM(H6:H17) -> 74283.273 | I18: =SUM(I6:I17) -> 87285.499 | J18: =SUM(J6:J17) -> 177887.36 | K18: =SUM(K6:K17) -> 226148.31 | L18: =SUM(L6:L17) -> 272480.54
B20: # As per the directions of the RBI, AU Small Finance Bank (AU SFB), announced the merger of Fincare SFB into AU SFB, effective from 01.04.2024.
B22: 1

Sheet Assets
B2: Statement II : Small Finance Banks : Assets/Gross and Net Non-Performing Assets
B3: As on March 31 | D3: (₹ Crore)
B4: Sr. No. | C4: Banks | D4: Total Assets | G4: Gross NPA | J4: Net NPA
D5: 2023 | E5: 2024 | F5: 2025 | G5: 2023 | H5: 2024 | I5: 2025 | J5: 2023 | K5: 2024 | L5: 2025
B6: 1 | C6: Au Small Finance Bank Ltd. | D6: 90216.11 | E6: 109425.67 | F6: 157845.67 | G6: 981.31 | H6: 1237.4004 | I6: 2477.0299 | J6: 245.1588 | K6: 400.9897 | L6: 791.34
B7: 2 | C7: Capital Small Finance Bank Ltd. | D7: 7990.77 | E7: 9295.28 | F7: 10107.51 | G7: 152.62 | H7: 170.18 | I7: 185.34 | J7: 74.05 | K7: 85.07 | L7: 91.84
B8: 3 | C8: Equitas Small Finance Bank Ltd. | D8: 34958.126 | E8: 45303.87 | F8: 52835.63 | G8: 723.96 | H8: 821.2772 | I8: 1067.7299 | J8: 312.01 | K8: 360.8988 | L8: 354.1952
B9: 4 | C9: ESAF Small Finance Bank Ltd. | D9: 20223.66 | E9: 26086.88 | F9: 27178.29 | G9: 351.69 | H9: 893.04 | I9: 1290.56 | J9: 157.89 | K9: 413.79 | L9: 539.64
B10: 5 | C10: Fincare Small Finance Bank Ltd. | D10: 12467.69 | E10: 17267.43 | F10: - | G10: 288.47 | H10: 199.54 | I10: - | J10: 113.02 | K10: 78.42 | L10: -
B11: 6 | C11: Jana Small Finance Bank Ltd. | D11: 25643.6 | E11: 32709.78 | F11: 38463.62 | G11: 709.19 | H11: 494.33 | I11: 749.6 | J11: 468 | K11: 130.02 | L11: 254.185
B12: 7 | C12: Slice Small Finance Bank Ltd. (earlier North East SFB) | D12: 2710.44 | E12: 1686.55 | F12: 4329.9 | G12: 347.33 | H12: 99.2 | I12: 184.76 | J12: 27.16 | K12: 67.06 | L12: 135.59
B13: 8 | C13: Suryoday Small Finance Bank Ltd. | D13: 9861.22 | E13: 12377.69 | F13: 15614.39 | G13: 191.4 | H13: 242.37 | I13: 733.84 | J13: 92.97 | K13: 69.87 | L13: 457.02
B14: 9 | C14: Ujjivan Small Finance Bank Ltd. | D14: 33316.88 | E14: 40422.22 | F14: 47689.15 | G14: 630.61 | H14: 612.52 | I14: 695.89 | J14: 9.04 | K14: 76.29 | L14: 152.43
B15: 10 | C15: Utkarsh Small Finance Bank Ltd. | D15: 19117.54 | E15: 23902.677 | F15: 28127.43 | G15: 431.5 | H15: 417.5782 | I15: 1854.38 | J15: 50.51 | K15: 4.48 | L15: 905.27
B16: 11 | C16: Shivalik Small Finance Bank Ltd. | D16: 2249.85 | E16: 3028.52 | F16: 4119.76 | G16: 32.73 | H16: 42.71 | I16: 80.1265 | J16: 16.3 | K16: 17.63 | L16: 44.246
B17: 12 | C17: Unity Small Finance Bank Ltd. | D17: 8761.33 | E17: 13774 | F17: 19151.94 | G17: 3767.36 | H17: 360.21 | I17: 669.43 | J17: 15.31 | K17: 50 | L17: 169.37
C18: TOTAL OF SMALL FINANCE BANKS [I] | D18: =SUM(D6:D17) -> 267517.22 | E18: =SUM(E6:E17) -> 335280.57 | F18: =SUM(F6:F17) -> 405463.29 | G18: =SUM(G6:G17) -> 8608.17 | H18: =SUM(H6:H17) -> 5590.3558 | I18: =SUM(I6:I17) -> 9988.6863 | J18: =SUM(J6:J17) -> 1581.4188 | K18: =SUM(K6:K17) -> 1754.5185 | L18: =SUM(L6:L17) -> 3895.1262
B20: 2

Sheet Income
B2: Statement III : Small Finance Banks : Income
B3: As on March 31 | D3: (₹ Crore)
B4: Sr. No. | C4: Banks | D4: Interest Income | G4: Other Income | J4: Total Income
D5: 2023 | E5: 2024 | F5: 2025 | G5: 2023 | H5: 2024 | I5: 2025 | J5: 2023 | K5: 2024 | L5: 2025
B6: 1 | C6: Au Small Finance Bank Ltd. | D6: 8205.41 | E6: 10554.713 | F6: 16063.73 | G6: 1034.46 | H6: 1697.14 | I6: 2526.31 | J6: =D6+G6-1 -> 9238.87 | K6: =E6+H6 -> 12251.853 | L6: =F6+I6 -> 18590.04
B7: 2 | C7: Capital Small Finance Bank Ltd. | D7: 676.01 | E7: 794.33 | F7: 908.5 | G7: 49.47 | H7: 68.08 | I7: 86.02 | J7: =D7+G7 -> 725.48 | K7: =E7+H7 -> 862.41 | L7: =F7+I7 -> 994.52
B8: 3 | C8: Equitas Small Finance Bank Ltd. | D8: 4161.87 | E8: 5486.4034 | F8: 6311.725 | G8: 669.58 | H8: 798.6706 | I8: 911.4891 | J8: =D8+G8+1 -> 4832.45 | K8: =E8+H8 -> 6285.074 | L8: =F8+I8 -> 7223.2141
B9: 4 | C9: ESAF Small Finance Bank Ltd. | D9: 2853.66 | E9: 3818.43 | F9: 3862.22 | G9: 287.91 | H9: 441.82 | I9: 467.09 | J9: =D9+G9 -> 3141.57 | K9: =E9+H9 -> 4260.25 | L9: =F9+I9 -> 4329.31
B10: 5 | C10: Fincare Small Finance Bank Ltd. | D10: 1744.12 | E10: 2670.63 | F10: - | G10: 226.68 | H10: 342.65 | I10: - | J10: =D10+G10 -> 1970.8 | K10: =E10+H10+1 -> 3014.28 | L10: -
B11: 6 | C11: Jana Small Finance Bank Ltd. | D11: 3075.01 | E11: 4013.81 | F11: 4709.79 | G11: 624.86 | H11: 670.24 | I11: 775.86 | J11: =D11+G11 -> 3699.87 | K11: =E11+H11 -> 4684.05 | L11: =F11+I11 -> 5485.65
B12: 7 | C12: Slice Small Finance Bank Ltd. (earlier North East SFB) | D12: 297.69 | E12: 195.83 | F12: 409.23 | G12: 37.59 | H12: 55.53 | I12: 194.48 | J12: =D12+G12+1 -> 336.28 | K12: =E12+H12 -> 251.36 | L12: =F12+I12 -> 603.71
B13: 8 | C13: Suryoday Small Finance Bank Ltd. | D13: 1183.68 | E13: 1588.7 | F13: 1953.75 | G13: 97.42 | H13: 219.39 | I13: 217.25 | J13: =D13+G13 -> 1281.1 | K13: =E13+H13 -> 1808.09 | L13: =F13+I13 -> 2171
B14: 9 | C14: Ujjivan Small Finance Bank Ltd. | D14: 4165 | E14: 5677.16 | F14: 6354.39 | G14: 589.19 | H14: 786.75 | I14: 846.2 | J14: =D14+G14 -> 4754.19 | K14: =E14+H14 -> 6463.91 | L14: =F14+I14 -> 7200.59
B15: 10 | C15: Utkarsh Small Finance Bank Ltd. | D15: 2504.97 | E15: 3178.41 | F15: 3764.926 | G15: 299.3 | H15: 400.34 | I15: 599.83 | J15: =D15+G15 -> 2804.27 | K15: =E15+H15 -> 3578.75 | L15: =F15+I15 -> 4364.756
B16: 11 | C16: Shivalik Small Finance Bank Ltd. | D16: 203.62 | E16: 280.67 | F16: 374.81 | G16: 15.1 | H16: 28.71 | I16: 48.07 | J16: =D16+G16 -> 218.72 | K16: =E16+H16 -> 309.38 | L16: =F16+I16 -> 422.88
B17: 12 | C17: Unity Small Finance Bank Ltd. | D17: 734.7 | E17: 1388 | F17: 2068.57 | G17: 68.61 | H17: 244 | I17: 768.52 | J17: =D17+G17 -> 803.31 | K17: =E17+H17 -> 1632 | L17: =F17+I17 -> 2837.09
C18: TOTAL OF SMALL FINANCE BANKS [I] | D18: =SUM(D6:D17) -> 29805.74 | E18: =SUM(E6:E17) -> 39647.087 | F18: =SUM(F6:F17) -> 46781.641 | G18: =SUM(G6:G17) -> 4000.17 | H18: =SUM(H6:H17) -> 5753.3206 | I18: =SUM(I6:I17) -> 7441.1191 | J18: =SUM(J6:J17) -> 33806.91 | K18: =SUM(K6:K17) -> 45401.407 | L18: =SUM(L6:L17) -> 54222.76
B20: 3

Sheet Exps.
B2: Statement IV : Small Finance Banks : Expenditure
B3: As on March 31 | D3: (₹ Crore)
B4: Sr. No. | C4: Banks | D4: Interest Expended | G4: Operating Expenses | J4: Total Expenditure *
D5: 2023 | E5: 2024 | F5: 2025 | G5: 2023 | H5: 2024 | I5: 2025 | J5: 2023 | K5: 2024 | L5: 2025
B6: 1 | C6: Au Small Finance Bank Ltd. | D6: 3780.12 | E6: 5397.6293 | F6: 8052.1494 | G6: 3440 | H6: 4388.0022 | I6: 5957.22 | J6: =D6+G6 -> 7220.12 | K6: =E6+H6 -> 9785.6315 | L6: =F6+I6 -> 14009.369
B7: 2 | C7: Capital Small Finance Bank Ltd. | D7: 354.02 | E7: 449.18 | F7: 498.3 | G7: 222.75 | H7: 258.33 | I7: 310.79 | J7: =D7+G7 -> 576.77 | K7: =E7+H7 -> 707.51 | L7: =F7+I7 -> 809.09
B8: 3 | C8: Equitas Small Finance Bank Ltd. | D8: 1617.15 | E8: 2406.6428 | F8: 3060.11 | G8: 2038.3 | H8: 2501.0668 | I8: 2828.83 | J8: =D8+G8 -> 3655.45 | K8: =E8+H8 -> 4907.7096 | L8: =F8+I8 -> 5888.94
B9: 4 | C9: ESAF Small Finance Bank Ltd. | D9: 1017.32 | E9: 1448.73 | F9: 1810.69 | G9: 1230.54 | H9: 1648.83 | I9: 1903.51 | J9: =D9+G9 -> 2247.86 | K9: =E9+H9 -> 3097.56 | L9: =F9+I9 -> 3714.2
B10: 5 | C10: Fincare Small Finance Bank Ltd. | D10: 653.68 | E10: 1023.44 | F10: - | G10: 874.05 | H10: 1283.09 | I10: - | J10: =D10+G10 -> 1527.73 | K10: =E10+H10-1 -> 2305.53 | L10: -
B11: 6 | C11: Jana Small Finance Bank Ltd. | D11: 1414.99 | E11: 1885.9047 | F11: 2316.66 | G11: 1284.51 | H11: 1604.8397 | I11: 1942.63 | J11: =D11+G11 -> 2699.5 | K11: =E11+H11 -> 3490.7444 | L11: =F11+I11 -> 4259.29
B12: 7 | C12: Slice Small Finance Bank Ltd. (earlier North East SFB) | D12: 141.33 | E12: 124.25 | F12: 200.53 | G12: 177.89 | H12: 174.59 | I12: 481.15 | J12: =D12+G12 -> 319.22 | K12: =E12+H12 -> 298.84 | L12: =F12+I12 -> 681.68
B13: 8 | C13: Suryoday Small Finance Bank Ltd. | D13: 437.11 | E13: 626.47 | F13: 847.61 | G13: 506.53 | H13: 727.71 | I13: 934.19 | J13: =D13+G13 -> 943.64 | K13: =E13+H13 -> 1354.18 | L13: =F13+I13 -> 1781.8
B14: 9 | C14: Ujjivan Small Finance Bank Ltd. | D14: 1467.09 | E14: 2267.7 | F14: 2718.12 | G14: 1802.06 | H14: 2279.1 | I14: 2793.24 | J14: =D14+G14 -> 3269.15 | K14: =E14+H14 -> 4546.8 | L14: =F14+I14 -> 5511.36
B15: 10 | C15: Utkarsh Small Finance Bank Ltd. | D15: 975.94 | E15: 1292.6 | F15: 1742.06 | G15: 990.01 | H15: 1288.87 | I15: 1615.76 | J15: =D15+G15 -> 1965.95 | K15: =E15+H15 -> 2581.47 | L15: =F15+I15 -> 3357.82
B16: 11 | C16: Shivalik Small Finance Bank Ltd. | D16: 106.42 | E16: 144.66 | F16: 207.69 | G16: 105.29 | H16: 146.16 | I16: 194.28 | J16: =D16+G16 -> 211.71 | K16: =E16+H16 -> 290.82 | L16: =F16+I16 -> 401.97
B17: 12 | C17: Unity Small Finance Bank Ltd. | D17: 174.91 | E17: 407 | F17: 881.68 | G17: 476.6 | H17: 808 | I17: 1227.44 | J17: =D17+G17 -> 651.51 | K17: =E17+H17 -> 1215 | L17: =F17+I17 -> 2109.12
C18: TOTAL OF SMALL FINANCE BANKS [I] | D18: =SUM(D6:D17) -> 12140.08 | E18: =SUM(E6:E17) -> 17474.207 | F18: =SUM(F6:F17) -> 22335.599 | G18: =SUM(G6:G17) -> 13148.53 | H18: =SUM(H6:H17) -> 17108.589 | I18: =SUM(I6:I17) -> 20189.04 | J18: =SUM(J6:J17) -> 25288.61 | K18: =SUM(K6:K17) -> 34581.796 | L18: =SUM(L6:L17) -> 42524.639
B20: * Excludes amount of Provisions & Contingencies.
B21: 4

Sheet Profit
B2: Statement V : Small Finance Banks : Profit
B3: As on March 31 | D3: (₹ Crore)
B4: Sr. No. | C4: Banks | D4: Operating Profit | G4: Provisions & Contingencies | J4: Net Profit
D5: 2023 | E5: 2024 | F5: 2025 | G5: 2023 | H5: 2024 | I5: 2025 | J5: 2023 | K5: 2024 | L5: 2025
B6: 1 | C6: Au Small Finance Bank Ltd. | D6: =Income!J6-Exps.!J6 -> 2018.75 | E6: =Income!K6-Exps.!K6 -> 2466.2216 | F6: =Income!L6-Exps.!L6 -> 4580.6706 | G6: =154.83+436.71 -> 591.54 | H6: =389.99+464.71+76.8 -> 931.5 | I6: =1792.62+682.1275 -> 2474.7475 | J6: =D6-G6 -> 1427.21 | K6: 1534.719 | L6: =F6-I6 -> 2105.9231
B7: 2 | C7: Capital Small Finance Bank Ltd. | D7: =Income!J7-Exps.!J7-1 -> 147.71 | E7: 154.9 | F7: =Income!L7-Exps.!L7 -> 185.43 | G7: 55.11 | H7: =36.68+6.69 -> 43.37 | I7: =10.3+43.48 -> 53.78 | J7: =D7-G7 -> 92.6 | K7: =E7-H7 -> 111.53 | L7: =F7-I7 -> 131.65
B8: 3 | C8: Equitas Small Finance Bank Ltd. | D8: =Income!J8-Exps.!J8 -> 1177 | E8: =Income!K8-Exps.!K8 -> 1377.3644 | F8: =Income!L8-Exps.!L8 -> 1334.2741 | G8: =407.2+195.21 -> 602.41 | H8: =314.2397+264.1645 -> 578.4042 | I8: =1135.4181+51.7992 -> 1187.2173 | J8: =D8-G8 -> 574.59 | K8: =E8-H8 -> 798.9602 | L8: =F8-I8 -> 147.0568
B9: 4 | C9: ESAF Small Finance Bank Ltd. | D9: =Income!J9-Exps.!J9 -> 893.71 | E9: =Income!K9-Exps.!K9 -> 1162.69 | F9: =Income!L9-Exps.!L9 -> 615.11 | G9: 591.38 | H9: =592.28+144.84 -> 737.12 | I9: =1250.08+58-171.58 -> 1136.5 | J9: =D9-G9+1 -> 303.33 | K9: =E9-H9 -> 425.57 | L9: =F9-I9 -> -521.39
B10: 5 | C10: Fincare Small Finance Bank Ltd. | D10: =Income!J10-Exps.!J10 -> 443.07 | E10: =Income!K10-Exps.!K10-1 -> 707.75 | F10: - | G10: 339 | H10: 311.78 | I10: - | J10: =D10-G10 -> 104.07 | K10: =E10-H10 -> 395.97 | L10: -
B11: 5 | C11: Jana Small Finance Bank Ltd. | D11: =Income!J11-Exps.!J11 -> 1000.37 | E11: =Income!K11-Exps.!K11 -> 1193.3056 | F11: =Income!L11-Exps.!L11 -> 1226.36 | G11: 744.4 | H11: =678.96-155.19 -> 523.77 | I11: =752.69-27.74 -> 724.95 | J11: =D11-G11 -> 255.97 | K11: =E11-H11 -> 669.5356 | L11: =F11-I11 -> 501.41
B12: 6 | C12: Slice Small Finance Bank Ltd. (earlier North East SFB) | D12: =Income!J12-Exps.!J12 -> 17.06 | E12: =Income!K12-Exps.!K12 -> -47.48 | F12: =Income!L12-Exps.!L12 -> -77.97 | G12: 229.06 | H12: 105.18 | I12: 138.72 | J12: =D12-G12 -> -212 | K12: =E12-H12 -> -152.66 | L12: =F12-I12 -> -216.69
B13: 7 | C13: Suryoday Small Finance Bank Ltd. | D13: =Income!J13-Exps.!J13 -> 337.46 | E13: =Income!K13-Exps.!K13 -> 453.91 | F13: =Income!L13-Exps.!L13 -> 389.2 | G13: =236.6+23.16 -> 259.76 | H13: =166.34+71.61 -> 237.95 | I13: =245.37+28.86 -> 274.23 | J13: =D13-G13-1 -> 76.7 | K13: =E13-H13 -> 215.96 | L13: =F13-I13 -> 114.97
B14: 8 | C14: Ujjivan Small Finance Bank Ltd. | D14: =Income!J14-Exps.!J14 -> 1485.04 | E14: =Income!K14-Exps.!K14 -> 1917.11 | F14: =Income!L14-Exps.!L14 -> 1689.23 | G14: =17.8+367.32 -> 385.12 | H14: =214.94+420.67 -> 635.61 | I14: =747.66+215.47 -> 963.13 | J14: =D14-G14 -> 1099.92 | K14: =E14-H14 -> 1281.5 | L14: =F14-I14 -> 726.1
B15: 9 | C15: Utkarsh Small Finance Bank Ltd. | D15: =Income!J15-Exps.!J15 -> 838.32 | E15: =Income!K15-Exps.!K15 -> 997.28 | F15: =Income!L15-Exps.!L15 -> 1006.936 | G15: =302.5+131.31 -> 433.81 | H15: =337.88+161.76 -> 499.64 | I15: =979.28+3.9467 -> 983.2267 | J15: =D15-G15-1 -> 403.51 | K15: =E15-H15 -> 497.64 | L15: =F15-I15 -> 23.7093
B16: 10 | C16: Shivalik Small Finance Bank Ltd. | D16: 7 | E16: 18 | F16: =Income!L16-Exps.!L16 -> 20.91 | G16: 4.7755 | H16: 16.16 | I16: 19.97 | J16: =D16-G16 -> 2.2245 | K16: 2.4 | L16: =F16-I16 -> 0.94
B17: 11 | C17: Unity Small Finance Bank Ltd. | D17: =Income!J17-Exps.!J17 -> 151.8 | E17: =Income!K17-Exps.!K17 -> 417 | F17: =Income!L17-Exps.!L17 -> 727.97 | G17: =139.29-22.11 -> 117.18 | H17: -22 | I17: 245.94 | J17: =D17-G17 -> 34.62 | K17: =E17-H17 -> 439 | L17: =F17-I17 -> 482.03
C18: TOTAL OF SMALL FINANCE BANKS [I] | D18: =SUM(D6:D17) -> 8517.29 | E18: =SUM(E6:E17) -> 10818.052 | F18: =SUM(F6:F17) -> 11698.121 | G18: =SUM(G6:G17) -> 4353.5455 | H18: =SUM(H6:H17) -> 4598.4842 | I18: =SUM(I6:I17) -> 8202.4115 | J18: =SUM(J6:J17) -> 4162.7445 | K18: =SUM(K6:K17) -> 6220.1248 | L18: =SUM(L6:L17) -> 3495.7092
B20: 5

Sheet CDRatio
B2: Statement VI : Small Finance Banks : Ratios
B3: As on March 31 | D3: (In Per Cent)
B4: Sr. No. | C4: Banks | D4: Credit Deposit Ratio | G4: Investment Deposit Ratio | J4: Spread as % to Total Assets
D5: 2023 | E5: 2024 | F5: 2025 | G5: 2023 | H5: 2024 | I5: 2025 | J5: 2023 | K5: 2024 | L5: 2025
B6: 1 | C6: Au Small Finance Bank Ltd. | D6: =DEPO!J6/DEPO!D6*100 -> 84.223381 | E6: =DEPO!K6/DEPO!E6*100 -> 83.919338 | F6: =DEPO!L6/DEPO!F6*100 -> 86.178272 | G6: =DEPO!G6/DEPO!D6*100 -> 28.936788 | H6: =DEPO!H6/DEPO!E6*100 -> 31.122627 | I6: =DEPO!I6/DEPO!F6*100 -> 30.456236 | J6: =(Income!D6-Exps.!D6)/Assets!D6*100 -> 4.9052104 | K6: =(Income!E6-Exps.!E6)/Assets!E6*100 -> 4.7128647 | L6: =(Income!F6-Exps.!F6)/Assets!F6*100 -> 5.0755784
B7: 2 | C7: Capital Small Finance Bank Ltd. | D7: =DEPO!J7/DEPO!D7*100 -> 82.7466 | E7: =DEPO!K7/DEPO!E7*100 -> 81.236978 | F7: =DEPO!L7/DEPO!F7*100 -> 85.19441 | G7: =DEPO!G7/DEPO!D7*100 -> 22.689624 | H7: =DEPO!H7/DEPO!E7*100 -> 22.810502 | I7: =DEPO!I7/DEPO!F7*100 -> 21.861558 | J7: =(Income!D7-Exps.!D7)/Assets!D7*100 -> 4.0295241 | K7: =(Income!E7-Exps.!E7)/Assets!E7*100 -> 3.7131749 | L7: =(Income!F7-Exps.!F7)/Assets!F7*100 -> 4.0583685
B8: 3 | C8: Equitas Small Finance Bank Ltd. | D8: =DEPO!J8/DEPO!D8*100 -> 101.77553 | E8: =DEPO!K8/DEPO!E8*100 -> 85.704356 | F8: =DEPO!L8/DEPO!F8*100 -> 83.998245 | G8: =DEPO!G8/DEPO!D8*100 -> 26.291754 | H8: =DEPO!H8/DEPO!E8*100 -> 25.091261 | I8: =DEPO!I8/DEPO!F8*100 -> 21.548114 | J8: =(Income!D8-Exps.!D8)/Assets!D8*100 -> 7.2793377 | K8: =(Income!E8-Exps.!E8)/Assets!E8*100 -> 6.7980078 | L8: =(Income!F8-Exps.!F8)/Assets!F8*100 -> 6.1542088
B9: 4 | C9: ESAF Small Finance Bank Ltd. | D9: =DEPO!J9/DEPO!D9*100 -> 94.945325 | E9: =DEPO!K9/DEPO!E9*100 -> 92.07416 | F9: =DEPO!L9/DEPO!F9*100 -> 77.451148 | G9: =DEPO!G9/DEPO!D9*100 -> 33.333242 | H9: =DEPO!H9/DEPO!E9*100 -> 27.889449 | I9: =DEPO!I9/DEPO!F9*100 -> 25.756774 | J9: =(Income!D9-Exps.!D9)/Assets!D9*100 -> 9.0801566 | K9: =(Income!E9-Exps.!E9)/Assets!E9*100 -> 9.0838766 | L9: =(Income!F9-Exps.!F9)/Assets!F9*100 -> 7.5484146
B10: 5 | C10: Fincare Small Finance Bank Ltd. | D10: =DEPO!J10/DEPO!D10*100 -> 108.33081 | E10: =DEPO!K10/DEPO!E10*100 -> 117.45041 | F10: - | G10: =DEPO!G10/DEPO!D10*100 -> 31.405208 | H10: =DEPO!H10/DEPO!E10*100 -> 30.267067 | I10: - | J10: =(Income!D10-Exps.!D10)/Assets!D10*100 -> 8.746127 | K10: =(Income!E10-Exps.!E10)/Assets!E10*100 -> 9.5392887 | L10: -
B11: 6 | C11: Jana Small Finance Bank Ltd. | D11: =DEPO!J11/DEPO!D11*100 -> 108.72743 | E11: =DEPO!K11/DEPO!E11*100 -> 102.39251 | F11: =DEPO!L11/DEPO!F11*100 -> 93.254413 | G11: =DEPO!G11/DEPO!D11*100 -> 31.965309 | H11: =DEPO!H11/DEPO!E11*100 -> 29.850761 | I11: =DEPO!I11/DEPO!F11*100 -> 20.414234 | J11: =(Income!D11-Exps.!D11)/Assets!D11*100 -> 6.4734281 | K11: =(Income!E11-Exps.!E11)/Assets!E11*100 -> 6.50541 | L11: =(Income!F11-Exps.!F11)/Assets!F11*100 -> 6.2218013
B12: 7 | C12: Slice Small Finance Bank Ltd. (earlier North East SFB) | D12: =DEPO!J12/DEPO!D12*100 -> 78.604943 | E12: =DEPO!K12/DEPO!E12*100 -> 52.806386 | F12: =DEPO!L12/DEPO!F12*100 -> 120.11636 | G12: =DEPO!G12/DEPO!D12*100 -> 17.076136 | H12: =DEPO!H12/DEPO!E12*100 -> 36.206953 | I12: =DEPO!I12/DEPO!F12*100 -> 32.175671 | J12: =(Income!D12-Exps.!D12)/Assets!D12*100 -> 5.7688051 | K12: =(Income!E12-Exps.!E12)/Assets!E12*100 -> 4.2441671 | L12: =(Income!F12-Exps.!F12)/Assets!F12*100 -> 4.8199727
B13: 8 | C13: Suryoday Small Finance Bank Ltd. | D13: =DEPO!J13/DEPO!D13*100 -> 116.41912 | E13: =DEPO!K13/DEPO!E13*100 -> 103.8664 | F13: =DEPO!L13/DEPO!F13*100 -> 94.278995 | G13: =DEPO!G13/DEPO!D13*100 -> 49.745099 | H13: =DEPO!H13/DEPO!E13*100 -> 33.421753 | I13: =DEPO!I13/DEPO!F13*100 -> 29.655914 | J13: =(Income!D13-Exps.!D13)/Assets!D13*100 -> 7.5707671 | K13: =(Income!E13-Exps.!E13)/Assets!E13*100 -> 7.7739061 | L13: =(Income!F13-Exps.!F13)/Assets!F13*100 -> 7.0841064
B14: 9 | C14: Ujjivan Small Finance Bank Ltd. | D14: =DEPO!J14/DEPO!D14*100 -> 83.365678 | E14: =DEPO!K14/DEPO!E14*100 -> 85.444703 | F14: =DEPO!L14/DEPO!F14*100 -> 83.416422 | G14: =DEPO!G14/DEPO!D14*100 -> 33.324523 | H14: =DEPO!H14/DEPO!E14*100 -> 31.040329 | I14: =DEPO!I14/DEPO!F14*100 -> 31.171513 | J14: =(Income!D14-Exps.!D14)/Assets!D14*100 -> 8.097727 | K14: =(Income!E14-Exps.!E14)/Assets!E14*100 -> 8.4346184 | L14: =(Income!F14-Exps.!F14)/Assets!F14*100 -> 7.6249419
B15: 10 | C15: Utkarsh Small Finance Bank Ltd. | D15: =DEPO!J15/DEPO!D15*100 -> 95.321784 | E15: =DEPO!K15/DEPO!E15*100 -> 93.65985 | F15: =DEPO!L15/DEPO!F15*100 -> 86.788172 | G15: =DEPO!G15/DEPO!D15*100 -> 20.856242 | H15: =DEPO!H15/DEPO!E15*100 -> 21.058489 | I15: =DEPO!I15/DEPO!F15*100 -> 22.98968 | J15: =(Income!D15-Exps.!D15)/Assets!D15*100 -> 7.9980479 | K15: =(Income!E15-Exps.!E15)/Assets!E15*100 -> 7.8895347 | L15: =(Income!F15-Exps.!F15)/Assets!F15*100 -> 7.1917911
B16: 11 | C16: Shivalik Small Finance Bank Ltd. | D16: =DEPO!J16/DEPO!D16*100 -> 74.296559 | E16: =DEPO!K16/DEPO!E16*100 -> 86.957496 | F16: =DEPO!L16/DEPO!F16*100 -> 92.834666 | G16: =DEPO!G16/DEPO!D16*100 -> 28.156114 | H16: =DEPO!H16/DEPO!E16*100 -> 20.568462 | I16: =DEPO!I16/DEPO!F16*100 -> 20.073298 | J16: =(Income!D16-Exps.!D16)/Assets!D16*100 -> 4.320288 | K16: =(Income!E16-Exps.!E16)/Assets!E16*100 -> 4.4909725 | L16: =(Income!F16-Exps.!F16)/Assets!F16*100 -> 4.056547
B17: 12 | C17: Unity Small Finance Bank Ltd. | D17: =DEPO!J17/DEPO!D17*100 -> 166.43659 | E17: =DEPO!K17/DEPO!E17*100 -> 122.38278 | F17: =DEPO!L17/DEPO!F17*100 -> 91.911656 | G17: =DEPO!G17/DEPO!D17*100 -> 90.731649 | H17: =DEPO!H17/DEPO!E17*100 -> 58.800922 | I17: =DEPO!I17/DEPO!F17*100 -> 43.106069 | J17: =(Income!D17-Exps.!D17)/Assets!D17*100 -> 6.3893267 | K17: =(Income!E17-Exps.!E17)/Assets!E17*100 -> 7.1221141 | L17: =(Income!F17-Exps.!F17)/Assets!F17*100 -> 6.1972312
C18: TOTAL OF SMALL FINANCE BANKS [I] | D18: =DEPO!J18/DEPO!D18*100 -> 92.969258 | E18: =DEPO!K18/DEPO!E18*100 -> 90.136181 | F18: =DEPO!L18/DEPO!F18*100 -> 86.391727 | G18: =DEPO!G18/DEPO!D18*100 -> 30.372685 | H18: =DEPO!H18/DEPO!E18*100 -> 29.607165 | I18: =DEPO!I18/DEPO!F18*100 -> 27.674435 | J18: =(Income!D18-Exps.!D18)/Assets!D18*100 -> 6.6035601 | K18: =(Income!E18-Exps.!E18)/Assets!E18*100 -> 6.6132314 | L18: =(Income!F18-Exps.!F18)/Assets!F18*100 -> 6.0291628
B20: 6

Sheet CRAR
B2: Statement VII : Small Finance Banks : Ratios
B3: As on March 31 | D3: (In Per Cent)
B4: Sr. No. | C4: Banks | D4: Operating Exp. as % to Total Expenses | G4: Return on Assets [%] | J4: Capital Adequacy Ratio - Basel III [%] *
D5: 2023 | E5: 2024 | F5: 2025 | G5: 2023 | H5: 2024 | I5: 2025 | J5: 2023 | K5: 2024 | L5: 2025
B6: 1 | C6: Au Small Finance Bank Ltd. | D6: =Exps.!G6/Exps.!J6*100 -> 47.644637 | E6: =Exps.!H6/Exps.!K6*100 -> 44.841278 | F6: =Exps.!I6/Exps.!L6*100 -> 42.523113 | G6: 1.79 | H6: 1.54 | I6: 1.53 | J6: 23.59 | K6: 20.06 | L6: 20.06
B7: 2 | C7: Capital Small Finance Bank Ltd. | D7: =Exps.!G7/Exps.!J7*100 -> 38.620247 | E7: =Exps.!H7/Exps.!K7*100 -> 36.512558 | F7: =Exps.!I7/Exps.!L7*100 -> 38.41229 | G7: 1.22 | H7: 1.27 | I7: 1.35 | J7: 18.87 | K7: 27.39 | L7: 25.39
B8: 3 | C8: Equitas Small Finance Bank Ltd. | D8: =Exps.!G8/Exps.!J8*100 -> 55.760577 | E8: =Exps.!H8/Exps.!K8*100 -> 50.961997 | F8: =Exps.!I8/Exps.!L8*100 -> 48.036319 | G8: 1.82 | H8: 1.96 | I8: 0.3 | J8: 23.8 | K8: 21.7 | L8: 20.6
B9: 4 | C9: ESAF Small Finance Bank Ltd. | D9: =Exps.!G9/Exps.!J9*100 -> 54.742733 | E9: =Exps.!H9/Exps.!K9*100 -> 53.229962 | F9: =Exps.!I9/Exps.!L9*100 -> 51.249529 | G9: 1.63 | H9: 1.86 | I9: -1.94 | J9: 19.83 | K9: 23.27 | L9: 21.84
B10: 5 | C10: Fincare Small Finance Bank Ltd. | D10: =Exps.!G10/Exps.!J10*100 -> 57.212335 | E10: =Exps.!H10/Exps.!K10*100 -> 55.652713 | F10: - | G10: 0.95 | H10: 2.69 | I10: - | J10: 20.04 | K10: 24.53 | L10: -
B11: 5 | C11: Jana Small Finance Bank Ltd. | D11: =Exps.!G11/Exps.!J11*100 -> 47.583256 | E11: =Exps.!H11/Exps.!K11*100 -> 45.974139 | F11: =Exps.!I11/Exps.!L11*100 -> 45.609245 | G11: 1.13 | H11: 2.38 | I11: 1.49 | J11: 15.57 | K11: 20.31 | L11: 20.68
B12: 6 | C12: Slice Small Finance Bank Ltd. (earlier North East SFB) | D12: =Exps.!G12/Exps.!J12*100 -> 55.726458 | E12: =Exps.!H12/Exps.!K12*100 -> 58.422567 | F12: =Exps.!I12/Exps.!L12*100 -> 70.582971 | G12: -7.68 | H12: -6.28 | I12: -7.78 | J12: 5.5 | K12: 11.31 | L12: 20.3
B13: 7 | C13: Suryoday Small Finance Bank Ltd. | D13: =Exps.!G13/Exps.!J13*100 -> 53.67831 | E13: =Exps.!H13/Exps.!K13*100 -> 53.738056 | F13: =Exps.!I13/Exps.!L13*100 -> 52.429566 | G13: 0.87 | H13: 1.94 | I13: 0.84 | J13: 33.72 | K13: 28.41 | L13: 25.83
B14: 8 | C14: Ujjivan Small Finance Bank Ltd. | D14: =Exps.!G14/Exps.!J14*100 -> 55.123197 | E14: =Exps.!H14/Exps.!K14*100 -> 50.125363 | F14: =Exps.!I14/Exps.!L14*100 -> 50.681501 | G14: 4.04 | H14: 3.47 | I14: 1.67 | J14: 25.81 | K14: 24.69 | L14: 23.1
B15: 9 | C15: Utkarsh Small Finance Bank Ltd. | D15: =Exps.!G15/Exps.!J15*100 -> 50.357842 | E15: =Exps.!H15/Exps.!K15*100 -> 49.927754 | F15: =Exps.!I15/Exps.!L15*100 -> 48.119316 | G15: 2.45 | H15: 2.46 | I15: 0.09 | J15: 20.64 | K15: 22.57 | L15: 20.93
B16: 10 | C16: Shivalik Small Finance Bank Ltd. | D16: =Exps.!G16/Exps.!J16*100 -> 49.733126 | E16: =Exps.!H16/Exps.!K16*100 -> 50.257891 | F16: =Exps.!I16/Exps.!L16*100 -> 48.331965 | G16: 0.07 | H16: 0.09 | I16: 0.03 | J16: 23.46 | K16: 20.19 | L16: 20.95
B17: 11 | C17: Unity Small Finance Bank Ltd. | D17: =Exps.!G17/Exps.!J17*100 -> 73.153137 | E17: =Exps.!H17/Exps.!K17*100 -> 66.502058 | F17: =Exps.!I17/Exps.!L17*100 -> 58.196783 | G17: 0.43 | H17: 4 | I17: 2.88 | J17: 49.4 | K17: 36.46 | L17: 28.75
C18: TOTAL OF SMALL FINANCE BANKS [I] | D18: =Exps.!G18/Exps.!J18*100 -> 51.993882 | E18: =Exps.!H18/Exps.!K18*100 -> 49.472818 | F18: =Exps.!I18/Exps.!L18*100 -> 47.476099
B20: * Capital Adequacy Ratio (CRAR) as mandated by RBI to Small Finance Banks (SFBs) is minimum 15 per cent.
B22: 7

Sheet NetNPAtoNetAdv
B2: Statement VIII : Small Finance Banks : Ratios
B3: As on March 31 | D3: (In Per Cent) | G3: (₹ Crore) | J3: (₹ Lacs)
B4: Sr. No. | C4: Banks | D4: Net NPA as % to Net Advances | G4: Business Per Employee | J4: Profit Per Employee
D5: 2023 | E5: 2024 | F5: 2025 | G5: 2023 | H5: 2024 | I5: 2025 | J5: 2023 | K5: 2024 | L5: 2025
B6: 1 | C6: Au Small Finance Bank Ltd. | D6: =Assets!J6/DEPO!J6*100 -> 0.41963769 | E6: 0.55 | F6: =Assets!L6/DEPO!L6*100 -> 0.73893144 | G6: 3.68 | H6: 4.65 | I6: 4.02 | J6: 5 | K6: 5.33 | L6: 4.39
B7: 2 | C7: Capital Small Finance Bank Ltd. | D7: =Assets!J7/DEPO!J7*100 -> 1.3640492 | E7: 1.4 | F7: =Assets!L7/DEPO!L7*100 -> 1.2952743 | G7: 6.99 | H7: 7.4 | I7: 7.88 | J7: 5.42 | K7: 6.05 | L7: 6.69
B8: 3 | C8: Equitas Small Finance Bank Ltd. | D8: =Assets!J8/DEPO!J8*100 -> 1.2094091 | E8: 1.17 | F8: =Assets!L8/DEPO!L8*100 -> 0.9781996 | G8: 2.45 | H8: 2.8 | I8: 3.03 | J8: 3 | K8: 3.7 | L8: 0.6
B9: 4 | C9: ESAF Small Finance Bank Ltd. | D9: 1.13 | E9: 2.26 | F9: =Assets!L9/DEPO!L9*100 -> 2.9933653 | G9: 5.44 | H9: 6.16 | I9: 3.2 | J9: 6 | K9: 7.13 | L9: -4.16
B10: 5 | C10: Fincare Small Finance Bank Ltd. | D10: =Assets!J10/DEPO!J10*100 -> 1.2987192 | E10: 0.63 | F10: - | G10: 0.97 | H10: 1.17 | I10: - | J10: 0.82 | K10: 2.76 | L10: -
B11: 6 | C11: Jana Small Finance Bank Ltd. | D11: =Assets!J11/DEPO!J11*100 -> 2.6352004 | E11: 0.56 | F11: =Assets!L11/DEPO!L11*100 -> 0.93603575 | G11: 1.85 | H11: 2.17 | I11: 2.31 | J11: 1.56 | K11: 3.07 | L11: 1.97
B12: 7 | C12: Slice Small Finance Bank Ltd. (earlier North East SFB) | D12: 1.71 | E12: 8.36 | F12: =Assets!L12/DEPO!L12*100 -> 4.6676788 | G12: 1.98 | H12: 1.14 | I12: 1.95 | J12: -9.79 | K12: -7.36 | L12: -8.27
B13: 8 | C13: Suryoday Small Finance Bank Ltd. | D13: =Assets!J13/DEPO!J13*100 -> 1.5456231 | E13: 0.86 | F13: =Assets!L13/DEPO!L13*100 -> 4.5819527 | G13: 1.98 | H13: 2.28 | I13: 2.55 | J13: 1.37 | K13: 3.11 | L13: 0.01
B14: 9 | C14: Ujjivan Small Finance Bank Ltd. # | D14: =Assets!J14/DEPO!J14*100 -> 0.042461928 | E14: 0.28 | F14: =Assets!L14/DEPO!L14*100 -> 0.48560051 | G14: 2.39 | H14: 2.5989 | I14: 2.4275 | J14: 6.33 | K14: 6.34 | L14: 3.09
B15: 10 | C15: Utkarsh Small Finance Bank Ltd. | D15: =Assets!J15/DEPO!J15*100 -> 0.3864945 | E15: 0.03 | F15: =Assets!L15/DEPO!L15*100 -> 4.8367546 | G15: 1.67 | H15: 1.83 | I15: 1.91 | J15: 2.87 | K15: 3.07 | L15: 0.13
B16: 11 | C16: Shivalik Small Finance Bank Ltd. | D16: =Assets!J16/DEPO!J16*100 -> 1.1581887 | E16: 0.84 | F16: =Assets!L16/DEPO!L16*100 -> 1.5077561 | G16: 5.01 | H16: 5.97 | I16: 6.82 | J16: 0.24 | K16: 0.34 | L16: 0.11
B17: 12 | C17: Unity Small Finance Bank Ltd. | D17: =Assets!J17/DEPO!J17*100 -> 0.34264434 | E17: 0.63 | F17: =Assets!L17/DEPO!L17*100 -> 1.5418045 | G17: 2.43 | H17: 3.11 | I17: 4.67 | J17: 0.01 | K17: 0.09 | L17: 0.1
C18: TOTAL OF SMALL FINANCE BANKS [I] | D18: =Assets!J18/DEPO!J18*100 -> 0.8890001 | E18: =Assets!K18/DEPO!K18*100 -> 0.77582648 | F18: =Assets!L18/DEPO!L18*100 -> 1.4295062
B20: # Total Business is considered as Deposits + Gross Advances for claculating business per employee ratio.
B22: 8
